Componets/MIPI-CSI-Transciever/Cam_I2C/Cam_I2C.v
module Cam_I2C(input clk200kHz, clk400kHz,clk1_6MHz,reset,send_data,input[7:0] datain,input[15:0] register_in,input[6:0] slave_addr,input ackn,inout scl,inout  sda);
	localparam reg[7:0] idle=0;
	localparam reg[7:0] start=1;
	localparam reg[7:0] send=2;
	localparam reg[7:0] reg0=3;
	localparam reg[7:0] reg1=4;
	localparam reg[7:0] data=5;
	localparam reg[7:0] stop=6;
	
	
	reg[7:0] state=idle;
	reg send_data_old=0;
	reg rising_edge=0;
	integer counter =0;
	reg sda0=1;
	assign sda=sda0;
	reg sending=0;
	reg[36:0] i2cdata={slave_addr,1'b0,1'b1,register_in[15:8],1'b1,register_in[7:0],1'b1,datain,1'b1,1'b0};
	reg [36:0] i2cin=0;
	always @(posedge clk400kHz) begin
		if (reset==1) begin
			state<=0;		
			sda0<=1;
			counter=0;
		end else begin
			//sda=1;
			send_data_old<=send_data;
			rising_edge=(send_data==1&&send_data_old==0)?1:0;			
			case (state)
				idle: begin
				sda0<=1;
				sending=0;
				if(rising_edge==1) begin
					state<=start;
					counter=0;
					sda0<=0;
					//sending=1;
				end
				end	
				start: begin
					sending=(counter>=36)?0:1;
					sda0<=(counter>=36)?0:i2cdata[36-counter];				
					counter=(counter>=36)?0:counter+1;
					state<=(counter>=36)?stop:start;		
					
				end
				stop: begin
					state<=idle;
					sda0<=0;
				end
				default: begin
				end
			endcase
		end
	end
	reg [7:0]clkcount=0;
	reg clkdelay0;
	reg clkdelay1;	
	reg scl0,scl1,scl2;	
	assign scl=scl0;	
	always @(posedge clk1_6MHz) begin
		clkcount=clkcount+1;			
		scl0<=sending?~clkcount[1]:1;
		scl1<=scl0;
		//scl2<=scl1;		
	end
	//ODDRX2F ddr1(.D0(0),.D1(1),.D2(1),.D3(0),.ECLK(clk400kHz),.SCLK(clk200kHz),.Q(scl));
  
	
endmodule

Componets/MIPI-CSI-Transciever/Cam_I2C/blinky.vcd
$version Generated by VerilatedVcd $end
$date Fri Dec  2 14:18:12 2022
 $end
$timescale   1ps $end

 $scope module TOP $end
  $var wire  1 1 ackn $end
  $var wire  1 + clk1_6MHz $end
  $var wire  1 ) clk200kHz $end
  $var wire  1 * clk400kHz $end
  $var wire  8 . datain [7:0] $end
  $var wire 16 / register_in [15:0] $end
  $var wire  1 , reset $end
  $var wire  1 2 scl $end
  $var wire  1 3 sda $end
  $var wire  1 - send_data $end
  $var wire  7 0 slave_addr [6:0] $end
  $scope module Cam_I2C $end
   $var wire  1 1 ackn $end
   $var wire  1 + clk1_6MHz $end
   $var wire  1 ) clk200kHz $end
   $var wire  1 * clk400kHz $end
   $var wire  8 # clkcount [7:0] $end
   $var wire  1 B clkdelay0 $end
   $var wire  1 C clkdelay1 $end
   $var wire 32 ( counter [31:0] $end
   $var wire  8 > data [7:0] $end
   $var wire  8 . datain [7:0] $end
   $var wire 37 7 i2cdata [36:0] $end
   $var wire 37 @ i2cin [36:0] $end
   $var wire  8 9 idle [7:0] $end
   $var wire  8 < reg0 [7:0] $end
   $var wire  8 = reg1 [7:0] $end
   $var wire 16 / register_in [15:0] $end
   $var wire  1 , reset $end
   $var wire  1 ' rising_edge $end
   $var wire  1 2 scl $end
   $var wire  1 $ scl0 $end
   $var wire  1 % scl1 $end
   $var wire  1 D scl2 $end
   $var wire  1 3 sda $end
   $var wire  1 5 sda0 $end
   $var wire  8 ; send [7:0] $end
   $var wire  1 - send_data $end
   $var wire  1 & send_data_old $end
   $var wire  1 6 sending $end
   $var wire  7 0 slave_addr [6:0] $end
   $var wire  8 : start [7:0] $end
   $var wire  8 4 state [7:0] $end
   $var wire  8 ? stop [7:0] $end
  $upscope $end
 $upscope $end
$enddefinitions $end


#10
b00000001 #
1$
0%
0&
0'
b00000000000000000000000000000000 (
0)
1*
1+
0,
0-
b10101011 .
b1010101010101010 /
b0010000 0
01
02
13
b00000000 4
15
06
b0010000011010101011010101011010101110 7
b00000000 9
b00000001 :
b00000010 ;
b00000011 <
b00000100 =
b00000101 >
b00000110 ?
b0000000000000000000000000000000000000 @
0B
0C
0D
#15
0+
#20
b00000010 #
1%
1+
12
#25
0+
#30
b00000011 #
0*
1+
#35
0+
#40
b00000100 #
1+
#45
0+
#50
b00000101 #
1*
1+
#55
0+
#60
b00000110 #
1+
#65
0+
#70
b00000111 #
0*
1+
#75
0+
#80
b00001000 #
1+
#85
0+
#90
b00001001 #
1*
1+
#95
0+
#100
b00001010 #
1+
#105
0+
#110
b00001011 #
0*
1+
11
#115
0+
#120
b00001100 #
1+
1-
#125
0+
#130
b00001101 #
1&
1'
1*
1+
03
b00000001 4
05
#135
0+
#140
b00001110 #
0$
1+
#145
0+
#150
b00001111 #
0%
0*
1+
02
#155
0+
#160
b00010000 #
1+
#165
0+
#170
b00010001 #
0'
b00000000000000000000000000000001 (
1*
1+
16
#175
0+
#180
b00010010 #
1$
1+
#185
0+
#190
b00010011 #
1%
0*
1+
12
#195
0+
#200
b00010100 #
0$
1+
#205
0+
#210
b00010101 #
0%
b00000000000000000000000000000010 (
1*
1+
02
#215
0+
#220
b00010110 #
1$
1+
#225
0+
#230
b00010111 #
1%
0*
1+
12
#235
0+
#240
b00011000 #
0$
1+
#245
0+
#250
b00011001 #
0%
b00000000000000000000000000000011 (
1*
1+
02
13
15
#255
0+
#260
b00011010 #
1$
1+
#265
0+
#270
b00011011 #
1%
0*
1+
12
#275
0+
#280
b00011100 #
0$
1+
#285
0+
#290
b00011101 #
0%
b00000000000000000000000000000100 (
1*
1+
02
03
05
#295
0+
#300
b00011110 #
1$
1+
#305
0+
#310
b00011111 #
1%
0*
1+
12
#315
0+
#320
b00100000 #
0$
1+
#325
0+
#330
b00100001 #
0%
b00000000000000000000000000000101 (
1*
1+
02
#335
0+
#340
b00100010 #
1$
1+
#345
0+
#350
b00100011 #
1%
0*
1+
12
#355
0+
#360
b00100100 #
0$
1+
#365
0+
#370
b00100101 #
0%
b00000000000000000000000000000110 (
1*
1+
02
#375
0+
#380
b00100110 #
1$
1+
#385
0+
#390
b00100111 #
1%
0*
1+
12
#395
0+
#400
b00101000 #
0$
1+
#405
0+
#410
b00101001 #
0%
b00000000000000000000000000000111 (
1*
1+
02
#415
0+
#420
b00101010 #
1$
1+
#425
0+
#430
b00101011 #
1%
0*
1+
12
#435
0+
#440
b00101100 #
0$
1+
#445
0+
#450
b00101101 #
0%
b00000000000000000000000000001000 (
1*
1+
02
#455
0+
#460
b00101110 #
1$
1+
#465
0+
#470
b00101111 #
1%
0*
1+
12
#475
0+
#480
b00110000 #
0$
1+
#485
0+
#490
b00110001 #
0%
b00000000000000000000000000001001 (
1*
1+
02
13
15
#495
0+
#500
b00110010 #
1$
1+
#505
0+
#510
b00110011 #
1%
0*
1+
12
#515
0+
#520
b00110100 #
0$
1+
#525
0+
#530
b00110101 #
0%
b00000000000000000000000000001010 (
1*
1+
02
#535
0+
#540
b00110110 #
1$
1+
#545
0+
#550
b00110111 #
1%
0*
1+
12
#555
0+
#560
b00111000 #
0$
1+
#565
0+
#570
b00111001 #
0%
b00000000000000000000000000001011 (
1*
1+
02
03
05
#575
0+
#580
b00111010 #
1$
1+
#585
0+
#590
b00111011 #
1%
0*
1+
12
#595
0+
#600
b00111100 #
0$
1+
#605
0+
#610
b00111101 #
0%
b00000000000000000000000000001100 (
1*
1+
02
13
15
#615
0+
#620
b00111110 #
1$
1+
#625
0+
#630
b00111111 #
1%
0*
1+
12
#635
0+
#640
b01000000 #
0$
1+
#645
0+
#650
b01000001 #
0%
b00000000000000000000000000001101 (
1*
1+
02
03
05
#655
0+
#660
b01000010 #
1$
1+
#665
0+
#670
b01000011 #
1%
0*
1+
12
#675
0+
#680
b01000100 #
0$
1+
#685
0+
#690
b01000101 #
0%
b00000000000000000000000000001110 (
1*
1+
02
13
15
#695
0+
#700
b01000110 #
1$
1+
#705
0+
#710
b01000111 #
1%
0*
1+
12
#715
0+
#720
b01001000 #
0$
1+
#725
0+
#730
b01001001 #
0%
b00000000000000000000000000001111 (
1*
1+
02
03
05
#735
0+
#740
b01001010 #
1$
1+
#745
0+
#750
b01001011 #
1%
0*
1+
12
#755
0+
#760
b01001100 #
0$
1+
#765
0+
#770
b01001101 #
0%
b00000000000000000000000000010000 (
1*
1+
02
13
15
#775
0+
#780
b01001110 #
1$
1+
#785
0+
#790
b01001111 #
1%
0*
1+
12
#795
0+
#800
b01010000 #
0$
1+
#805
0+
#810
b01010001 #
0%
b00000000000000000000000000010001 (
1*
1+
02
03
05
#815
0+
#820
b01010010 #
1$
1+
#825
0+
#830
b01010011 #
1%
0*
1+
12
#835
0+
#840
b01010100 #
0$
1+
#845
0+
#850
b01010101 #
0%
b00000000000000000000000000010010 (
1*
1+
02
13
15
#855
0+
#860
b01010110 #
1$
1+
#865
0+
#870
b01010111 #
1%
0*
1+
12
b00000000 4
06
#875
0+
#880
b01011000 #
1+
#885
0+
#890
b01011001 #
1*
1+
#895
0+
#900
b01011010 #
1+
#905
0+
#910
b01011011 #
0*
1+
#915
0+
#920
b01011100 #
1+
#925
0+
#930
b01011101 #
1*
1+
#935
0+
#940
b01011110 #
1+
#945
0+
#950
b01011111 #
0*
1+
#955
0+
#960
b01100000 #
1+
#965
0+
#970
b01100001 #
1*
1+
#975
0+
#980
b01100010 #
1+
#985
0+
#990
b01100011 #
0*
1+
#995
0+
#1000
b01100100 #
1+
#1005
0+
#1010
b01100101 #
1*
1+
#1015
0+
#1020
b01100110 #
1+
#1025
0+
#1030
b01100111 #
0*
1+
#1035
0+
#1040
b01101000 #
1+
#1045
0+
#1050
b01101001 #
1*
1+
#1055
0+
#1060
b01101010 #
1+
#1065
0+
#1070
b01101011 #
0*
1+
#1075
0+
#1080
b01101100 #
1+
#1085
0+
#1090
b01101101 #
1*
1+
#1095
0+
#1100
b01101110 #
1+
#1105
0+
#1110
b01101111 #
0*
1+
#1115
0+
#1120
b01110000 #
1+
#1125
0+
#1130
b01110001 #
1*
1+
#1135
0+
#1140
b01110010 #
1+
#1145
0+
#1150
b01110011 #
0*
1+
#1155
0+
#1160
b01110100 #
1+
#1165
0+
#1170
b01110101 #
1*
1+
#1175
0+
#1180
b01110110 #
1+
#1185
0+
#1190
b01110111 #
0*
1+
#1195
0+
#1200
b01111000 #
1+
#1205
0+
#1210
b01111001 #
1*
1+
#1215
0+
#1220
b01111010 #
1+
#1225
0+
#1230
b01111011 #
0*
1+
#1235
0+
#1240
b01111100 #
1+
#1245
0+
#1250
b01111101 #
1*
1+
#1255
0+
#1260
b01111110 #
1+
#1265
0+
#1270
b01111111 #
0*
1+
#1275
0+
#1280
b10000000 #
1+
#1285
0+
#1290
b10000001 #
1*
1+
#1295
0+
#1300
b10000010 #
1+
#1305
0+
#1310
b10000011 #
0*
1+
#1315
0+
#1320
b10000100 #
1+
#1325
0+
#1330
b10000101 #
1*
1+
#1335
0+
#1340
b10000110 #
1+
#1345
0+
#1350
b10000111 #
0*
1+
#1355
0+
#1360
b10001000 #
1+
#1365
0+
#1370
b10001001 #
1*
1+
#1375
0+
#1380
b10001010 #
1+
#1385
0+
#1390
b10001011 #
0*
1+
#1395
0+
#1400
b10001100 #
1+
#1405
0+
#1410
b10001101 #
1*
1+
#1415
0+
#1420
b10001110 #
1+
#1425
0+
#1430
b10001111 #
0*
1+
#1435
0+
#1440
b10010000 #
1+
#1445
0+
#1450
b10010001 #
1*
1+
#1455
0+
#1460
b10010010 #
1+
#1465
0+
#1470
b10010011 #
0*
1+
#1475
0+
#1480
b10010100 #
1+
#1485
0+
#1490
b10010101 #
1*
1+
#1495
0+
#1500
b10010110 #
1+
#1505
0+
#1510
b10010111 #
0*
1+
#1515
0+
#1520
b10011000 #
1+
#1525
0+
#1530
b10011001 #
1*
1+
#1535
0+
#1540
b10011010 #
1+
#1545
0+
#1550
b10011011 #
0*
1+
#1555
0+
#1560
b10011100 #
1+
#1565
0+
#1570
b10011101 #
1*
1+
#1575
0+
#1580
b10011110 #
1+
#1585
0+
#1590
b10011111 #
0*
1+
#1595
0+
#1600
b10100000 #
1+
#1605
0+
#1610
b10100001 #
1*
1+
#1615
0+
#1620
b10100010 #
1+
#1625
0+
#1630
b10100011 #
0*
1+
#1635
0+
#1640
b10100100 #
1+
#1645
0+
#1650
b10100101 #
1*
1+
#1655
0+
#1660
b10100110 #
1+
#1665
0+
#1670
b10100111 #
0*
1+
#1675
0+
#1680
b10101000 #
1+
#1685
0+
#1690
b10101001 #
1*
1+
#1695
0+
#1700
b10101010 #
1+
#1705
0+
#1710
b10101011 #
0*
1+
#1715
0+
#1720
b10101100 #
1+
#1725
0+
#1730
b10101101 #
1*
1+
#1735
0+
#1740
b10101110 #
1+
#1745
0+
#1750
b10101111 #
0*
1+
#1755
0+
#1760
b10110000 #
1+
#1765
0+
#1770
b10110001 #
1*
1+
#1775
0+
#1780
b10110010 #
1+
#1785
0+
#1790
b10110011 #
0*
1+
#1795
0+
#1800
b10110100 #
1+
#1805
0+
#1810
b10110101 #
1*
1+
#1815
0+
#1820
b10110110 #
1+
#1825
0+
#1830
b10110111 #
0*
1+
#1835
0+
#1840
b10111000 #
1+
#1845
0+
#1850
b10111001 #
1*
1+
#1855
0+
#1860
b10111010 #
1+
#1865
0+
#1870
b10111011 #
0*
1+
#1875
0+
#1880
b10111100 #
1+
#1885
0+
#1890
b10111101 #
1*
1+
#1895
0+
#1900
b10111110 #
1+
#1905
0+
#1910
b10111111 #
0*
1+
#1915
0+
#1920
b11000000 #
1+
#1925
0+
#1930
b11000001 #
1*
1+
#1935
0+
#1940
b11000010 #
1+
#1945
0+
#1950
b11000011 #
0*
1+
#1955
0+
#1960
b11000100 #
1+
#1965
0+
#1970
b11000101 #
1*
1+
#1975
0+
#1980
b11000110 #
1+
#1985
0+
#1990
b11000111 #
0*
1+
#1995
0+
#2000
b11001000 #
1+
#2005
0+
#2010
b11001001 #
1*
1+
#2015
0+
#2020
b11001010 #
1+
#2025
0+
#2030
b11001011 #
0*
1+
#2035
0+
#2040
b11001100 #
1+
#2045
0+
#2050
b11001101 #
1*
1+
#2055
0+
#2060
b11001110 #
1+
#2065
0+
#2070
b11001111 #
0*
1+
#2075
0+
#2080
b11010000 #
1+
#2085
0+
#2090
b11010001 #
1*
1+
#2095
0+
#2100
b11010010 #
1+
#2105
0+
#2110
b11010011 #
0*
1+
#2115
0+
#2120
b11010100 #
1+
#2125
0+
#2130
b11010101 #
1*
1+
#2135
0+
#2140
b11010110 #
1+
#2145
0+
#2150
b11010111 #
0*
1+
#2155
0+
#2160
b11011000 #
1+
#2165
0+
#2170
b11011001 #
1*
1+
#2175
0+
#2180
b11011010 #
1+
#2185
0+
#2190
b11011011 #
0*
1+
#2195
0+
#2200
b11011100 #
1+
#2205
0+
#2210
b11011101 #
1*
1+
#2215
0+
#2220
b11011110 #
1+
#2225
0+
#2230
b11011111 #
0*
1+
#2235
0+
#2240
b11100000 #
1+
#2245
0+
#2250
b11100001 #
1*
1+
#2255
0+
#2260
b11100010 #
1+
#2265
0+
#2270
b11100011 #
0*
1+
#2275
0+
#2280
b11100100 #
1+
#2285
0+
#2290
b11100101 #
1*
1+
#2295
0+
#2300
b11100110 #
1+
#2305
0+
#2310
b11100111 #
0*
1+
#2315
0+
#2320
b11101000 #
1+
#2325
0+
#2330
b11101001 #
1*
1+
#2335
0+
#2340
b11101010 #
1+
#2345
0+
#2350
b11101011 #
0*
1+
#2355
0+
#2360
b11101100 #
1+
#2365
0+
#2370
b11101101 #
1*
1+
#2375
0+
#2380
b11101110 #
1+
#2385
0+
#2390
b11101111 #
0*
1+
#2395
0+
#2400
b11110000 #
1+
#2405
0+
#2410
b11110001 #
1*
1+
#2415
0+
#2420
b11110010 #
1+
#2425
0+
#2430
b11110011 #
0*
1+
#2435
0+
#2440
b11110100 #
1+
#2445
0+
#2450
b11110101 #
1*
1+
#2455
0+
#2460
b11110110 #
1+
#2465
0+
#2470
b11110111 #
0*
1+
#2475
0+
#2480
b11111000 #
1+
#2485
0+
#2490
b11111001 #
1*
1+
#2495
0+
#2500
b11111010 #
1+
#2505
0+
#2510
b11111011 #
0*
1+
#2515
0+
#2520
b11111100 #
1+
#2525
0+
#2530
b11111101 #
1*
1+
#2535
0+
#2540
b11111110 #
1+
#2545
0+
#2550
b11111111 #
0*
1+
#2555
0+
#2560
b00000000 #
1+
#2565
0+
#2570
b00000001 #
1*
1+
#2575
0+
#2580
b00000010 #
1+
#2585
0+
#2590
b00000011 #
0*
1+
#2595
0+
#2600
b00000100 #
1+
#2605
0+
#2610
b00000101 #
1*
1+
#2615
0+
#2620
b00000110 #
1+
#2625
0+
#2630
b00000111 #
0*
1+
#2635
0+
#2640
b00001000 #
1+
#2645
0+
#2650
b00001001 #
1*
1+
#2655
0+
#2660
b00001010 #
1+
#2665
0+
#2670
b00001011 #
0*
1+
#2675
0+
#2680
b00001100 #
1+
#2685
0+
#2690
b00001101 #
1*
1+
#2695
0+
#2700
b00001110 #
1+
#2705
0+
#2710
b00001111 #
0*
1+
#2715
0+
#2720
b00010000 #
1+
#2725
0+
#2730
b00010001 #
1*
1+
#2735
0+
#2740
b00010010 #
1+
#2745
0+
#2750
b00010011 #
0*
1+
#2755
0+
#2760
b00010100 #
1+
#2765
0+
#2770
b00010101 #
1*
1+
#2775
0+
#2780
b00010110 #
1+
#2785
0+
#2790
b00010111 #
0*
1+
#2795
0+
#2800
b00011000 #
1+
#2805
0+
#2810
b00011001 #
1*
1+
#2815
0+
#2820
b00011010 #
1+
#2825
0+
#2830
b00011011 #
0*
1+
#2835
0+
#2840
b00011100 #
1+
#2845
0+
#2850
b00011101 #
1*
1+
#2855
0+
#2860
b00011110 #
1+
#2865
0+
#2870
b00011111 #
0*
1+
#2875
0+
#2880
b00100000 #
1+
#2885
0+
#2890
b00100001 #
1*
1+
#2895
0+
#2900
b00100010 #
1+
#2905
0+
#2910
b00100011 #
0*
1+
#2915
0+
#2920
b00100100 #
1+
#2925
0+
#2930
b00100101 #
1*
1+
#2935
0+
#2940
b00100110 #
1+
#2945
0+
#2950
b00100111 #
0*
1+
#2955
0+
#2960
b00101000 #
1+
#2965
0+
#2970
b00101001 #
1*
1+
#2975
0+
#2980
b00101010 #
1+
#2985
0+
#2990
b00101011 #
0*
1+
#2995
0+
#3000
b00101100 #
1+
#3005
0+
#3010
b00101101 #
1*
1+
#3015
0+
#3020
b00101110 #
1+
#3025
0+
#3030
b00101111 #
0*
1+
#3035
0+
#3040
b00110000 #
1+
#3045
0+
#3050
b00110001 #
1*
1+
#3055
0+
#3060
b00110010 #
1+
#3065
0+
#3070
b00110011 #
0*
1+
#3075
0+
#3080
b00110100 #
1+
#3085
0+
#3090
b00110101 #
1*
1+
#3095
0+
#3100
b00110110 #
1+
#3105
0+
#3110
b00110111 #
0*
1+
#3115
0+
#3120
b00111000 #
1+
#3125
0+
#3130
b00111001 #
1*
1+
#3135
0+
#3140
b00111010 #
1+
#3145
0+
#3150
b00111011 #
0*
1+
#3155
0+
#3160
b00111100 #
1+
#3165
0+
#3170
b00111101 #
1*
1+
#3175
0+
#3180
b00111110 #
1+
#3185
0+
#3190
b00111111 #
0*
1+
#3195
0+
#3200
b01000000 #
1+
#3205
0+
#3210
b01000001 #
1*
1+
#3215
0+
#3220
b01000010 #
1+
#3225
0+
#3230
b01000011 #
0*
1+
#3235
0+
#3240
b01000100 #
1+
#3245
0+
#3250
b01000101 #
1*
1+
#3255
0+
#3260
b01000110 #
1+
#3265
0+
#3270
b01000111 #
0*
1+
#3275
0+
#3280
b01001000 #
1+
#3285
0+
#3290
b01001001 #
1*
1+
#3295
0+
#3300
b01001010 #
1+
#3305
0+
#3310
b01001011 #
0*
1+
#3315
0+
#3320
b01001100 #
1+
#3325
0+
#3330
b01001101 #
1*
1+
#3335
0+
#3340
b01001110 #
1+
#3345
0+
#3350
b01001111 #
0*
1+
#3355
0+
#3360
b01010000 #
1+
#3365
0+
#3370
b01010001 #
1*
1+
#3375
0+
#3380
b01010010 #
1+
#3385
0+
#3390
b01010011 #
0*
1+
#3395
0+
#3400
b01010100 #
1+
#3405
0+
#3410
b01010101 #
1*
1+
#3415
0+
#3420
b01010110 #
1+
#3425
0+
#3430
b01010111 #
0*
1+
#3435
0+
#3440
b01011000 #
1+
#3445
0+
#3450
b01011001 #
1*
1+
#3455
0+
#3460
b01011010 #
1+
#3465
0+
#3470
b01011011 #
0*
1+
#3475
0+
#3480
b01011100 #
1+
#3485
0+
#3490
b01011101 #
1*
1+
#3495
0+
#3500
b01011110 #
1+
#3505
0+
#3510
b01011111 #
0*
1+
#3515
0+
#3520
b01100000 #
1+
#3525
0+
#3530
b01100001 #
1*
1+
#3535
0+
#3540
b01100010 #
1+
#3545
0+
#3550
b01100011 #
0*
1+
#3555
0+
#3560
b01100100 #
1+
#3565
0+
#3570
b01100101 #
1*
1+
#3575
0+
#3580
b01100110 #
1+
#3585
0+
#3590
b01100111 #
0*
1+
#3595
0+
#3600
b01101000 #
1+
#3605
0+
#3610
b01101001 #
1*
1+
#3615
0+
#3620
b01101010 #
1+
#3625
0+
#3630
b01101011 #
0*
1+
#3635
0+
#3640
b01101100 #
1+
#3645
0+
#3650
b01101101 #
1*
1+
#3655
0+
#3660
b01101110 #
1+
#3665
0+
#3670
b01101111 #
0*
1+
#3675
0+
#3680
b01110000 #
1+
#3685
0+
#3690
b01110001 #
1*
1+
#3695
0+
#3700
b01110010 #
1+
#3705
0+
#3710
b01110011 #
0*
1+
#3715
0+
#3720
b01110100 #
1+
#3725
0+
#3730
b01110101 #
1*
1+
#3735
0+
#3740
b01110110 #
1+
#3745
0+
#3750
b01110111 #
0*
1+
#3755
0+
#3760
b01111000 #
1+
#3765
0+
#3770
b01111001 #
1*
1+
#3775
0+
#3780
b01111010 #
1+
#3785
0+
#3790
b01111011 #
0*
1+
#3795
0+
#3800
b01111100 #
1+
#3805
0+
#3810
b01111101 #
1*
1+
#3815
0+
#3820
b01111110 #
1+
#3825
0+
#3830
b01111111 #
0*
1+
#3835
0+
#3840
b10000000 #
1+
#3845
0+
#3850
b10000001 #
1*
1+
#3855
0+
#3860
b10000010 #
1+
#3865
0+
#3870
b10000011 #
0*
1+
#3875
0+
#3880
b10000100 #
1+
#3885
0+
#3890
b10000101 #
1*
1+
#3895
0+
#3900
b10000110 #
1+
#3905
0+
#3910
b10000111 #
0*
1+
#3915
0+
#3920
b10001000 #
1+
#3925
0+
#3930
b10001001 #
1*
1+
#3935
0+
#3940
b10001010 #
1+
#3945
0+
#3950
b10001011 #
0*
1+
#3955
0+
#3960
b10001100 #
1+
#3965
0+
#3970
b10001101 #
1*
1+
#3975
0+
#3980
b10001110 #
1+
#3985
0+
#3990
b10001111 #
0*
1+
#3995
0+
#4000
b10010000 #
1+
#4005
0+
#4010
b10010001 #
1*
1+
#4015
0+
#4020
b10010010 #
1+
#4025
0+
#4030
b10010011 #
0*
1+
#4035
0+
#4040
b10010100 #
1+
#4045
0+
#4050
b10010101 #
1*
1+
#4055
0+
#4060
b10010110 #
1+
#4065
0+
#4070
b10010111 #
0*
1+
#4075
0+
#4080
b10011000 #
1+
#4085
0+
#4090
b10011001 #
1*
1+
#4095
0+
#4100
b10011010 #
1+
#4105
0+
#4110
b10011011 #
0*
1+
#4115
0+
#4120
b10011100 #
1+
#4125
0+
#4130
b10011101 #
1*
1+
#4135
0+
#4140
b10011110 #
1+
#4145
0+
#4150
b10011111 #
0*
1+
#4155
0+
#4160
b10100000 #
1+
#4165
0+
#4170
b10100001 #
1*
1+
#4175
0+
#4180
b10100010 #
1+
#4185
0+
#4190
b10100011 #
0*
1+
#4195
0+
#4200
b10100100 #
1+
#4205
0+
#4210
b10100101 #
1*
1+
#4215
0+
#4220
b10100110 #
1+
#4225
0+
#4230
b10100111 #
0*
1+
#4235
0+
#4240
b10101000 #
1+
#4245
0+
#4250
b10101001 #
1*
1+
#4255
0+
#4260
b10101010 #
1+
#4265
0+
#4270
b10101011 #
0*
1+
#4275
0+
#4280
b10101100 #
1+
#4285
0+
#4290
b10101101 #
1*
1+
#4295
0+
#4300
b10101110 #
1+
#4305
0+
#4310
b10101111 #
0*
1+
#4315
0+
#4320
b10110000 #
1+
#4325
0+
#4330
b10110001 #
1*
1+
#4335
0+
#4340
b10110010 #
1+
#4345
0+
#4350
b10110011 #
0*
1+
#4355
0+
#4360
b10110100 #
1+
#4365
0+
#4370
b10110101 #
1*
1+
#4375
0+
#4380
b10110110 #
1+
#4385
0+
#4390
b10110111 #
0*
1+
#4395
0+
#4400
b10111000 #
1+
#4405
0+
#4410
b10111001 #
1*
1+
#4415
0+
#4420
b10111010 #
1+
#4425
0+
#4430
b10111011 #
0*
1+
#4435
0+
#4440
b10111100 #
1+
#4445
0+
#4450
b10111101 #
1*
1+
#4455
0+
#4460
b10111110 #
1+
#4465
0+
#4470
b10111111 #
0*
1+
#4475
0+
#4480
b11000000 #
1+
#4485
0+
#4490
b11000001 #
1*
1+
#4495
0+
#4500
b11000010 #
1+
#4505
0+
#4510
b11000011 #
0*
1+
#4515
0+
#4520
b11000100 #
1+
#4525
0+
#4530
b11000101 #
1*
1+
#4535
0+
#4540
b11000110 #
1+
#4545
0+
#4550
b11000111 #
0*
1+
#4555
0+
#4560
b11001000 #
1+
#4565
0+
#4570
b11001001 #
1*
1+
#4575
0+
#4580
b11001010 #
1+
#4585
0+
#4590
b11001011 #
0*
1+
#4595
0+
#4600
b11001100 #
1+
#4605
0+
#4610
b11001101 #
1*
1+
#4615
0+
#4620
b11001110 #
1+
#4625
0+
#4630
b11001111 #
0*
1+
#4635
0+
#4640
b11010000 #
1+
#4645
0+
#4650
b11010001 #
1*
1+
#4655
0+
#4660
b11010010 #
1+
#4665
0+
#4670
b11010011 #
0*
1+
#4675
0+
#4680
b11010100 #
1+
#4685
0+
#4690
b11010101 #
1*
1+
#4695
0+
#4700
b11010110 #
1+
#4705
0+
#4710
b11010111 #
0*
1+
#4715
0+
#4720
b11011000 #
1+
#4725
0+
#4730
b11011001 #
1*
1+
#4735
0+
#4740
b11011010 #
1+
#4745
0+
#4750
b11011011 #
0*
1+
#4755
0+
#4760
b11011100 #
1+
#4765
0+
#4770
b11011101 #
1*
1+
#4775
0+
#4780
b11011110 #
1+
#4785
0+
#4790
b11011111 #
0*
1+
#4795
0+
#4800
b11100000 #
1+
#4805
0+
#4810
b11100001 #
1*
1+
#4815
0+
#4820
b11100010 #
1+
#4825
0+
#4830
b11100011 #
0*
1+
#4835
0+
#4840
b11100100 #
1+
#4845
0+
#4850
b11100101 #
1*
1+
#4855
0+
#4860
b11100110 #
1+
#4865
0+
#4870
b11100111 #
0*
1+
#4875
0+
#4880
b11101000 #
1+
#4885
0+
#4890
b11101001 #
1*
1+
#4895
0+
#4900
b11101010 #
1+
#4905
0+
#4910
b11101011 #
0*
1+
#4915
0+
#4920
b11101100 #
1+
#4925
0+
#4930
b11101101 #
1*
1+
#4935
0+
#4940
b11101110 #
1+
#4945
0+
#4950
b11101111 #
0*
1+
#4955
0+
#4960
b11110000 #
1+
#4965
0+
#4970
b11110001 #
1*
1+
#4975
0+
#4980
b11110010 #
1+
#4985
0+
#4990
b11110011 #
0*
1+
#4995
0+
#5000
b11110100 #
1+
#5005
0+
#5010
b11110101 #
1*
1+
#5015
0+
#5020
b11110110 #
1+
#5025
0+
#5030
b11110111 #
0*
1+
#5035
0+
#5040
b11111000 #
1+
#5045
0+
#5050
b11111001 #
1*
1+
#5055
0+
#5060
b11111010 #
1+
#5065
0+
#5070
b11111011 #
0*
1+
#5075
0+
#5080
b11111100 #
1+
#5085
0+
#5090
b11111101 #
1*
1+
#5095
0+
#5100
b11111110 #
1+
#5105
0+
#5110
b11111111 #
0*
1+
#5115
0+
#5120
b00000000 #
1+
#5125
0+
#5130
b00000001 #
1*
1+
#5135
0+
#5140
b00000010 #
1+
#5145
0+
#5150
b00000011 #
0*
1+
#5155
0+
#5160
b00000100 #
1+
#5165
0+
#5170
b00000101 #
1*
1+
#5175
0+
#5180
b00000110 #
1+
#5185
0+
#5190
b00000111 #
0*
1+
#5195
0+
#5200
b00001000 #
1+
#5205
0+
#5210
b00001001 #
1*
1+
#5215
0+
#5220
b00001010 #
1+
#5225
0+
#5230
b00001011 #
0*
1+
#5235
0+
#5240
b00001100 #
1+
#5245
0+
#5250
b00001101 #
1*
1+
#5255
0+
#5260
b00001110 #
1+
#5265
0+
#5270
b00001111 #
0*
1+
#5275
0+
#5280
b00010000 #
1+
#5285
0+
#5290
b00010001 #
1*
1+
#5295
0+
#5300
b00010010 #
1+
#5305
0+
#5310
b00010011 #
0*
1+
#5315
0+
#5320
b00010100 #
1+
#5325
0+
#5330
b00010101 #
1*
1+
#5335
0+
#5340
b00010110 #
1+
#5345
0+
#5350
b00010111 #
0*
1+
#5355
0+
#5360
b00011000 #
1+
#5365
0+
#5370
b00011001 #
1*
1+
#5375
0+
#5380
b00011010 #
1+
#5385
0+
#5390
b00011011 #
0*
1+
#5395
0+
#5400
b00011100 #
1+
#5405
0+
#5410
b00011101 #
1*
1+
#5415
0+
#5420
b00011110 #
1+
#5425
0+
#5430
b00011111 #
0*
1+
#5435
0+
#5440
b00100000 #
1+
#5445
0+
#5450
b00100001 #
1*
1+
#5455
0+
#5460
b00100010 #
1+
#5465
0+
#5470
b00100011 #
0*
1+
#5475
0+
#5480
b00100100 #
1+
#5485
0+
#5490
b00100101 #
1*
1+
#5495
0+
#5500
b00100110 #
1+
#5505
0+
#5510
b00100111 #
0*
1+
#5515
0+
#5520
b00101000 #
1+
#5525
0+
#5530
b00101001 #
1*
1+
#5535
0+
#5540
b00101010 #
1+
#5545
0+
#5550
b00101011 #
0*
1+
#5555
0+
