Componets/MIPI-CSI-Transciever/Cam_I2C/Cam_I2C.v
module Cam_I2C(input clk400kHz,reset,send_data,input[7:0] datain,input[15:0] register_in,input[7:0] slave_addr,input ackn,inout scl,inout  sda);
	localparam reg[7:0] idle=0;
	localparam reg[7:0] adress=1;
	localparam reg[7:0] rw=2;
	localparam reg[7:0] reg0=3;
	localparam reg[7:0] reg1=4;
	localparam reg[7:0] data=5;
	
	reg[7:0] state=idle;
	reg send_data_old=0;
	reg rising_edge=0;
	integer counter =0;
	reg sda0=1;
	assign sda=sda0;
	always @(posedge clk400kHz) begin
		if (reset==1) begin
			state<=0;		
			sda0<=1;
			counter=0;
		end else begin
			//sda=1;
			send_data_old<=send_data;
			rising_edge=(send_data==1&&send_data_old==0)?1:0;			
			case (state)
				idle: begin
				sda0<=1;
				if(rising_edge==1) begin
					state<=adress;
					sda0<=0;
					counter=0;
				end			
				end
				adress: begin
					sda0<=slave_addr[counter];				
					counter=(counter>=7)?0:counter+1;
					state<=(counter>=7)?rw:adress;
				end
				rw: begin
					sda0<=0;
					state<=((sda==0||ackn==1) && counter==1)?reg0:rw;
					counter=(counter>=1)?0:counter+1;						
				end
				reg0: begin
					sda0<=register_in[counter];				
					counter=(counter>=8)?0:counter+1;
					state<=(counter>=8&&(sda==0||ackn==1))?reg1:reg0;					
				end
				reg1: begin
					sda0<=register_in[counter+8];				
					counter=(counter>=8)?0:counter+1;
					state<=(counter>=8&&(sda==0||ackn==1))?data:reg1;
				end
				data: begin
					sda0<=datain[counter];				
					counter=(counter>=8)?0:counter+1;
					state<=(counter>=8&&(sda==0||ackn==1))?idle:data;		
				end
				default: begin
				end
			endcase
		end
	end
	
	
endmodule

Componets/MIPI-CSI-Transciever/Cam_I2C/blinky.vcd
$version Generated by VerilatedVcd $end
$date Mon Nov 21 21:40:14 2022
 $end
$timescale   1ps $end

 $scope module TOP $end
  $var wire  1 . ackn $end
  $var wire  1 ( clk400kHz $end
  $var wire  8 + datain [7:0] $end
  $var wire 16 , register_in [15:0] $end
  $var wire  1 ) reset $end
  $var wire  1 / scl $end
  $var wire  1 0 sda $end
  $var wire  1 * send_data $end
  $var wire  8 - slave_addr [7:0] $end
  $scope module Cam_I2C $end
   $var wire  1 . ackn $end
   $var wire  8 2 adress [7:0] $end
   $var wire  1 ( clk400kHz $end
   $var wire 32 & counter [31:0] $end
   $var wire  8 6 data [7:0] $end
   $var wire  8 + datain [7:0] $end
   $var wire  8 1 idle [7:0] $end
   $var wire  8 4 reg0 [7:0] $end
   $var wire  8 5 reg1 [7:0] $end
   $var wire 16 , register_in [15:0] $end
   $var wire  1 ) reset $end
   $var wire  1 % rising_edge $end
   $var wire  8 3 rw [7:0] $end
   $var wire  1 / scl $end
   $var wire  1 0 sda $end
   $var wire  1 ' sda0 $end
   $var wire  1 * send_data $end
   $var wire  1 $ send_data_old $end
   $var wire  8 - slave_addr [7:0] $end
   $var wire  8 # state [7:0] $end
  $upscope $end
 $upscope $end
$enddefinitions $end


#10
b00000001 #
1$
1%
b00000000000000000000000000000000 &
0'
1(
0)
1*
b10101010 +
b1010101010101010 ,
b10101010 -
0.
0/
00
b00000000 1
b00000001 2
b00000010 3
b00000011 4
b00000100 5
b00000101 6
#15
0(
#20
0%
b00000000000000000000000000000001 &
1(
#25
0(
#30
b00000000000000000000000000000010 &
1'
1(
10
#35
0(
#40
b00000000000000000000000000000011 &
0'
1(
00
#45
0(
#50
b00000000000000000000000000000100 &
1'
1(
10
#55
0(
#60
b00000000000000000000000000000101 &
0'
1(
00
#65
0(
#70
b00000000000000000000000000000110 &
1'
1(
10
#75
0(
#80
b00000000000000000000000000000111 &
0'
1(
00
#85
0(
#90
b00000010 #
b00000000000000000000000000000000 &
1'
1(
10
#95
0(
#100
b00000000000000000000000000000001 &
0'
1(
00
#105
0(
#110
b00000011 #
b00000000000000000000000000000000 &
1(
1.
#115
0(
#120
b00000000000000000000000000000001 &
1(
#125
0(
#130
b00000000000000000000000000000010 &
1'
1(
10
#135
0(
#140
b00000000000000000000000000000011 &
0'
1(
00
#145
0(
#150
b00000000000000000000000000000100 &
1'
1(
10
#155
0(
#160
b00000000000000000000000000000101 &
0'
1(
00
#165
0(
#170
b00000000000000000000000000000110 &
1'
1(
10
#175
0(
#180
b00000000000000000000000000000111 &
0'
1(
00
#185
0(
#190
b00000100 #
b00000000000000000000000000001000 &
1'
1(
10
#195
0(
#200
b00000000000000000000000000000000 &
0'
1(
00
#205
0(
#210
b00000000000000000000000000000001 &
1(
#215
0(
#220
b00000000000000000000000000000010 &
1'
1(
10
#225
0(
#230
b00000000000000000000000000000011 &
0'
1(
00
#235
0(
#240
b00000000000000000000000000000100 &
1'
1(
10
#245
0(
#250
b00000000000000000000000000000101 &
0'
1(
00
#255
0(
#260
b00000000000000000000000000000110 &
1'
1(
10
#265
0(
#270
b00000000000000000000000000000111 &
0'
1(
00
#275
0(
#280
b00000101 #
b00000000000000000000000000001000 &
1'
1(
10
#285
0(
#290
b00000000000000000000000000000000 &
0'
1(
00
#295
0(
#300
b00000000000000000000000000000001 &
1(
#305
0(
#310
b00000000000000000000000000000010 &
1'
1(
10
#315
0(
#320
b00000000000000000000000000000011 &
0'
1(
00
#325
0(
#330
b00000000000000000000000000000100 &
1'
1(
10
#335
0(
#340
b00000000000000000000000000000101 &
0'
1(
00
#345
0(
#350
b00000000000000000000000000000110 &
1'
1(
10
#355
0(
#360
b00000000000000000000000000000111 &
0'
1(
00
#365
0(
#370
b00000000 #
b00000000000000000000000000001000 &
1'
1(
10
