Componets/MIPI-CSI-Transciever/MIPI_Reciever/Cam_I2C.v
module Cam_I2C(output valid,input clk400kHz,reset,send_data,r_w,input[7:0] datain,input[15:0] register_in,input[6:0] slave_addr,input ackn,inout scl,inout  sda, output ready);
	localparam reg[7:0] idle=0;
	localparam reg[7:0] start=1;
	localparam reg[7:0] send=2;
	localparam reg[7:0] reg0=3;
	localparam reg[7:0] reg1=4;
	localparam reg[7:0] data=5;
	localparam reg[7:0] stop=6;
	
	reg valid_r;
	reg[7:0] state=idle;
	reg send_data_old=0;
	reg rising_edge=0;
	integer counter =0;
	reg sda0=1;
	assign sda=sda0;
	reg sending=0;
	reg[36:0] i2cdata={slave_addr,1'b0,1'b1,register_in[15:8],1'b1,register_in[7:0],1'b1,datain,1'b1,1'b0};
	reg [36:0] i2cin=0;
	reg ready0;
	assign valid=valid_r;
	always @(posedge clk400kHz) begin
		if (reset==1) begin
			state<=0;		
			sda0<=1;
			counter=0;
			valid_r=0;			
		end else begin
			//sda=1;
			send_data_old<=send_data;
			rising_edge=(send_data==1&&send_data_old==0)?1:0;			
			case (state)
				idle: begin
					valid_r=0;
					ready0<=1;
					sda0<=1;
					sending=0;
					if(rising_edge==1) begin
						state<=start;
						ready0<=0;
						counter=0;
						sda0<=0;
						//sending=1;
					end
				end	
				start: begin
					sending=(counter>=36)?0:1;
					sda0<=(counter>=36)?0:i2cdata[36-counter];				
					counter=(counter>=36)?0:counter+1;
					state<=(counter>=36)?stop:start;		
					
				end
				stop: begin					
					state<=idle;
					sda0<=0;
					if(i2cin[1]==0&&i2cin[10]==0&&i2cin[19]==0&&i2cin[28]==0)begin
						valid_r=1;
					end
				end
				default: begin
				end
			endcase
		end
	end
	reg [7:0]clkcount=0;
	reg clkdelay0;
	reg clkdelay1;	
	reg scl0,scl1,scl2;	
	assign scl=sending?~clk400kHz:1;
	assign ready=ready0;
	
endmodule

Componets/MIPI-CSI-Transciever/Cam_I2C/blinky.vcd
$version Generated by VerilatedVcd $end
$date Wed Dec  7 22:01:17 2022
 $end
$timescale   1ps $end

 $scope module TOP $end
  $var wire  1 3 ackn $end
  $var wire  1 , clk400kHz $end
  $var wire  8 0 datain [7:0] $end
  $var wire  1 / r_w $end
  $var wire  1 6 ready $end
  $var wire 16 1 register_in [15:0] $end
  $var wire  1 - reset $end
  $var wire  1 4 scl $end
  $var wire  1 5 sda $end
  $var wire  1 . send_data $end
  $var wire  7 2 slave_addr [6:0] $end
  $var wire  1 + valid $end
  $scope module Cam_I2C $end
   $var wire  1 3 ackn $end
   $var wire  1 , clk400kHz $end
   $var wire  8 9 clkcount [7:0] $end
   $var wire  1 B clkdelay0 $end
   $var wire  1 C clkdelay1 $end
   $var wire 32 ' counter [31:0] $end
   $var wire  8 > data [7:0] $end
   $var wire  8 0 datain [7:0] $end
   $var wire 37 7 i2cdata [36:0] $end
   $var wire 37 @ i2cin [36:0] $end
   $var wire  8 9 idle [7:0] $end
   $var wire  1 / r_w $end
   $var wire  1 6 ready $end
   $var wire  1 * ready0 $end
   $var wire  8 < reg0 [7:0] $end
   $var wire  8 = reg1 [7:0] $end
   $var wire 16 1 register_in [15:0] $end
   $var wire  1 - reset $end
   $var wire  1 & rising_edge $end
   $var wire  1 4 scl $end
   $var wire  1 D scl0 $end
   $var wire  1 E scl1 $end
   $var wire  1 F scl2 $end
   $var wire  1 5 sda $end
   $var wire  1 ( sda0 $end
   $var wire  8 ; send [7:0] $end
   $var wire  1 . send_data $end
   $var wire  1 % send_data_old $end
   $var wire  1 ) sending $end
   $var wire  7 2 slave_addr [6:0] $end
   $var wire  8 : start [7:0] $end
   $var wire  8 $ state [7:0] $end
   $var wire  8 ? stop [7:0] $end
   $var wire  1 + valid $end
   $var wire  1 # valid_r $end
  $upscope $end
 $upscope $end
$enddefinitions $end


#10
0#
b00000000 $
0%
0&
b00000000000000000000000000000000 '
1(
0)
1*
0+
1,
0-
0.
0/
b00000000 0
b0000000000000000 1
b0010000 2
03
14
15
16
b0010000010000000010000000010000000010 7
b00000000 9
b00000001 :
b00000010 ;
b00000011 <
b00000100 =
b00000101 >
b00000110 ?
b0000000000000000000000000000000000000 @
0B
0C
0D
0E
0F
#15
#20
#25
#30
0,
#35
#40
#45
#50
1,
#55
#60
#65
#70
0,
#75
#80
#85
#90
1,
#95
#100
#105
#110
0,
13
#115
#120
1.
#125
#130
b00000001 $
1%
1&
0(
0*
1,
05
06
#135
#140
#145
#150
0,
#155
#160
#165
#170
0&
b00000000000000000000000000000001 '
1)
1,
04
#175
#180
#185
#190
0,
14
#195
#200
#205
#210
b00000000000000000000000000000010 '
1,
04
#215
#220
#225
#230
0,
14
#235
#240
#245
#250
b00000000000000000000000000000011 '
1(
1,
04
15
#255
#260
#265
#270
0,
14
#275
#280
#285
#290
b00000000000000000000000000000100 '
0(
1,
04
05
#295
#300
#305
#310
0,
14
#315
#320
#325
#330
b00000000000000000000000000000101 '
1,
04
#335
#340
#345
#350
0,
14
#355
#360
#365
#370
b00000000000000000000000000000110 '
1,
04
#375
#380
#385
#390
0,
14
#395
#400
#405
#410
b00000000000000000000000000000111 '
1,
04
#415
#420
#425
#430
0,
14
#435
#440
#445
#450
b00000000000000000000000000001000 '
1,
04
#455
#460
#465
#470
0,
14
#475
#480
#485
#490
b00000000000000000000000000001001 '
1(
1,
04
15
#495
#500
#505
#510
0,
14
#515
#520
#525
#530
b00000000000000000000000000001010 '
0(
1,
04
05
#535
#540
#545
#550
0,
14
#555
#560
#565
#570
b00000000000000000000000000001011 '
1,
04
#575
#580
#585
#590
0,
14
#595
#600
#605
#610
b00000000000000000000000000001100 '
1,
04
#615
#620
#625
#630
0,
14
#635
#640
#645
#650
b00000000000000000000000000001101 '
1,
04
#655
#660
#665
#670
0,
14
#675
#680
#685
#690
b00000000000000000000000000001110 '
1,
04
#695
#700
#705
#710
0,
14
#715
#720
#725
#730
b00000000000000000000000000001111 '
1,
04
#735
#740
#745
#750
0,
14
#755
#760
#765
#770
b00000000000000000000000000010000 '
1,
04
#775
#780
#785
#790
0,
14
#795
#800
#805
#810
b00000000000000000000000000010001 '
1,
04
#815
#820
#825
#830
0,
14
#835
#840
#845
#850
b00000000000000000000000000010010 '
1(
1,
04
15
#855
#860
#865
#870
0,
14
#875
#880
#885
#890
b00000000000000000000000000010011 '
0(
1,
04
05
#895
#900
#905
#910
0,
14
#915
#920
#925
#930
b00000000000000000000000000010100 '
1,
04
#935
#940
#945
#950
0,
14
#955
#960
#965
#970
b00000000000000000000000000010101 '
1,
04
#975
#980
#985
#990
0,
14
#995
#1000
#1005
#1010
b00000000000000000000000000010110 '
1,
04
#1015
#1020
#1025
#1030
0,
14
#1035
#1040
#1045
#1050
b00000000000000000000000000010111 '
1,
04
#1055
#1060
#1065
#1070
0,
14
#1075
#1080
#1085
#1090
b00000000000000000000000000011000 '
1,
04
#1095
#1100
#1105
#1110
0,
14
#1115
#1120
#1125
#1130
b00000000000000000000000000011001 '
1,
04
#1135
#1140
#1145
#1150
0,
14
#1155
#1160
#1165
#1170
b00000000000000000000000000011010 '
1,
04
#1175
#1180
#1185
#1190
0,
14
#1195
#1200
#1205
#1210
b00000000000000000000000000011011 '
1(
1,
04
15
#1215
#1220
#1225
#1230
0,
14
#1235
#1240
#1245
#1250
b00000000000000000000000000011100 '
0(
1,
04
05
#1255
#1260
#1265
#1270
0,
14
#1275
#1280
#1285
#1290
b00000000000000000000000000011101 '
1,
04
#1295
#1300
#1305
#1310
0,
14
#1315
#1320
#1325
#1330
b00000000000000000000000000011110 '
1,
04
#1335
#1340
#1345
#1350
0,
14
#1355
#1360
#1365
#1370
b00000000000000000000000000011111 '
1,
04
#1375
#1380
#1385
#1390
0,
14
#1395
#1400
#1405
#1410
b00000000000000000000000000100000 '
1,
04
#1415
#1420
#1425
#1430
0,
14
#1435
#1440
#1445
#1450
b00000000000000000000000000100001 '
1,
04
#1455
#1460
#1465
#1470
0,
14
#1475
#1480
#1485
#1490
b00000000000000000000000000100010 '
1,
04
#1495
#1500
#1505
#1510
0,
14
#1515
#1520
#1525
#1530
b00000000000000000000000000100011 '
1,
04
#1535
#1540
#1545
#1550
0,
14
#1555
#1560
#1565
#1570
b00000000000000000000000000100100 '
1(
1,
04
15
#1575
#1580
#1585
#1590
0,
14
#1595
#1600
#1605
#1610
b00000110 $
b00000000000000000000000000000000 '
0(
0)
1,
05
#1615
#1620
#1625
#1630
0,
#1635
#1640
#1645
#1650
1#
b00000000 $
1+
1,
#1655
#1660
#1665
#1670
0,
#1675
#1680
#1685
#1690
0#
1(
1*
0+
1,
15
16
