src/MIPI/IDDR1/IDDRX1F.v
module IDDRX1F(input D,input SCLK,input RST,output Q0,output Q1);
	reg Q0_r,Q1_r;
	always @(posedge SCLK) begin
		Q0_r<=D;
	end
	always @(negedge SCLK) begin
		Q1_r<=D;
	end	
	assign Q1=Q1_r;
	assign Q0=Q0_r;
	
endmodule

src/MIPI/IDDR1/CLKDIVF.v
module CLKDIVF(input CLKI,RST,output CDIVX);
	reg[7:0] counter;
	assign CDIVX=counter[0];
	always @(posedge CLKI) begin
		if(RST==1)begin
			counter<=0;
		end else begin
			counter<=counter+1;
		end
	end
endmodule

src/MIPI/IDDR1/MIPI_Reciever.v
module MIPI_Reciever
#(parameter
	mipi_frec=216,
	iddr_ratio=4
		)
(input sys_clk,reset,lane0_d,mipi_clk,lane1_d,inout lane0_p,lane0_n,lane1_p,lane1_n
 ,output[31:0] data_o,output[31:0] address_out,output ram_clk
 ,output reg debug0,debug1,debug3,debug2,output termination,rec_data_o);
    
	wire stop_clk, rec_data;
	wire[7:0] lane0byte,lane1byte;	 	
    SoTFSM #(.mipi_frec(mipi_frec)) RxFSM (.rec_data(rec_data),.clk50MHz(sys_clk),.reset(reset),.lane0_p(lane0_p),.lane0_n(lane0_n),.lane1_p(lane1_p),.lane1_n(lane1_n),.stop_rx(stop_clk),.term(termination),.debug0(debug0));
	wire[1:0]q_o_0,q_o_1;	
	wire sync;	
	wire mipi_clk_2,mipi_clk_4,mipi_clk_8;	

	CLKDIVF div2 (.CLKI(mipi_clk),.RST(reset),.CDIVX(mipi_clk_2));
	CLKDIVF div4 (.CLKI(mipi_clk_2),.RST(reset),.CDIVX(mipi_clk_4));
	CLKDIVF div8 (.CLKI(mipi_clk_4),.RST(reset),.CDIVX(mipi_clk_8));

    IDDR1 lane0 (.lane(lane0_d),.mipi_clk(mipi_clk),.reset(reset),.stop(stop_clk),.sync(sync),.q_o(q_o_0));
	IDDR1 lane1 (.lane(lane1_d),.mipi_clk(mipi_clk),.reset(reset),.stop(stop_clk),/*.sync(sync),*/.q_o(q_o_1));

	wire[7:0] byte_o_0,byte_o_1;
	Byte_Arranger BA0 (.reset(reset),.stop(stop_clk),.mipi_clk(mipi_clk),.q_o(q_o_0),.byte_o(byte_o_0));
	Byte_Arranger BA1 (.reset(reset),.stop(stop_clk),.mipi_clk(mipi_clk),.q_o(q_o_1),.byte_o(byte_o_1));	
	
	wire[7:0] byte_0,byte_1;
	Byte_Alligner BAL0(.reset(reset),.stop(stop_clk),.mipi_clk(mipi_clk),.sync(sync),.byte_i(byte_o_0),.byte_o(byte_0));
	Byte_Alligner BAL1(.reset(reset),.stop(stop_clk),.mipi_clk(mipi_clk),.sync(sync),.byte_i(byte_o_1),.byte_o(byte_1));	

	wire [31:0] data;
	wire valid;
	wire[5:0] type_w;
	wire[15:0] wordcount;
	DATA_Encoder DE (.mipi_clk_4(mipi_clk_4),.reset(reset),.stop(stop_clk),.sync(sync),.byte_in0(byte_0),.data(data),.type_o(type_w),.wordcount(wordcount),.byte_in1(byte_1),.valid(valid));	
	
	Protocoll Prot (.debug(debug2),.debug1(debug3),.mipi_clk_8(mipi_clk_8),.stop(stop_clk),.reset(reset),.valid(valid),.type_i(type_w),.wordcount(wordcount),.data_o(data_o),.data(data),.rec_data(rec_data),.address_o(address_out));
	assign rec_data_o=rec_data;	
	assign ram_clk=mipi_clk_8;

	assign debug1=rec_data;
	//assign debug2=rec_data;
	//assign debug3=stop_clk;
endmodule



module IDDR1(input lane,stop,reset,mipi_clk,output sync,output[1:0] q_o);	
	IDDRX1F l0(.D(lane),.SCLK(mipi_clk),.Q0(ddr[0]),.Q1(ddr[1]),.RST('b0));
	reg[7:0] byte_r;
	reg sync_r=0;
	reg[1:0] q_o_r;
	assign sync=sync_r;
	assign q_o=q_o_r;
	wire[1:0] ddr;
	always @(posedge mipi_clk) begin
		if(stop==1||reset==1)begin
			byte_r<=0;
			sync_r<=0;
		end else begin
			byte_r<={ddr,byte_r[7:2]};
			sync_r<=(byte_r[7:0]==8'b10111000)?1:sync_r;
			q_o_r<=ddr;
		end
	end
endmodule

module Byte_Arranger(input reset,stop,mipi_clk,input[1:0] q_o,output[7:0] byte_o);
	reg[7:0] byte_r;
	assign byte_o=byte_r;
	always @(posedge mipi_clk) begin
		if(reset||stop)begin
			byte_r<=0;			
		end else begin				
			byte_r<={q_o,byte_r[7:2]};					
		end		
	end
endmodule

module Byte_Alligner(input reset,stop,mipi_clk,sync,input[7:0] byte_i,output[7:0] byte_o);
	reg[7:0] byte_o_r;
	assign byte_o=byte_o_r;	//////////////////////////SYNC
	reg[7:0]counter;		
	always @(posedge mipi_clk) begin
		if(reset||stop)begin
			byte_o_r<=0;					
			counter<=0;			
		end else begin			
			if(sync)begin
				counter<=(counter>=4)?1:counter+1;				
				byte_o_r<=(counter>=4)?byte_i:byte_o_r;				
			end
		end
	end
endmodule


module DATA_Encoder(input mipi_clk_4,reset,stop,sync,input[7:0] byte_in0,byte_in1,output[31:0]data,output valid,output[5:0] type_o,output[15:0] wordcount);
	reg[31:0] out_r,out_r_old;
	reg valid_r,start;
	assign valid=valid_r&&(!stop);	
	reg[31:0] counter;
	wire[31:0] regheader;
	assign regheader=out_r;
	wire[7:0] ecc;
	reg [31:0] data_r;
	reg[5:0] type_o_r;
	reg[15:0] wordcount_r;
	assign data=data_r;
	assign type_o=type_o_r;
	assign wordcount=wordcount_r;
	assign ecc[0]=regheader[0]^regheader[1]^regheader[2]^regheader[4]^regheader[5]^regheader[7]^regheader[10]^regheader[11]^regheader[13]^regheader[16]^
		regheader[20]^regheader[21]^regheader[22]^regheader[23];
	assign ecc[1]=regheader[0]^regheader[1]^regheader[3]^regheader[4]^regheader[6]^regheader[8]^regheader[10]^regheader[12]^regheader[14]^regheader[17]^
		regheader[20]^regheader[21]^regheader[22]^regheader[23];
	assign ecc[2]=regheader[0]^regheader[2]^regheader[3]^regheader[5]^regheader[6]^regheader[9]^regheader[11]^regheader[12]^regheader[15]^regheader[18]^
		regheader[20]^regheader[21]^regheader[22];
	assign ecc[3]=regheader[1]^regheader[2]^regheader[3]^regheader[7]^regheader[8]^regheader[9]^regheader[13]^regheader[14]^regheader[15]^regheader[19]^
		regheader[20]^regheader[21]^regheader[23];
	assign ecc[4]=regheader[4]^regheader[5]^regheader[6]^regheader[7]^regheader[8]^regheader[9]^regheader[16]^regheader[17]^regheader[18]^regheader[19]^
		regheader[20]^regheader[22]^regheader[23];
	assign ecc[5]=regheader[10]^regheader[11]^regheader[12]^regheader[13]^regheader[14]^regheader[15]^regheader[16]^regheader[17]^regheader[18]^regheader[19]^
		regheader[21]^regheader[22]^regheader[23];	
	assign ecc[6]=0;
	assign ecc[7]=0;
	wire[7:0] syndrom;
	assign syndrom=ecc^regheader[31:24];
	
	wire[23:0] correction;
	wire[31:0] regheader_correct;

	assign correction[0]=syndrom==8'h07;
	assign correction[1]=syndrom==8'h0B;
	assign correction[2]=syndrom==8'h0D;
	assign correction[3]=syndrom==8'h0E;
	assign correction[4]=syndrom==8'h13;
	assign correction[5]=syndrom==8'h15;
	assign correction[4]=syndrom==8'h16;
	assign correction[7]=syndrom==8'h19;
	assign correction[8]=syndrom==8'h1A;
	assign correction[9]=syndrom==8'h1C;
	assign correction[10]=syndrom==8'h23;
	assign correction[11]=syndrom==8'h25;
	assign correction[12]=syndrom==8'h26;
	assign correction[13]=syndrom==8'h29;
	assign correction[14]=syndrom==8'h2A;
	assign correction[15]=syndrom==8'h2C;
	assign correction[16]=syndrom==8'h31;
	assign correction[17]=syndrom==8'h32;
	assign correction[18]=syndrom==8'h34;
	assign correction[19]=syndrom==8'h38;
	assign correction[20]=syndrom==8'h1F;
	assign correction[21]=syndrom==8'h2F;
	assign correction[22]=syndrom==8'h37;
	assign correction[23]=syndrom==8'h3B;
	
	assign regheader_correct=regheader^ {8'h00,correction};


	always @(posedge mipi_clk_4) begin
		if(reset||stop)begin
			out_r<=0;
			out_r_old<=0;
			valid_r<=0;		
			start=0;
			counter<=0;
			data_r<=0;
			type_o_r<=0;
			wordcount_r<=0;
		end else begin			
			if(sync)begin
				out_r_old<=out_r;
				out_r<={byte_in1,byte_in0,out_r[31:16]};
				valid_r<=(ecc==regheader_correct[31:24]&&regheader_correct!=0)?1:valid_r;
				start=(ecc==regheader_correct[31:24]&&regheader_correct!=0)?1:start;
				type_o_r<=(ecc==regheader_correct[31:24]&&regheader_correct!=0)?regheader_correct[5:0]:type_o_r;
				wordcount_r<=(ecc==regheader_correct[31:24]&&regheader_correct!=0)?regheader_correct[23:8]:wordcount_r;				
				if(start)begin
					counter<=counter+1;
					if(counter[0]==0&&counter[1]==1)begin
						counter<=1;
						//data_r<=even?{1'b1,out_r[30:0]}:{4'b0000,out_r[27:0]};
						//data_r<={4'b1000,out_r[31:28],4'b1000,out_r[23:20],4'b1000,out_r[15:12],4'b1000,out_r[7:4]};
						//data_r<={out_r[27:0],4'b0000};
						//data_r<={4'd0,out_r[31:4]};
						data_r<=out_r;
					end else begin
						counter<=counter+1;
					end


				end	

			end
		end
	end
endmodule


module SoTFSM
	#(parameter
		mipi_frec=350
	 )
	 (input clk50MHz,reset,rec_data,lane0_p,lane0_n,lane1_p,lane1_n,stop_tran,
	output stop_rx,term,debug0,debug1);
	///////////////////States for long and short Packet Recieve
	localparam reg[7:0] TIMEOUT=0;
	localparam reg[7:0] LP11=1;
	localparam reg[7:0] LP01=2;
	localparam reg[7:0] LP00=3;
	localparam reg[7:0] SYNC=4;
	localparam reg[7:0] HEADER=5;
	///////////////////Const for Timing 
	localparam integer Tlpx=2;//50ns -> nearest =40ns
	localparam[31:0]  Timeout=(2000*50/mipi_frec);
	localparam[31:0]  Tdterm=2+(2*50/mipi_frec);
	localparam[31:0]  Thssettle=3+(3*50/mipi_frec);
	///////////////////
	reg[7:0] state_mipi=TIMEOUT;	
	reg stop_rx_r,term_r,debug0_r,debug1_r;
	assign stop_rx=stop_rx_r;
	assign term=term_r;
	assign debug0=debug0_r;
	assign debug1=debug1_r;	

	integer timer_tou,timer_term,timer_hs;	
	///////////////////////////////////////////////FSM
	always @(posedge clk50MHz) begin
		if(reset==1) begin
			state_mipi<=TIMEOUT;
			timer_tou<=0;
			timer_term<=0;
			timer_hs<=0;			
			term_r<=0;
			stop_rx_r<=1;
		end else begin
			case (state_mipi)
				TIMEOUT: begin
					state_mipi<=(lane0_p==1 && lane0_n==1 &&lane1_p==1 &&lane1_n==1)?LP11:TIMEOUT; 				
					timer_tou<=0;
					timer_term<=0;
					timer_hs<=0;			
					term_r<=0;
					debug0_r<=0;
					stop_rx_r<=1;	
				end
				LP11:begin					
					state_mipi<=(lane0_p==0 && lane0_n==1 &&lane1_p==0 &&lane1_n==1)?LP01:LP11;	
					debug0_r<=0;						
				end
				LP01:begin
					if(timer_tou>=Timeout) begin
						state_mipi<=TIMEOUT;
					end else begin
						if(lane0_p==0 && lane0_n==0 &&lane1_p==0 &&lane1_n==0)begin
							state_mipi<=LP00;
							timer_tou<=0;
							timer_hs<=0;					 
						end					
					end	
					if(timer_term>=Tdterm) begin					
						term_r<=1;					
					end 					
					timer_tou<=timer_tou+1;
					timer_term<=timer_term+1;	
					stop_rx_r<=1;			
				end
				LP00:begin
					stop_rx_r<=1;	
					if(timer_term>=Tdterm) begin					
						term_r<=1;					
					end 
					if(timer_hs>=Thssettle) begin
						state_mipi<=SYNC;
						timer_tou<=0;	
						stop_rx_r<=0;
					end
					if(timer_tou>=Timeout)begin
						state_mipi<=TIMEOUT;
					end
					timer_tou<=timer_tou+1;
					timer_term<=timer_term+1;
					timer_hs<=timer_hs+1;					
				end
				SYNC:begin		
					debug0_r<=1;
					if(timer_tou>=Timeout)begin
						state_mipi<=TIMEOUT;
						stop_rx_r<=1;					
					end				
					timer_tou<=timer_tou+1;
					if(rec_data==1)begin
						state_mipi<=HEADER;
						timer_tou<=0;
					end				
				end	
				HEADER:begin					
					timer_tou<=timer_tou+1;
					if(rec_data==0||timer_tou>Timeout)begin
						state_mipi<=TIMEOUT;
						term_r<=0;
						//stop_rx_r<=1;	
					end	
				end		
				default: begin
				end
			endcase		
		end	   
	end
endmodule

module Protocoll(input mipi_clk_8,stop,reset,valid,input[5:0] type_i,input[15:0] wordcount,input[31:0] data,output[31:0] data_o,output[31:0]address_o,output rec_data,output reg debug,output reg debug1);
	reg rec_data_r,state,valid_old;
	reg[31:0] counter,count_val,data_o_r,counter_addr,cX_r,cY_r;
	assign data_o=data_o_r;
	assign rec_data=rec_data_r&&(!stop);	
	assign address_o=counter_addr;	
	reg[15:0] c='hffff;//crc code
	wire[15:0] c_calk;
	wire[31:0] d;//recieved data
	assign d=data;
	////////////////////////////////////////////////////////CRC Sum
	assign c_calk[0]=d[21]^d[10]^c [10]^d[28]^d[6]^c [6]^d[24]^d[13]^c [13]^d[20]^d[5]^c [5]^d[12]^c [12]^d[4]^c [4]^d[0]^c [0];
	assign c_calk[1]=d[22]^d[11]^c [11]^d[0]^c [0]^d[29]^d[7]^c [7]^d[25]^d[14]^c[14]^d[21]^d[6]^c [6]^d[13]^c [13]^d[5]^c [5]^d[1]^c [1];
	assign c_calk[2]=d[23]^d[12]^c [12]^d[1]^c [1]^d[30]^d[8]^c [8]^d[26]^d[15]^c [15]^d[22]^d[7]^c [7]^d[14]^c [14]^d[6]^c [6]^d[2]^c [2];
	assign c_calk[3]=d[24]^d[13]^c [13]^d[2]^c [2]^d[31]^d[9]^c [9]^d[27]^d[16]^d[23]^d[8]^c [8]^d[15]^c [15]^d[0]^c [0]^d[7]^c [7]^d[3]^c [3];
	assign c_calk[4]=d[20]^d[16]^d[12]^c [12]^d[8]^c [8]^d[0]^c [0]^d[25]^d[14]^c [14]^d[3]^c [3]^d[21]^d[17]^d[6]^c [6]^d[13]^c [13]^d[9]^c [9]^d[5]^c [5]^d[1]^c [1];
	assign c_calk[5]=d[21]^d[17]^d[13]^c [13]^d[9]^c [9]^d[1]^c [1]^d[26]^d[15]^c [15]^d[4]^c [4]^d[22]^d[0]^c [0]^d[18]^d[7]^c [7]^d[14]^c [14]^d[10]^c [10]^d[6]^c [6]^d[2]^c [2];
	assign c_calk[6]=d[22]^d[18]^d[14]^c [14]^d[10]^c [10]^d[2]^c [2]^d[27]^d[16]^d[5]^c [5]^d[23]^d[1]^c [1]^d[19]^d[8]^c [8]^d[15]^c [15]^d[11]^c [11]^d[7]^c [7]^d[3]^c [3];
	assign c_calk[7]=d[23]^d[19]^d[15]^c [15]^d[11]^c [11]^d[3]^c [3]^d[28]^d[17]^d[6]^c [6]^d[24]^d[2]^c [2]^d[20]^d[9]^c [9]^d[16]^d[12]^c [12]^d[8]^c [8]^d[4]^c [4]^d[0]^c [0];
	assign c_calk[8]=d[24]^d[20]^d[16]^d[12]^c [12]^d[4]^c [4]^d[29]^d[18]^d[7]^c [7]^d[25]^d[3]^c [3]^d[21]^d[10]^c [10]^d[17]^d[13]^c [13]^d[9]^c [9]^d[5]^c [5]^d[1]^c [1];
	assign c_calk[9]=d[25]^d[21]^d[17]^d[13]^c [13]^d[5]^c [5]^d[30]^d[19]^d[8]^c [8]^d[26]^d[4]^c [4]^d[22]^d[11]^c [11]^d[18]^d[14]^c [14]^d[10]^c [10]^d[6]^c [6]^d[2]^c [2];
	assign c_calk[10]=d[26]^d[22]^d[18]^d[14]^c [14]^d[6]^c [6]^d[31]^d[20]^d[9]^c [9]^d[27]^d[5]^c [5]^d[23]^d[12]^c [12]^d[19]^d[15]^c [15]^d[11]^c [11]^d[0]^c [0]^d[7]^c [7]^d[3]^c [3];
	assign c_calk[11]=d[27]^d[16]^d[5]^c [5]^d[23]^d[1]^c [1]^d[19]^d[8]^c [8]^d[15]^c [15]^d[0]^c [0]^d[7]^c [7];
	assign c_calk[12]=d[28]^d[17]^d[6]^c [6]^d[24]^d[2]^c [2]^d[20]^d[9]^c [9]^d[16]^d[1]^c [1]^d[8]^c [8]^d[0]^c [0];
	assign c_calk[13]=d[29]^d[18]^d[7]^c [7]^d[25]^d[3]^c [3]^d[21]^d[10]^c [10]^d[17]^d[2]^c [2]^d[9]^c [9]^d[1]^c [1];
	assign c_calk[14]=d[30]^d[19]^d[8]^c [8]^d[26]^d[4]^c [4]^d[22]^d[11]^c [11]^d[18]^d[3]^c [3]^d[10]^c [10]^d[2]^c [2];
	assign c_calk[15]=d[31]^d[20]^d[9]^c [9]^d[27]^d[5]^c [5]^d[23]^d[12]^c [12]^d[19]^d[4]^c [4]^d[11]^c [11]^d[3]^c [3];			
	//////////////////////////////////////////////
	always @(posedge mipi_clk_8) begin
		if(reset)begin
			rec_data_r<=0;
			state<=0;
			data_o_r<=0;
			counter_addr<=0;
			valid_old<=0;
			cX_r<=0;
			cY_r<=0;
			debug<=0;
			//counter<=0;
			//count_val<=0;			
		end	else begin
			valid_old<=valid;			
			case (state)
				0:begin
					c<='hffff;	
					if(((valid==1&&valid_old==0)&&(type_i=='h00||type_i=='h01)))begin
						counter_addr<=0;							
						debug<=1;					
					end		
					if((valid==1&&valid_old==0)&&type_i=='h2a&&wordcount=='h0280)begin
						state<=1;
						count_val<=160;						
						debug<=0;
						debug1<=0;											
					end															
				end 
				1:begin						
					if(counter<count_val)begin						
						counter<=counter+1;
						rec_data_r<=1;						
						counter_addr<=counter_addr+1;
						data_o_r<=data;
						c<=c_calk;						
					end else begin
						rec_data_r<=0;
						state<=0;
						counter<=0;
						if(c==data[15:0])begin
							debug1<=1;
						end							
					end
				end
				default:begin					
				end 
			endcase
		end
	end
endmodule

src/MIPI/IDDR1/MIPI_Sim.vcd
$version Generated by VerilatedVcd $end
$date Tue Apr 11 11:06:01 2023
 $end
$timescale   1ps $end

 $scope module TOP $end
  $var wire 32 \ address_out [31:0] $end
  $var wire 32 [ data_o [31:0] $end
  $var wire  1 ^ debug0 $end
  $var wire  1 _ debug1 $end
  $var wire  1 a debug2 $end
  $var wire  1 ` debug3 $end
  $var wire  1 T lane0_d $end
  $var wire  1 X lane0_n $end
  $var wire  1 W lane0_p $end
  $var wire  1 V lane1_d $end
  $var wire  1 Z lane1_n $end
  $var wire  1 Y lane1_p $end
  $var wire  1 U mipi_clk $end
  $var wire  1 ] ram_clk $end
  $var wire  1 c rec_data_o $end
  $var wire  1 S reset $end
  $var wire  1 R sys_clk $end
  $var wire  1 b termination $end
  $scope module MIPI_Reciever $end
   $var wire 32 \ address_out [31:0] $end
   $var wire  8 I byte_0 [7:0] $end
   $var wire  8 J byte_1 [7:0] $end
   $var wire  8 & byte_o_0 [7:0] $end
   $var wire  8 ' byte_o_1 [7:0] $end
   $var wire 32 = data [31:0] $end
   $var wire 32 [ data_o [31:0] $end
   $var wire  1 ^ debug0 $end
   $var wire  1 _ debug1 $end
   $var wire  1 a debug2 $end
   $var wire  1 ` debug3 $end
   $var wire 32 n iddr_ratio [31:0] $end
   $var wire  1 T lane0_d $end
   $var wire  1 X lane0_n $end
   $var wire  1 W lane0_p $end
   $var wire  8 o lane0byte [7:0] $end
   $var wire  1 V lane1_d $end
   $var wire  1 Z lane1_n $end
   $var wire  1 Y lane1_p $end
   $var wire  8 p lane1byte [7:0] $end
   $var wire  1 U mipi_clk $end
   $var wire  1 % mipi_clk_2 $end
   $var wire  1 e mipi_clk_4 $end
   $var wire  1 0 mipi_clk_8 $end
   $var wire 32 m mipi_frec [31:0] $end
   $var wire  2 # q_o_0 [1:0] $end
   $var wire  2 $ q_o_1 [1:0] $end
   $var wire  1 ] ram_clk $end
   $var wire  1 d rec_data $end
   $var wire  1 c rec_data_o $end
   $var wire  1 S reset $end
   $var wire  1 K stop_clk $end
   $var wire  1 H sync $end
   $var wire  1 R sys_clk $end
   $var wire  1 b termination $end
   $var wire  6 > type_w [5:0] $end
   $var wire  1 f valid $end
   $var wire 16 ? wordcount [15:0] $end
   $scope module BA0 $end
    $var wire  8 & byte_o [7:0] $end
    $var wire  8 & byte_r [7:0] $end
    $var wire  1 U mipi_clk $end
    $var wire  2 # q_o [1:0] $end
    $var wire  1 S reset $end
    $var wire  1 K stop $end
   $upscope $end
   $scope module BA1 $end
    $var wire  8 ' byte_o [7:0] $end
    $var wire  8 ' byte_r [7:0] $end
    $var wire  1 U mipi_clk $end
    $var wire  2 $ q_o [1:0] $end
    $var wire  1 S reset $end
    $var wire  1 K stop $end
   $upscope $end
   $scope module BAL0 $end
    $var wire  8 & byte_i [7:0] $end
    $var wire  8 I byte_o [7:0] $end
    $var wire  8 I byte_o_r [7:0] $end
    $var wire  8 . counter [7:0] $end
    $var wire  1 U mipi_clk $end
    $var wire  1 S reset $end
    $var wire  1 K stop $end
    $var wire  1 H sync $end
   $upscope $end
   $scope module BAL1 $end
    $var wire  8 ' byte_i [7:0] $end
    $var wire  8 J byte_o [7:0] $end
    $var wire  8 J byte_o_r [7:0] $end
    $var wire  8 / counter [7:0] $end
    $var wire  1 U mipi_clk $end
    $var wire  1 S reset $end
    $var wire  1 K stop $end
    $var wire  1 H sync $end
   $upscope $end
   $scope module DE $end
    $var wire  8 I byte_in0 [7:0] $end
    $var wire  8 J byte_in1 [7:0] $end
    $var wire 24 F correction [23:0] $end
    $var wire 32 C counter [31:0] $end
    $var wire 32 = data [31:0] $end
    $var wire 32 = data_r [31:0] $end
    $var wire  8 D ecc [7:0] $end
    $var wire  1 e mipi_clk_4 $end
    $var wire 32 @ out_r [31:0] $end
    $var wire 32 A out_r_old [31:0] $end
    $var wire 32 @ regheader [31:0] $end
    $var wire 32 G regheader_correct [31:0] $end
    $var wire  1 S reset $end
    $var wire  1 B start $end
    $var wire  1 K stop $end
    $var wire  1 H sync $end
    $var wire  8 E syndrom [7:0] $end
    $var wire  6 > type_o [5:0] $end
    $var wire  6 > type_o_r [5:0] $end
    $var wire  1 f valid $end
    $var wire  1 2 valid_r $end
    $var wire 16 ? wordcount [15:0] $end
    $var wire 16 ? wordcount_r [15:0] $end
   $upscope $end
   $scope module Prot $end
    $var wire 32 \ address_o [31:0] $end
    $var wire 16 < c [15:0] $end
    $var wire 32 : cX_r [31:0] $end
    $var wire 32 ; cY_r [31:0] $end
    $var wire 16 l c_calk [15:0] $end
    $var wire 32 7 count_val [31:0] $end
    $var wire 32 6 counter [31:0] $end
    $var wire 32 9 counter_addr [31:0] $end
    $var wire 32 = d [31:0] $end
    $var wire 32 = data [31:0] $end
    $var wire 32 [ data_o [31:0] $end
    $var wire 32 8 data_o_r [31:0] $end
    $var wire  1 a debug $end
    $var wire  1 ` debug1 $end
    $var wire  1 0 mipi_clk_8 $end
    $var wire  1 d rec_data $end
    $var wire  1 3 rec_data_r $end
    $var wire  1 S reset $end
    $var wire  1 4 state $end
    $var wire  1 K stop $end
    $var wire  6 > type_i [5:0] $end
    $var wire  1 f valid $end
    $var wire  1 5 valid_old $end
    $var wire 16 ? wordcount [15:0] $end
   $upscope $end
   $scope module RxFSM $end
    $var wire  8 x HEADER [7:0] $end
    $var wire  8 v LP00 [7:0] $end
    $var wire  8 u LP01 [7:0] $end
    $var wire  8 t LP11 [7:0] $end
    $var wire  8 w SYNC [7:0] $end
    $var wire  8 s TIMEOUT [7:0] $end
    $var wire 32 { Tdterm [31:0] $end
    $var wire 32 | Thssettle [31:0] $end
    $var wire 32 z Timeout [31:0] $end
    $var wire 32 y Tlpx [31:0] $end
    $var wire  1 R clk50MHz $end
    $var wire  1 ^ debug0 $end
    $var wire  1 N debug0_r $end
    $var wire  1 r debug1 $end
    $var wire  1 r debug1_r $end
    $var wire  1 X lane0_n $end
    $var wire  1 W lane0_p $end
    $var wire  1 Z lane1_n $end
    $var wire  1 Y lane1_p $end
    $var wire 32 m mipi_frec [31:0] $end
    $var wire  1 d rec_data $end
    $var wire  1 S reset $end
    $var wire  8 L state_mipi [7:0] $end
    $var wire  1 K stop_rx $end
    $var wire  1 K stop_rx_r $end
    $var wire  1 q stop_tran $end
    $var wire  1 b term $end
    $var wire  1 M term_r $end
    $var wire 32 Q timer_hs [31:0] $end
    $var wire 32 P timer_term [31:0] $end
    $var wire 32 O timer_tou [31:0] $end
   $upscope $end
   $scope module div2 $end
    $var wire  1 % CDIVX $end
    $var wire  1 U CLKI $end
    $var wire  1 S RST $end
    $var wire  8 ( counter [7:0] $end
   $upscope $end
   $scope module div4 $end
    $var wire  1 e CDIVX $end
    $var wire  1 % CLKI $end
    $var wire  1 S RST $end
    $var wire  8 g counter [7:0] $end
   $upscope $end
   $scope module div8 $end
    $var wire  1 0 CDIVX $end
    $var wire  1 e CLKI $end
    $var wire  1 S RST $end
    $var wire  8 1 counter [7:0] $end
   $upscope $end
   $scope module lane0 $end
    $var wire  8 ) byte_r [7:0] $end
    $var wire  2 h ddr [1:0] $end
    $var wire  1 T lane $end
    $var wire  1 U mipi_clk $end
    $var wire  2 # q_o [1:0] $end
    $var wire  2 # q_o_r [1:0] $end
    $var wire  1 S reset $end
    $var wire  1 K stop $end
    $var wire  1 H sync $end
    $var wire  1 H sync_r $end
    $scope module l0 $end
     $var wire  1 T D $end
     $var wire  1 * Q0 $end
     $var wire  1 * Q0_r $end
     $var wire  1 i Q1 $end
     $var wire  1 i Q1_r $end
     $var wire  1 } RST $end
     $var wire  1 U SCLK $end
    $upscope $end
   $upscope $end
   $scope module lane1 $end
    $var wire  8 , byte_r [7:0] $end
    $var wire  2 j ddr [1:0] $end
    $var wire  1 V lane $end
    $var wire  1 U mipi_clk $end
    $var wire  2 $ q_o [1:0] $end
    $var wire  2 $ q_o_r [1:0] $end
    $var wire  1 S reset $end
    $var wire  1 K stop $end
    $var wire  1 + sync $end
    $var wire  1 + sync_r $end
    $scope module l0 $end
     $var wire  1 V D $end
     $var wire  1 - Q0 $end
     $var wire  1 - Q0_r $end
     $var wire  1 k Q1 $end
     $var wire  1 k Q1_r $end
     $var wire  1 } RST $end
     $var wire  1 U SCLK $end
    $upscope $end
   $upscope $end
  $upscope $end
 $upscope $end
$enddefinitions $end


#1100
b00 #
b00 $
1%
b00000000 &
b00000000 '
b00000001 (
b00000000 )
0*
0+
b00000000 ,
0-
b00000000 .
b00000000 /
10
b00000001 1
02
03
04
05
b00000000000000000000000000000000 6
b00000000000000000000000000000000 7
b00000000000000000000000000000000 8
b00000000000000000000000000000000 9
b00000000000000000000000000000000 :
b00000000000000000000000000000000 ;
b1111111111111111 <
b00000000000000000000000000000000 =
b000000 >
b0000000000000000 ?
b00000000000000000000000000000000 @
b00000000000000000000000000000000 A
0B
b00000000000000000000000000000000 C
b00000000 D
b00000000 E
b000000000000000000000000 F
b00000000000000000000000000000000 G
0H
b00000000 I
b00000000 J
1K
b00000001 L
0M
0N
b00000000000000000000000000000000 O
b00000000000000000000000000000000 P
b00000000000000000000000000000000 Q
1R
0S
0T
1U
0V
1W
1X
1Y
1Z
b00000000000000000000000000000000 [
b00000000000000000000000000000000 \
1]
0^
0_
0`
0a
0b
0c
0d
1e
0f
b00000001 g
b00 h
0i
b00 j
0k
b0000001100100001 l
b00000000000000000000000011011000 m
b00000000000000000000000000000100 n
b00000000 o
b00000000 p
0q
0r
b00000000 s
b00000001 t
b00000010 u
b00000011 v
b00000100 w
b00000101 x
b00000000000000000000000000000010 y
b00000000000000000000000111001110 z
b00000000000000000000000000000010 {
b00000000000000000000000000000011 |
0}
#2200
0U
#3300
0%
b00000010 (
1U
#4400
0U
#5500
1%
b00000011 (
1U
0e
b00000010 g
#6600
0U
#7700
0%
b00000100 (
1U
#8800
0U
#9900
1%
b00000101 (
00
b00000010 1
0R
1U
0]
1e
b00000011 g
#11000
0U
#12100
0%
b00000110 (
1U
0W
0Y
#13200
0U
#14300
1%
b00000111 (
1U
0e
b00000100 g
#15400
0U
#16500
0%
b00001000 (
1U
#17600
0U
#18700
1%
b00001001 (
10
b00000011 1
b00000010 L
1R
1U
1]
1e
b00000101 g
#19800
0U
#20900
0%
b00001010 (
1U
#22000
0U
#23100
1%
b00001011 (
1U
0X
0Z
0e
b00000110 g
#24200
0U
#25300
0%
b00001100 (
1U
#26400
0U
#27500
1%
b00001101 (
00
b00000100 1
0R
1U
0]
1e
b00000111 g
#28600
0U
#29700
0%
b00001110 (
1U
#30800
0U
#31900
1%
b00001111 (
1U
0e
b00001000 g
#33000
0U
#34100
0%
b00010000 (
1U
#35200
0U
#36300
1%
b00010001 (
10
b00000101 1
b00000011 L
b00000000000000000000000000000001 O
b00000000000000000000000000000001 P
1R
1U
1]
1e
b00001001 g
#37400
0U
#38500
0%
b00010010 (
1U
#39600
0U
#40700
1%
b00010011 (
1U
0e
b00001010 g
#41800
0U
#42900
0%
b00010100 (
1U
#44000
0U
#45100
1%
b00010101 (
00
b00000110 1
0R
1U
0]
1e
b00001011 g
#46200
0U
#47300
0%
b00010110 (
1U
#48400
0U
#49500
1%
b00010111 (
1U
0e
b00001100 g
#50600
0U
#51700
0%
b00011000 (
1U
#52800
0U
#53900
1%
b00011001 (
10
b00000111 1
b00000000000000000000000000000010 O
b00000000000000000000000000000010 P
b00000000000000000000000000000001 Q
1R
1U
1]
1e
b00001101 g
#55000
0U
#56100
0%
b00011010 (
1U
#57200
0U
#58300
1%
b00011011 (
1U
0e
b00001110 g
#59400
0U
#60500
0%
b00011100 (
1U
#61600
0U
#62700
1%
b00011101 (
00
b00001000 1
0R
1U
0]
1e
b00001111 g
#63800
0U
#64900
0%
b00011110 (
1U
#66000
0U
#67100
1%
b00011111 (
1U
0e
b00010000 g
#68200
0U
#69300
0%
b00100000 (
1U
#70400
0U
#71500
1%
b00100001 (
10
b00001001 1
1M
b00000000000000000000000000000011 O
b00000000000000000000000000000011 P
b00000000000000000000000000000010 Q
1R
1U
1]
1b
1e
b00010001 g
#72600
0U
#73700
0%
b00100010 (
1U
#74800
0U
#75900
1%
b00100011 (
1U
0e
b00010010 g
#77000
0U
