Componets/HDMI_Transciever/TMDS_Encoder/TMDS_Encoder.v
module TMDS_Encoder(input clklow,input clkhigh,input reset,input [1:0]state
					,input[7:0] pix_data,input[1:0] H_VSync_Ctr,input[3:0] aux_data,output data_o);
///////////////////////////
	//reg[9:0] outreg;
	reg[9:0] q_m;
	reg[9:0] q_out;	
	integer cnt=0;
	integer cnt_old=0;	

	always @(posedge clklow) begin
		if(reset==1)begin			
		end 		
		else begin			
	    	case (state)
	    		'h0: begin	//h0 refers to Control Period coding
	    			case (H_VSync_Ctr)
	    				'h0: begin
	    					q_out='b1101010100;	
						end
						'h1: begin
							q_out='b0010101011;	
						end
						'h2: begin
							q_out='b0101010100;
						end
						'h3: begin						
							q_out='b1010101011;	
						end
						default: begin
						end
					endcase
				end
				'h1: begin	//h0 refers to Data Island coding	
					case (aux_data)
						'h0: begin
							q_out='b1010011100;	
						end
						'h1: begin
							q_out='b1001100011;	
						end
						'h2: begin
							q_out='b1011100100;
						end
						'h3: begin						
							q_out='b1011100010;	
						end
						'h4: begin						
							q_out='b0101110001;	
						end
						'h5: begin						
							q_out='b0100011110;	
						end
						'h6: begin						
							q_out='b0110001110;	
						end
						'h7: begin						
							q_out='b0100111100;	
						end
						'h8: begin						
							q_out='b1011001100;	
						end
						'h9: begin						
							q_out='b0100111001;	
						end
						'ha: begin						
							q_out='b0110011100;	
						end
						'hb: begin						
							q_out='b1011000110;	
						end
						'hc: begin						
							q_out='b1010001110;	
						end
						'hd: begin						
							q_out='b1001110001;	
						end
						'he: begin						
							q_out='b0101100011;	
						end
						'hf: begin						
							q_out='b1011000011;	
						end
						default: begin
						end
					endcase
				end
				'h2: begin	//h0 refers to Video Data coding	
					cnt_old=cnt;
					//cnt=cnt(pix_data);
					if ((N1(pix_data)>4) || (N1(pix_data)=='d4 && pix_data[0]=='b0)) begin
						q_m[0]=pix_data[0];
						q_m[1]=q_m[0]~^pix_data[1];
						q_m[2]=q_m[1]~^pix_data[2];
						q_m[3]=q_m[2]~^pix_data[3];
						q_m[4]=q_m[3]~^pix_data[4];
						q_m[5]=q_m[4]~^pix_data[5];
						q_m[6]=q_m[5]~^pix_data[6];
						q_m[7]=q_m[6]~^pix_data[7];
						q_m[8]='b1;											
					end else begin
						q_m[0]=pix_data[0];
						q_m[1]=q_m[0]^pix_data[1];
						q_m[2]=q_m[1]^pix_data[2];
						q_m[3]=q_m[2]^pix_data[3];
						q_m[4]=q_m[3]^pix_data[4];
						q_m[5]=q_m[4]^pix_data[5];
						q_m[6]=q_m[5]^pix_data[6];
						q_m[7]=q_m[6]^pix_data[7];
						q_m[8]='b1;	
					end
					if ((cnt_old==0)^(N1(q_m)==N0(q_m))) begin
						q_out[9]=!q_m[8];
						q_out[8]=q_m[8];
						q_out[7:2]=(q_m[8])?q_m[7:0]:~q_m[7:0];
						if (q_m[8]==0) begin
							cnt=cnt_old+(N0(q_m[7:0])-N1(q_m[7:0]));							
						end else begin
							cnt=cnt_old+(N1(q_m[7:0])-N0(q_m[7:0]));							
						end					
					end else begin
						if (cnt_old>0 && (N1(q_m[7:0]>N0(q_m[7:0])))||(cnt_old<0 && (N0(q_m[7:0]>N1(q_m[7:0]))))) begin
							q_out[9]='b1;
							q_out[8]=q_m[8];
							q_out[7:0]=~q_m[7:0];
							cnt=cnt_old+2*q_m[8]+N0(q_m[7:0])-N1(q_m[7:0]);
						end else begin
							q_out[9]='b0;
							q_out[8]=q_m[8];
							q_out[7:0]=~q_m[7:0];
							cnt=cnt_old+2*(~q_m[8])+N1(q_m[7:0])-N0(q_m[7:0]);
						end						
					end				
				end
				default: begin
				end
				endcase
				 
		end
	end
	
	always @(posedge clkhigh) begin
	if (reset==1) begin
		end else begin			
			//q_out={'b0,q_out[9:1]};
			q_out={'b0,q_out[9:1]};
			
		end
	end
	assign data_o =q_out[0];
endmodule


function integer N0 (reg [7:0 ]data);
	integer counter;
	for (counter=0; counter<8; counter++) begin
		if(data[counter]==0) begin
		N0=N0+1;
	end
		end
endfunction

function integer N1 (reg [7:0 ]data);
	integer counter;
	for (counter=0; counter<8; counter++) begin
		if(data[counter]==1) begin
		N1=N1+1;
	end
		end
endfunction

Componets/HDMI_Transciever/TMDS_Encoder/blinky.vcd
$version Generated by VerilatedVcd $end
$date Sat Oct 29 00:10:39 2022
 $end
$timescale   1ps $end

 $scope module TOP $end
  $var wire  2 + H_VSync_Ctr [1:0] $end
  $var wire  4 , aux_data [3:0] $end
  $var wire  1 ' clkhigh $end
  $var wire  1 & clklow $end
  $var wire  1 - data_o $end
  $var wire  8 * pix_data [7:0] $end
  $var wire  1 ( reset $end
  $var wire  2 ) state [1:0] $end
  $scope module TMDS_Encoder $end
   $var wire  2 + H_VSync_Ctr [1:0] $end
   $var wire  4 , aux_data [3:0] $end
   $var wire  1 ' clkhigh $end
   $var wire  1 & clklow $end
   $var wire 32 $ cnt [31:0] $end
   $var wire 32 % cnt_old [31:0] $end
   $var wire  1 - data_o $end
   $var wire  8 * pix_data [7:0] $end
   $var wire 10 # q_m [9:0] $end
   $var wire 10 . q_out [9:0] $end
   $var wire  1 ( reset $end
   $var wire  2 ) state [1:0] $end
  $upscope $end
 $upscope $end
$enddefinitions $end


#10
b0100010111 #
b11111111111111111111111111111100 $
b00000000000000000000000000000000 %
1&
1'
0(
b10 )
b00111001 *
b00 +
b0000 ,
0-
b0111101000 .
#15
0'
#20
1'
b0011110100 .
#25
0'
#30
1'
b0001111010 .
#35
0'
#40
1'
1-
b0000111101 .
#45
0'
#50
1'
0-
b0000011110 .
#55
0'
#60
0&
1'
1-
b0000001111 .
#65
0'
#70
1'
b0000000111 .
#75
0'
#80
1'
b0000000011 .
#85
0'
#90
1'
b0000000001 .
#95
0'
#100
1'
0-
b0000000000 .
#105
0'
#110
b11111111111111111111111111111100 %
1&
1'
b0101011100 .
#115
0'
#120
1'
b0010101110 .
#125
0'
#130
1'
1-
b0001010111 .
#135
0'
#140
1'
b0000101011 .
#145
0'
#150
1'
b0000010101 .
#155
0'
#160
0&
1'
0-
b0000001010 .
#165
0'
#170
1'
1-
b0000000101 .
#175
0'
#180
1'
0-
b0000000010 .
#185
0'
#190
1'
1-
b0000000001 .
#195
0'
#200
1'
0-
b0000000000 .
#205
0'
#210
1&
1'
b0101011100 .
#215
0'
#220
1'
b0010101110 .
#225
0'
#230
1'
1-
b0001010111 .
#235
0'
#240
1'
b0000101011 .
#245
0'
#250
1'
b0000010101 .
#255
0'
#260
0&
1'
0-
b0000001010 .
#265
0'
#270
1'
1-
b0000000101 .
#275
0'
#280
1'
0-
b0000000010 .
#285
0'
#290
1'
1-
b0000000001 .
#295
0'
#300
1'
0-
b0000000000 .
#305
0'
#310
1&
1'
b0101011100 .
#315
0'
#320
1'
b0010101110 .
#325
0'
#330
1'
1-
b0001010111 .
#335
0'
#340
1'
b0000101011 .
#345
0'
#350
1'
b0000010101 .
#355
0'
#360
0&
1'
0-
b0000001010 .
#365
0'
#370
1'
1-
b0000000101 .
#375
0'
#380
1'
0-
b0000000010 .
#385
0'
#390
1'
1-
b0000000001 .
#395
0'
#400
1'
0-
b0000000000 .
#405
0'
#410
1&
1'
b0101011100 .
#415
0'
#420
1'
b0010101110 .
#425
0'
#430
1'
1-
b0001010111 .
#435
0'
#440
1'
b0000101011 .
#445
0'
#450
1'
b0000010101 .
#455
0'
#460
0&
1'
0-
b0000001010 .
#465
0'
#470
1'
1-
b0000000101 .
#475
0'
#480
1'
0-
b0000000010 .
#485
0'
#490
1'
1-
b0000000001 .
#495
0'
#500
1'
0-
b0000000000 .
#505
0'
#510
1&
1'
b0101011100 .
#515
0'
#520
1'
b0010101110 .
#525
0'
#530
1'
1-
b0001010111 .
#535
0'
#540
1'
b0000101011 .
#545
0'
#550
1'
b0000010101 .
#555
0'
#560
0&
1'
0-
b0000001010 .
#565
0'
#570
1'
1-
b0000000101 .
#575
0'
#580
1'
0-
b0000000010 .
#585
0'
#590
1'
1-
b0000000001 .
#595
0'
#600
1'
0-
b0000000000 .
#605
0'
#610
1&
1'
b0101011100 .
#615
0'
#620
1'
b0010101110 .
#625
0'
#630
1'
1-
b0001010111 .
#635
0'
#640
1'
b0000101011 .
#645
0'
#650
1'
b0000010101 .
#655
0'
#660
0&
1'
0-
b0000001010 .
#665
0'
#670
1'
1-
b0000000101 .
#675
0'
#680
1'
0-
b0000000010 .
#685
0'
#690
1'
1-
b0000000001 .
#695
0'
#700
1'
0-
b0000000000 .
#705
0'
#710
1&
1'
b0101011100 .
#715
0'
#720
1'
b0010101110 .
#725
0'
#730
1'
1-
b0001010111 .
#735
0'
#740
1'
b0000101011 .
#745
0'
#750
1'
b0000010101 .
#755
0'
#760
0&
1'
0-
b0000001010 .
#765
0'
#770
1'
1-
b0000000101 .
#775
0'
#780
1'
0-
b0000000010 .
#785
0'
#790
1'
1-
b0000000001 .
#795
0'
#800
1'
0-
b0000000000 .
#805
0'
#810
1&
1'
b0101011100 .
#815
0'
#820
1'
b0010101110 .
#825
0'
#830
1'
1-
b0001010111 .
#835
0'
#840
1'
b0000101011 .
#845
0'
#850
1'
b0000010101 .
#855
0'
#860
0&
1'
0-
b0000001010 .
#865
0'
#870
1'
1-
b0000000101 .
#875
0'
#880
1'
0-
b0000000010 .
#885
0'
#890
1'
1-
b0000000001 .
#895
0'
#900
1'
0-
b0000000000 .
#905
0'
#910
1&
1'
b0101011100 .
#915
0'
#920
1'
b0010101110 .
#925
0'
#930
1'
1-
b0001010111 .
#935
0'
#940
1'
b0000101011 .
#945
0'
#950
1'
b0000010101 .
#955
0'
#960
0&
1'
0-
b0000001010 .
#965
0'
#970
1'
1-
b0000000101 .
#975
0'
#980
1'
0-
b0000000010 .
#985
0'
#990
1'
1-
b0000000001 .
#995
0'
#1000
1'
0-
b0000000000 .
#1005
0'
#1010
1&
1'
b0101011100 .
#1015
0'
#1020
1'
b0010101110 .
#1025
0'
#1030
1'
1-
b0001010111 .
#1035
0'
#1040
1'
b0000101011 .
#1045
0'
#1050
1'
b0000010101 .
#1055
0'
#1060
0&
1'
0-
b0000001010 .
#1065
0'
#1070
1'
1-
b0000000101 .
#1075
0'
#1080
1'
0-
b0000000010 .
#1085
0'
#1090
1'
1-
b0000000001 .
#1095
0'
#1100
1'
0-
b0000000000 .
#1105
0'
#1110
1&
1'
b0101011100 .
#1115
0'
#1120
1'
b0010101110 .
#1125
0'
#1130
1'
1-
b0001010111 .
#1135
0'
#1140
1'
b0000101011 .
#1145
0'
#1150
1'
b0000010101 .
#1155
0'
#1160
0&
1'
0-
b0000001010 .
#1165
0'
#1170
1'
1-
b0000000101 .
#1175
0'
#1180
1'
0-
b0000000010 .
#1185
0'
#1190
1'
1-
b0000000001 .
#1195
0'
#1200
1'
0-
b0000000000 .
#1205
0'
#1210
1&
1'
b0101011100 .
#1215
0'
#1220
1'
b0010101110 .
#1225
0'
#1230
1'
1-
b0001010111 .
#1235
0'
#1240
1'
b0000101011 .
#1245
0'
#1250
1'
b0000010101 .
#1255
0'
#1260
0&
1'
0-
b0000001010 .
#1265
0'
#1270
1'
1-
b0000000101 .
#1275
0'
#1280
1'
0-
b0000000010 .
#1285
0'
#1290
1'
1-
b0000000001 .
#1295
0'
#1300
1'
0-
b0000000000 .
#1305
0'
#1310
1&
1'
b0101011100 .
#1315
0'
#1320
1'
b0010101110 .
#1325
0'
#1330
1'
1-
b0001010111 .
#1335
0'
#1340
1'
b0000101011 .
#1345
0'
#1350
1'
b0000010101 .
#1355
0'
#1360
0&
1'
0-
b0000001010 .
#1365
0'
#1370
1'
1-
b0000000101 .
#1375
0'
#1380
1'
0-
b0000000010 .
#1385
0'
#1390
1'
1-
b0000000001 .
#1395
0'
#1400
1'
0-
b0000000000 .
#1405
0'
#1410
1&
1'
b0101011100 .
#1415
0'
#1420
1'
b0010101110 .
#1425
0'
#1430
1'
1-
b0001010111 .
#1435
0'
#1440
1'
b0000101011 .
#1445
0'
#1450
1'
b0000010101 .
#1455
0'
#1460
0&
1'
0-
b0000001010 .
#1465
0'
#1470
1'
1-
b0000000101 .
#1475
0'
#1480
1'
0-
b0000000010 .
#1485
0'
#1490
1'
1-
b0000000001 .
#1495
0'
#1500
1'
0-
b0000000000 .
#1505
0'
#1510
1&
1'
b0101011100 .
#1515
0'
#1520
1'
b0010101110 .
#1525
0'
#1530
1'
1-
b0001010111 .
#1535
0'
#1540
1'
b0000101011 .
#1545
0'
#1550
1'
b0000010101 .
#1555
0'
#1560
0&
1'
0-
b0000001010 .
#1565
0'
#1570
1'
1-
b0000000101 .
#1575
0'
#1580
1'
0-
b0000000010 .
#1585
0'
#1590
1'
1-
b0000000001 .
#1595
0'
#1600
1'
0-
b0000000000 .
#1605
0'
#1610
1&
1'
b0101011100 .
#1615
0'
#1620
1'
b0010101110 .
#1625
0'
#1630
1'
1-
b0001010111 .
#1635
0'
#1640
1'
b0000101011 .
#1645
0'
#1650
1'
b0000010101 .
#1655
0'
#1660
0&
1'
0-
b0000001010 .
#1665
0'
#1670
1'
1-
b0000000101 .
#1675
0'
#1680
1'
0-
b0000000010 .
#1685
0'
#1690
1'
1-
b0000000001 .
#1695
0'
#1700
1'
0-
b0000000000 .
#1705
0'
#1710
1&
1'
b0101011100 .
#1715
0'
#1720
1'
b0010101110 .
#1725
0'
#1730
1'
1-
b0001010111 .
#1735
0'
#1740
1'
b0000101011 .
#1745
0'
#1750
1'
b0000010101 .
#1755
0'
#1760
0&
1'
0-
b0000001010 .
#1765
0'
#1770
1'
1-
b0000000101 .
#1775
0'
#1780
1'
0-
b0000000010 .
#1785
0'
#1790
1'
1-
b0000000001 .
#1795
0'
#1800
1'
0-
b0000000000 .
#1805
0'
#1810
1&
1'
b0101011100 .
#1815
0'
#1820
1'
b0010101110 .
#1825
0'
#1830
1'
1-
b0001010111 .
#1835
0'
#1840
1'
b0000101011 .
#1845
0'
#1850
1'
b0000010101 .
#1855
0'
#1860
0&
1'
0-
b0000001010 .
#1865
0'
#1870
1'
1-
b0000000101 .
#1875
0'
#1880
1'
0-
b0000000010 .
#1885
0'
#1890
1'
1-
b0000000001 .
#1895
0'
#1900
1'
0-
b0000000000 .
#1905
0'
#1910
1&
1'
b0101011100 .
#1915
0'
#1920
1'
b0010101110 .
#1925
0'
#1930
1'
1-
b0001010111 .
#1935
0'
#1940
1'
b0000101011 .
#1945
0'
#1950
1'
b0000010101 .
#1955
0'
#1960
0&
1'
0-
b0000001010 .
#1965
0'
#1970
1'
1-
b0000000101 .
#1975
0'
#1980
1'
0-
b0000000010 .
#1985
0'
#1990
1'
1-
b0000000001 .
#1995
0'
#2000
1'
0-
b0000000000 .
#2005
0'
#2010
1&
1'
b0101011100 .
#2015
0'
#2020
1'
b0010101110 .
#2025
0'
#2030
1'
1-
b0001010111 .
#2035
0'
#2040
1'
b0000101011 .
#2045
0'
#2050
1'
b0000010101 .
#2055
0'
#2060
0&
1'
0-
b0000001010 .
#2065
0'
#2070
1'
1-
b0000000101 .
#2075
0'
#2080
1'
0-
b0000000010 .
#2085
0'
#2090
1'
1-
b0000000001 .
#2095
0'
#2100
1'
0-
b0000000000 .
#2105
0'
#2110
1&
1'
b0101011100 .
#2115
0'
#2120
1'
b0010101110 .
#2125
0'
#2130
1'
1-
b0001010111 .
#2135
0'
#2140
1'
b0000101011 .
#2145
0'
#2150
1'
b0000010101 .
#2155
0'
#2160
0&
1'
0-
b0000001010 .
#2165
0'
#2170
1'
1-
b0000000101 .
#2175
0'
#2180
1'
0-
b0000000010 .
#2185
0'
#2190
1'
1-
b0000000001 .
#2195
0'
#2200
1'
0-
b0000000000 .
#2205
0'
#2210
1&
1'
b0101011100 .
#2215
0'
#2220
1'
b0010101110 .
#2225
0'
#2230
1'
1-
b0001010111 .
#2235
0'
#2240
1'
b0000101011 .
#2245
0'
#2250
1'
b0000010101 .
#2255
0'
#2260
0&
1'
0-
b0000001010 .
#2265
0'
#2270
1'
1-
b0000000101 .
#2275
0'
#2280
1'
0-
b0000000010 .
#2285
0'
#2290
1'
1-
b0000000001 .
#2295
0'
#2300
1'
0-
b0000000000 .
#2305
0'
#2310
1&
1'
b0101011100 .
#2315
0'
#2320
1'
b0010101110 .
#2325
0'
#2330
1'
1-
b0001010111 .
#2335
0'
#2340
1'
b0000101011 .
#2345
0'
#2350
1'
b0000010101 .
#2355
0'
#2360
0&
1'
0-
b0000001010 .
#2365
0'
#2370
1'
1-
b0000000101 .
#2375
0'
#2380
1'
0-
b0000000010 .
#2385
0'
#2390
1'
1-
b0000000001 .
#2395
0'
#2400
1'
0-
b0000000000 .
#2405
0'
#2410
1&
1'
b0101011100 .
#2415
0'
#2420
1'
b0010101110 .
#2425
0'
#2430
1'
1-
b0001010111 .
#2435
0'
#2440
1'
b0000101011 .
#2445
0'
#2450
1'
b0000010101 .
#2455
0'
#2460
0&
1'
0-
b0000001010 .
#2465
0'
#2470
1'
1-
b0000000101 .
#2475
0'
#2480
1'
0-
b0000000010 .
#2485
0'
#2490
1'
1-
b0000000001 .
#2495
0'
#2500
1'
0-
b0000000000 .
#2505
0'
#2510
1&
1'
b0101011100 .
#2515
0'
#2520
1'
b0010101110 .
#2525
0'
#2530
1'
1-
b0001010111 .
#2535
0'
#2540
1'
b0000101011 .
#2545
0'
#2550
1'
b0000010101 .
#2555
0'
#2560
0&
1'
0-
b0000001010 .
#2565
0'
#2570
1'
1-
b0000000101 .
#2575
0'
#2580
1'
0-
b0000000010 .
#2585
0'
#2590
1'
1-
b0000000001 .
#2595
0'
#2600
1'
0-
b0000000000 .
#2605
0'
#2610
1&
1'
b0101011100 .
#2615
0'
#2620
1'
b0010101110 .
#2625
0'
#2630
1'
1-
b0001010111 .
#2635
0'
#2640
1'
b0000101011 .
#2645
0'
#2650
1'
b0000010101 .
#2655
0'
#2660
0&
1'
0-
b0000001010 .
#2665
0'
#2670
1'
1-
b0000000101 .
#2675
0'
#2680
1'
0-
b0000000010 .
#2685
0'
#2690
1'
1-
b0000000001 .
#2695
0'
#2700
1'
0-
b0000000000 .
#2705
0'
#2710
1&
1'
b0101011100 .
#2715
0'
#2720
1'
b0010101110 .
#2725
0'
#2730
1'
1-
b0001010111 .
#2735
0'
#2740
1'
b0000101011 .
#2745
0'
#2750
1'
b0000010101 .
#2755
0'
#2760
0&
1'
0-
b0000001010 .
#2765
0'
#2770
1'
1-
b0000000101 .
#2775
0'
#2780
1'
0-
b0000000010 .
#2785
0'
#2790
1'
1-
b0000000001 .
#2795
0'
#2800
1'
0-
b0000000000 .
#2805
0'
#2810
1&
1'
b0101011100 .
#2815
0'
#2820
1'
b0010101110 .
#2825
0'
#2830
1'
1-
b0001010111 .
#2835
0'
#2840
1'
b0000101011 .
#2845
0'
#2850
1'
b0000010101 .
#2855
0'
#2860
0&
1'
0-
b0000001010 .
#2865
0'
#2870
1'
1-
b0000000101 .
#2875
0'
#2880
1'
0-
b0000000010 .
#2885
0'
#2890
1'
1-
b0000000001 .
#2895
0'
#2900
1'
0-
b0000000000 .
#2905
0'
#2910
1&
1'
b0101011100 .
#2915
0'
#2920
1'
b0010101110 .
#2925
0'
#2930
1'
1-
b0001010111 .
#2935
0'
#2940
1'
b0000101011 .
#2945
0'
#2950
1'
b0000010101 .
#2955
0'
#2960
0&
1'
0-
b0000001010 .
#2965
0'
#2970
1'
1-
b0000000101 .
#2975
0'
#2980
1'
0-
b0000000010 .
#2985
0'
#2990
1'
1-
b0000000001 .
#2995
0'
#3000
1'
0-
b0000000000 .
#3005
0'
#3010
1&
1'
b0101011100 .
#3015
0'
#3020
1'
b0010101110 .
#3025
0'
#3030
1'
1-
b0001010111 .
#3035
0'
#3040
1'
b0000101011 .
#3045
0'
#3050
1'
b0000010101 .
#3055
0'
#3060
0&
1'
0-
b0000001010 .
#3065
0'
#3070
1'
1-
b0000000101 .
#3075
0'
#3080
1'
0-
b0000000010 .
#3085
0'
#3090
1'
1-
b0000000001 .
#3095
0'
#3100
1'
0-
b0000000000 .
#3105
0'
#3110
1&
1'
b0101011100 .
#3115
0'
#3120
1'
b0010101110 .
#3125
0'
#3130
1'
1-
b0001010111 .
#3135
0'
#3140
1'
b0000101011 .
#3145
0'
#3150
1'
b0000010101 .
#3155
0'
#3160
0&
1'
0-
b0000001010 .
#3165
0'
#3170
1'
1-
b0000000101 .
#3175
0'
#3180
1'
0-
b0000000010 .
#3185
0'
#3190
1'
1-
b0000000001 .
#3195
0'
#3200
1'
0-
b0000000000 .
#3205
0'
#3210
1&
1'
b0101011100 .
#3215
0'
#3220
1'
b0010101110 .
#3225
0'
#3230
1'
1-
b0001010111 .
#3235
0'
#3240
1'
b0000101011 .
#3245
0'
#3250
1'
b0000010101 .
#3255
0'
#3260
0&
1'
0-
b0000001010 .
#3265
0'
#3270
1'
1-
b0000000101 .
#3275
0'
#3280
1'
0-
b0000000010 .
#3285
0'
#3290
1'
1-
b0000000001 .
#3295
0'
#3300
1'
0-
b0000000000 .
#3305
0'
#3310
1&
1'
b0101011100 .
#3315
0'
#3320
1'
b0010101110 .
#3325
0'
#3330
1'
1-
b0001010111 .
#3335
0'
#3340
1'
b0000101011 .
#3345
0'
#3350
1'
b0000010101 .
#3355
0'
#3360
0&
1'
0-
b0000001010 .
#3365
0'
#3370
1'
1-
b0000000101 .
#3375
0'
#3380
1'
0-
b0000000010 .
#3385
0'
#3390
1'
1-
b0000000001 .
#3395
0'
#3400
1'
0-
b0000000000 .
#3405
0'
#3410
1&
1'
b0101011100 .
#3415
0'
#3420
1'
b0010101110 .
#3425
0'
#3430
1'
1-
b0001010111 .
#3435
0'
#3440
1'
b0000101011 .
#3445
0'
#3450
1'
b0000010101 .
#3455
0'
#3460
0&
1'
0-
b0000001010 .
#3465
0'
#3470
1'
1-
b0000000101 .
#3475
0'
#3480
1'
0-
b0000000010 .
#3485
0'
#3490
1'
1-
b0000000001 .
#3495
0'
#3500
1'
0-
b0000000000 .
#3505
0'
#3510
1&
1'
b0101011100 .
#3515
0'
#3520
1'
b0010101110 .
#3525
0'
#3530
1'
1-
b0001010111 .
#3535
0'
#3540
1'
b0000101011 .
#3545
0'
#3550
1'
b0000010101 .
#3555
0'
#3560
0&
1'
0-
b0000001010 .
#3565
0'
#3570
1'
1-
b0000000101 .
#3575
0'
#3580
1'
0-
b0000000010 .
#3585
0'
#3590
1'
1-
b0000000001 .
#3595
0'
#3600
1'
0-
b0000000000 .
#3605
0'
#3610
1&
1'
b0101011100 .
#3615
0'
#3620
1'
b0010101110 .
#3625
0'
#3630
1'
1-
b0001010111 .
#3635
0'
#3640
1'
b0000101011 .
#3645
0'
#3650
1'
b0000010101 .
#3655
0'
#3660
0&
1'
0-
b0000001010 .
#3665
0'
#3670
1'
1-
b0000000101 .
#3675
0'
#3680
1'
0-
b0000000010 .
#3685
0'
#3690
1'
1-
b0000000001 .
#3695
0'
#3700
1'
0-
b0000000000 .
#3705
0'
#3710
1&
1'
b0101011100 .
#3715
0'
#3720
1'
b0010101110 .
#3725
0'
#3730
1'
1-
b0001010111 .
#3735
0'
#3740
1'
b0000101011 .
#3745
0'
#3750
1'
b0000010101 .
#3755
0'
#3760
0&
1'
0-
b0000001010 .
#3765
0'
#3770
1'
1-
b0000000101 .
#3775
0'
#3780
1'
0-
b0000000010 .
#3785
0'
#3790
1'
1-
b0000000001 .
#3795
0'
#3800
1'
0-
b0000000000 .
#3805
0'
#3810
1&
1'
b0101011100 .
#3815
0'
#3820
1'
b0010101110 .
#3825
0'
#3830
1'
1-
b0001010111 .
#3835
0'
#3840
1'
b0000101011 .
#3845
0'
#3850
1'
b0000010101 .
#3855
0'
#3860
0&
1'
0-
b0000001010 .
#3865
0'
#3870
1'
1-
b0000000101 .
#3875
0'
#3880
1'
0-
b0000000010 .
#3885
0'
#3890
1'
1-
b0000000001 .
#3895
0'
#3900
1'
0-
b0000000000 .
#3905
0'
#3910
1&
1'
b0101011100 .
#3915
0'
#3920
1'
b0010101110 .
#3925
0'
#3930
1'
1-
b0001010111 .
#3935
0'
#3940
1'
b0000101011 .
#3945
0'
#3950
1'
b0000010101 .
#3955
0'
#3960
0&
1'
0-
b0000001010 .
#3965
0'
#3970
1'
1-
b0000000101 .
#3975
0'
#3980
1'
0-
b0000000010 .
#3985
0'
#3990
1'
1-
b0000000001 .
#3995
0'
#4000
1'
0-
b0000000000 .
#4005
0'
#4010
1&
1'
b0101011100 .
#4015
0'
#4020
1'
b0010101110 .
#4025
0'
#4030
1'
1-
b0001010111 .
#4035
0'
#4040
1'
b0000101011 .
#4045
0'
#4050
1'
b0000010101 .
#4055
0'
#4060
0&
1'
0-
b0000001010 .
#4065
0'
#4070
1'
1-
b0000000101 .
#4075
0'
#4080
1'
0-
b0000000010 .
#4085
0'
#4090
1'
1-
b0000000001 .
#4095
0'
#4100
1'
0-
b0000000000 .
#4105
0'
#4110
1&
1'
b0101011100 .
#4115
0'
#4120
1'
b0010101110 .
#4125
0'
#4130
1'
1-
b0001010111 .
#4135
0'
#4140
1'
b0000101011 .
#4145
0'
#4150
1'
b0000010101 .
#4155
0'
#4160
0&
1'
0-
b0000001010 .
#4165
0'
#4170
1'
1-
b0000000101 .
#4175
0'
#4180
1'
0-
b0000000010 .
#4185
0'
#4190
1'
1-
b0000000001 .
#4195
0'
#4200
1'
0-
b0000000000 .
#4205
0'
#4210
1&
1'
b0101011100 .
#4215
0'
#4220
1'
b0010101110 .
#4225
0'
#4230
1'
1-
b0001010111 .
#4235
0'
#4240
1'
b0000101011 .
#4245
0'
#4250
1'
b0000010101 .
#4255
0'
#4260
0&
1'
0-
b0000001010 .
#4265
0'
#4270
1'
1-
b0000000101 .
#4275
0'
#4280
1'
0-
b0000000010 .
#4285
0'
#4290
1'
1-
b0000000001 .
#4295
0'
#4300
1'
0-
b0000000000 .
#4305
0'
#4310
1&
1'
b0101011100 .
#4315
0'
#4320
1'
b0010101110 .
#4325
0'
#4330
1'
1-
b0001010111 .
#4335
0'
#4340
1'
b0000101011 .
#4345
0'
#4350
1'
b0000010101 .
#4355
0'
#4360
0&
1'
0-
b0000001010 .
#4365
0'
#4370
1'
1-
b0000000101 .
#4375
0'
#4380
1'
0-
b0000000010 .
#4385
0'
#4390
1'
1-
b0000000001 .
#4395
0'
#4400
1'
0-
b0000000000 .
#4405
0'
#4410
1&
1'
b0101011100 .
#4415
0'
#4420
1'
b0010101110 .
#4425
0'
#4430
1'
1-
b0001010111 .
#4435
0'
#4440
1'
b0000101011 .
#4445
0'
#4450
1'
b0000010101 .
#4455
0'
#4460
0&
1'
0-
b0000001010 .
#4465
0'
#4470
1'
1-
b0000000101 .
#4475
0'
#4480
1'
0-
b0000000010 .
#4485
0'
#4490
1'
1-
b0000000001 .
#4495
0'
#4500
1'
0-
b0000000000 .
#4505
0'
#4510
1&
1'
b0101011100 .
#4515
0'
#4520
1'
b0010101110 .
#4525
0'
#4530
1'
1-
b0001010111 .
#4535
0'
#4540
1'
b0000101011 .
#4545
0'
#4550
1'
b0000010101 .
#4555
0'
#4560
0&
1'
0-
b0000001010 .
#4565
0'
#4570
1'
1-
b0000000101 .
#4575
0'
#4580
1'
0-
b0000000010 .
#4585
0'
#4590
1'
1-
b0000000001 .
#4595
0'
#4600
1'
0-
b0000000000 .
#4605
0'
#4610
1&
1'
b0101011100 .
#4615
0'
#4620
1'
b0010101110 .
#4625
0'
#4630
1'
1-
b0001010111 .
#4635
0'
#4640
1'
b0000101011 .
#4645
0'
#4650
1'
b0000010101 .
#4655
0'
#4660
0&
1'
0-
b0000001010 .
#4665
0'
#4670
1'
1-
b0000000101 .
#4675
0'
#4680
1'
0-
b0000000010 .
#4685
0'
#4690
1'
1-
b0000000001 .
#4695
0'
#4700
1'
0-
b0000000000 .
#4705
0'
#4710
1&
1'
b0101011100 .
#4715
0'
#4720
1'
b0010101110 .
#4725
0'
#4730
1'
1-
b0001010111 .
#4735
0'
#4740
1'
b0000101011 .
#4745
0'
#4750
1'
b0000010101 .
#4755
0'
#4760
0&
1'
0-
b0000001010 .
#4765
0'
#4770
1'
1-
b0000000101 .
#4775
0'
#4780
1'
0-
b0000000010 .
#4785
0'
#4790
1'
1-
b0000000001 .
#4795
0'
#4800
1'
0-
b0000000000 .
#4805
0'
#4810
1&
1'
b0101011100 .
#4815
0'
#4820
1'
b0010101110 .
#4825
0'
#4830
1'
1-
b0001010111 .
#4835
0'
#4840
1'
b0000101011 .
#4845
0'
#4850
1'
b0000010101 .
#4855
0'
#4860
0&
1'
0-
b0000001010 .
#4865
0'
#4870
1'
1-
b0000000101 .
#4875
0'
#4880
1'
0-
b0000000010 .
#4885
0'
#4890
1'
1-
b0000000001 .
#4895
0'
#4900
1'
0-
b0000000000 .
#4905
0'
#4910
1&
1'
b0101011100 .
#4915
0'
#4920
1'
b0010101110 .
#4925
0'
#4930
1'
1-
b0001010111 .
#4935
0'
#4940
1'
b0000101011 .
#4945
0'
#4950
1'
b0000010101 .
#4955
0'
#4960
0&
1'
0-
b0000001010 .
#4965
0'
#4970
1'
1-
b0000000101 .
#4975
0'
#4980
1'
0-
b0000000010 .
#4985
0'
#4990
1'
1-
b0000000001 .
#4995
0'
#5000
1'
0-
b0000000000 .
#5005
0'
#5010
1&
1'
b0101011100 .
#5015
0'
#5020
1'
b0010101110 .
#5025
0'
#5030
1'
1-
b0001010111 .
#5035
0'
#5040
1'
b0000101011 .
#5045
0'
#5050
1'
b0000010101 .
#5055
0'
#5060
0&
1'
0-
b0000001010 .
#5065
0'
#5070
1'
1-
b0000000101 .
#5075
0'
#5080
1'
0-
b0000000010 .
#5085
0'
#5090
1'
1-
b0000000001 .
#5095
0'
#5100
1'
0-
b0000000000 .
#5105
0'
#5110
1&
1'
b0101011100 .
#5115
0'
#5120
1'
b0010101110 .
#5125
0'
