Componets/MIPI-CSI-Transciever/MIPI_Reciever/MIPI_Reciever.v
module MIPI_Reciever(input bit_clk,mipi_clk,reset,lane0_d,lane1_d,inout  lane0_p,lane0_n,lane1_p,lane1_n,output[7:0] red,output[7:0] green,output[7:0] blue,output[7:0] adress_out,output reg debug0,debug1,debug2,output termination);
reg[7:0] bytereg0=0;
reg[7:0] bytereg1=0;
reg[7:0] bytereg=0;

integer delay_mipi=0;
reg end_data;
reg[7:0] state_mipi=TIMEOUT;
reg[7:0] state_mipi_sync=MIPI_IDLE;
integer allign_cnt=0;
reg termination_r=0;
reg lane0_pr,lane0_nr,lane1_pr,lane1_nr;
assign termination=termination_r;
reg start_clk=0;
reg stop_clk=0;
reg FS_detect,Eot_detect,sync_detect;
reg[24:0] addres=0;
reg[39:0] regheader=0;
wire[7:0] ecc;
reg[31:0] wordcount;
wire[1:0] lane0ddr;
wire[1:0] lane1ddr;
reg[7:0] timer0,timer1,timer2;//timeout termination hs-prepare
    //ECLKSYNCB ECLKS(.ECLKI(mipi_clk),.STOP(startclk),.ECLKO(clk_mipi_o));
    IDDRX1F l0(.D(lane0_d),.SCLK(mipi_clk),.Q0(lane0ddr[1]),.Q1(lane0ddr[0]),.RST('b0));
    IDDRX1F l1(.D(lane1_d),.SCLK(mipi_clk),.Q0(lane1ddr[0]),.Q1(lane1ddr[1]),.RST('b0));
    assign ecc[0]=regheader[0]^regheader[1]^regheader[2]^regheader[4]^regheader[5]^regheader[7]^regheader[10]^regheader[11]^regheader[13]^regheader[16]^
		regheader[20]^regheader[21]^regheader[22]^regheader[23];
	assign ecc[1]=regheader[0]^regheader[1]^regheader[3]^regheader[4]^regheader[6]^regheader[8]^regheader[10]^regheader[12]^regheader[14]^regheader[17]^
		regheader[20]^regheader[21]^regheader[22]^regheader[23];
	assign ecc[2]=regheader[0]^regheader[2]^regheader[3]^regheader[5]^regheader[6]^regheader[9]^regheader[11]^regheader[12]^regheader[15]^regheader[18]^
		regheader[20]^regheader[21]^regheader[22];
	assign ecc[3]=regheader[1]^regheader[2]^regheader[3]^regheader[7]^regheader[8]^regheader[9]^regheader[13]^regheader[14]^regheader[15]^regheader[19]^
		regheader[20]^regheader[21]^regheader[23];
	assign ecc[4]=regheader[4]^regheader[5]^regheader[6]^regheader[7]^regheader[8]^regheader[9]^regheader[16]^regheader[17]^regheader[18]^regheader[19]^
		regheader[20]^regheader[22]^regheader[23];
	assign ecc[5]=regheader[10]^regheader[11]^regheader[12]^regheader[13]^regheader[14]^regheader[15]^regheader[16]^regheader[17]^regheader[18]^regheader[19]^
		regheader[21]^regheader[22]^regheader[23];	
	assign ecc[6]=0;
	assign ecc[7]=0;
///////////////////States for long and short Packet Recieve
localparam reg[7:0] TIMEOUT=0;
localparam reg[7:0] LP11=1;
localparam reg[7:0] LP01=2;
localparam reg[7:0] LP00=3;
localparam reg[7:0] SYNC=4;
localparam reg[7:0] HEADER=5;
localparam reg[7:0] DATA=6;
///////////////////////////
localparam reg[7:0] MIPI_SYNC=0;
localparam reg[7:0] MIPI_IDLE=1;
localparam reg[7:0] MIPI_DATA=2;

//////////////////Const for Data_id
localparam reg[5:0] FS_const=6'h00;//Framestart
localparam reg[5:0] FE_const=6'h01;//Frameend
localparam reg[5:0] ED_const=6'h12;//Embedded data
localparam reg[5:0] RAW8_const=6'h2A;//Embedded data
localparam reg[5:0] RAW10_const=6'h2B;//Embedded data
///////////////////Const for Timing 
localparam integer Tlpx=5;
localparam integer Timeout=40;
localparam integer Tdterm=5;
localparam integer Thssettle=11;
///////////////////FSM for MIPI Reciever
always @(posedge bit_clk) begin
	if(reset==1) begin
		state_mipi<=TIMEOUT;
		timer0<=0;
		timer1<=0;
		timer2<=0;
		debug2<=0;		
		termination_r<=0;
	end else begin
		case (state_mipi)
	 	    TIMEOUT: begin
	 	    	state_mipi<=(lane0_p==1 && lane0_n==1 &&lane1_p==1 &&lane1_n==1)?LP11:TIMEOUT; 	    	
	 	    	debug2<=0;
	 	    	termination_r<=0;
	 	    end
			LP11:begin
				timer0<=0;	
				timer1<=0;
				timer2<=0;
				state_mipi<=(lane0_p==0 && lane0_n==1 &&lane1_p==0 &&lane1_n==1)?LP01:LP11;				
				debug2<=0;
				termination_r<=0;
			end
			LP01:begin
				if(timer0>=Timeout) begin
					state_mipi<=TIMEOUT;
				end else begin
					if(lane0_p==0 && lane0_n==0 &&lane1_p==0 &&lane1_n==0)begin
					 state_mipi<=LP00;
					 timer0<=0;					 
					end					
				end
				timer2<=0;	
				timer0<=timer0+1;
				timer1<=timer1+1;			
				end
			LP00:begin
				if(timer1>=Tdterm) begin					
					termination_r<=1;					
				end 
				if(timer2>=Thssettle) begin
					state_mipi<=SYNC;
					timer0<=0;	
					start_clk<=1;
				end
				if(timer0>=Timeout)begin
					state_mipi<=TIMEOUT;
				end
				timer0<=timer0+1;
				timer1<=timer1+1;
				timer2<=timer2+1;				
				debug2<=0;
			end
			SYNC:begin							
				debug2<=1;
				if(timer0>=6*Timeout)begin
					state_mipi<=TIMEOUT;
					start_clk<=0;					
				end
				timer0<=timer0+1;
				if(stop_clk==1)begin
					termination_r<=0;
					start_clk<=0;	
					state_mipi<=TIMEOUT;
				end				
			end			
			default: begin
			end
		endcase		
	end	
end

always@(negedge mipi_clk or negedge start_clk)begin
	if(start_clk==0) begin
		state_mipi_sync<=MIPI_IDLE;		
		debug0<=0;
		debug1<=0;
		stop_clk<=0;
	end else if(start_clk==1) begin				
				
				bytereg0={lane0ddr,bytereg0[7:2]};
				bytereg1={lane1ddr,bytereg1[7:2]};
				if (allign_cnt<4) begin
					allign_cnt<=allign_cnt+1;
				end else begin
					allign_cnt<=1;
					regheader={bytereg1,bytereg0,regheader[31:16]};
				end
				case (state_mipi_sync)
				MIPI_IDLE: begin
					if(bytereg0[6:0]=='b1011100)begin
						state_mipi_sync<=MIPI_SYNC;						
					end
					debug0<=0;
					debug1<=0;					
	            end
	            MIPI_SYNC: begin
	            	debug0<=0;
	            	debug1<=1;
	            	if(regheader[5:0]==FS_const[5:0])begin
	            		//state_mipi_sync<=MIPI_DATA;
	            	 	delay_mipi<=16;
	            	end	            	
	            end
	            MIPI_DATA: begin
	            	debug0<=1;
	            	debug1<=1;
	            	if(delay_mipi>2)begin
	            		delay_mipi<=delay_mipi-1;	
	            	end else begin
	            		//stop_clk<=1;
	            		state_mipi_sync<=MIPI_IDLE;
	            	end	            	
	            end
	            default: begin
	            end
                endcase
    end
end
///////////////////////FSM byte/bitclk
/*always@(posedge bit_clk)begin
	if(reset==1) begin
	end else begin
		case (state_byte)
			idle_bitclk: begin
				bytereg0={lane0ddr,bytereg0[7:2]};
				bytereg1={lane1ddr,bytereg1[7:2]};
				if (allign_cnt <4) begin
					allign_cnt<=allign_cnt+1;
				end else begin
					allign_cnt<=1;
					regheader={bytereg1,bytereg0,regheader[31:16]};
					end
					
			end			
			default: begin
			end
		endcase
	end
end
//////////////////////////
always @(posedge bit_clk or posedge reset) begin
	if(reset==1)begin
		state_mipi<=idle_mipi;
		led<=0;
	end else begin
		case (state_mipi)
			idle_mipi: begin							
				FS<=0;
				FE<=0;
				PIX<=0;
				led<=0;		
				if(bytereg0=='hb8)begin
					PIX<=1;
					led[0]<=1;
					state_mipi<=start_mipi;					
				end				
			end
			start_mipi:begin
				led[1]<=0;
				if(regheader[5:0]==RAW10_const[5:0]&&regheader[31:24]==ecc)begin
					FS<=1;//Frame start
					led[1]<=1;
					addres<=0;
					state_mipi<=data_mipi;
					mipi_cnt=0;
					wordcount<=regheader[23:8]*4;
				end				
			end
			data_mipi: begin
				if(mipi_cnt<=wordcount-1) begin
					mipi_cnt=mipi_cnt+1;
					addres<=(mipi_cnt)/8;
					led[2]<=1;
				end else begin
					state_mipi<=idle_mipi;
					mipi_cnt=0;
				end
			end
			PF_mipi: begin
				state_mipi<=idle_mipi;
			end
			default: begin
			end
		endcase
	end	
end*/
endmodule

/*module IDDRX1F(input D,input SCLK,input RST,output Q0,output Q1);
	reg Q0_r,Q1_r;
	always @(posedge SCLK) begin
		Q0_r<=D;
	end
	always @(negedge SCLK) begin
		Q1_r<=D;
	end	
	assign Q1=Q1_r;
	assign Q0=Q0_r;
	
endmodule

Componets/MIPI-CSI-Transciever/MIPI_Reciever/blinky.vcd
$version Generated by VerilatedVcd $end
$date Wed Feb  8 23:19:58 2023
 $end
$timescale   1ps $end

 $scope module TOP $end
  $var wire  8 < adress_out [7:0] $end
  $var wire  1 0 bit_clk $end
  $var wire  8 ; blue [7:0] $end
  $var wire  1 = debug0 $end
  $var wire  1 > debug1 $end
  $var wire  1 ? debug2 $end
  $var wire  8 : green [7:0] $end
  $var wire  1 3 lane0_d $end
  $var wire  1 6 lane0_n $end
  $var wire  1 5 lane0_p $end
  $var wire  1 4 lane1_d $end
  $var wire  1 8 lane1_n $end
  $var wire  1 7 lane1_p $end
  $var wire  1 1 mipi_clk $end
  $var wire  8 9 red [7:0] $end
  $var wire  1 2 reset $end
  $var wire  1 @ termination $end
  $scope module MIPI_Reciever $end
   $var wire  8 Y DATA [7:0] $end
   $var wire  6 \ ED_const [5:0] $end
   $var wire  1 P Eot_detect $end
   $var wire  6 [ FE_const [5:0] $end
   $var wire  6 Z FS_const [5:0] $end
   $var wire  1 O FS_detect $end
   $var wire  8 X HEADER [7:0] $end
   $var wire  8 V LP00 [7:0] $end
   $var wire  8 U LP01 [7:0] $end
   $var wire  8 T LP11 [7:0] $end
   $var wire  8 U MIPI_DATA [7:0] $end
   $var wire  8 T MIPI_IDLE [7:0] $end
   $var wire  8 I MIPI_SYNC [7:0] $end
   $var wire  6 ^ RAW10_const [5:0] $end
   $var wire  6 ] RAW8_const [5:0] $end
   $var wire  8 W SYNC [7:0] $end
   $var wire  8 I TIMEOUT [7:0] $end
   $var wire 32 _ Tdterm [31:0] $end
   $var wire 32 a Thssettle [31:0] $end
   $var wire 32 ` Timeout [31:0] $end
   $var wire 32 _ Tlpx [31:0] $end
   $var wire 25 R addres [24:0] $end
   $var wire  8 < adress_out [7:0] $end
   $var wire 32 ' allign_cnt [31:0] $end
   $var wire  1 0 bit_clk $end
   $var wire  8 ; blue [7:0] $end
   $var wire  8 I bytereg [7:0] $end
   $var wire  8 # bytereg0 [7:0] $end
   $var wire  8 $ bytereg1 [7:0] $end
   $var wire  1 = debug0 $end
   $var wire  1 > debug1 $end
   $var wire  1 ? debug2 $end
   $var wire 32 % delay_mipi [31:0] $end
   $var wire  8 * ecc [7:0] $end
   $var wire  1 J end_data $end
   $var wire  8 : green [7:0] $end
   $var wire  1 3 lane0_d $end
   $var wire  1 6 lane0_n $end
   $var wire  1 L lane0_nr $end
   $var wire  1 5 lane0_p $end
   $var wire  1 K lane0_pr $end
   $var wire  2 C lane0ddr [1:0] $end
   $var wire  1 4 lane1_d $end
   $var wire  1 8 lane1_n $end
   $var wire  1 N lane1_nr $end
   $var wire  1 7 lane1_p $end
   $var wire  1 M lane1_pr $end
   $var wire  2 D lane1ddr [1:0] $end
   $var wire  1 1 mipi_clk $end
   $var wire  8 9 red [7:0] $end
   $var wire 40 ( regheader [39:0] $end
   $var wire  1 2 reset $end
   $var wire  1 A start_clk $end
   $var wire  8 + state_mipi [7:0] $end
   $var wire  8 & state_mipi_sync [7:0] $end
   $var wire  1 B stop_clk $end
   $var wire  1 Q sync_detect $end
   $var wire  1 @ termination $end
   $var wire  1 , termination_r $end
   $var wire  8 - timer0 [7:0] $end
   $var wire  8 . timer1 [7:0] $end
   $var wire  8 / timer2 [7:0] $end
   $var wire 32 S wordcount [31:0] $end
   $scope module l0 $end
    $var wire  1 3 D $end
    $var wire  1 E Q0 $end
    $var wire  1 E Q0_r $end
    $var wire  1 F Q1 $end
    $var wire  1 F Q1_r $end
    $var wire  1 b RST $end
    $var wire  1 1 SCLK $end
   $upscope $end
   $scope module l1 $end
    $var wire  1 4 D $end
    $var wire  1 G Q0 $end
    $var wire  1 G Q0_r $end
    $var wire  1 H Q1 $end
    $var wire  1 H Q1_r $end
    $var wire  1 b RST $end
    $var wire  1 1 SCLK $end
   $upscope $end
  $upscope $end
 $upscope $end
$enddefinitions $end


#5000
b00000000 #
b00000000 $
b00000000000000000000000000000000 %
b00000001 &
b00000000000000000000000000000000 '
b0000000000000000000000000000000000000000 (
b00000000 *
b00000001 +
0,
b00000000 -
b00000000 .
b00000000 /
10
11
02
03
04
15
16
17
18
b00000000 9
b00000000 :
b00000000 ;
b00000000 <
0=
0>
0?
0@
0A
0B
b00 C
b00 D
0E
0F
0G
0H
b00000000 I
0J
0K
0L
0M
0N
0O
0P
0Q
b0000000000000000000000000 R
b00000000000000000000000000000000 S
b00000001 T
b00000010 U
b00000011 V
b00000100 W
b00000101 X
b00000110 Y
b000000 Z
b000001 [
b010010 \
b101010 ]
b101011 ^
b00000000000000000000000000000101 _
b00000000000000000000000000101000 `
b00000000000000000000000000001011 a
0b
#10000
00
01
#15000
10
11
#20000
00
01
#25000
10
11
#30000
00
01
#35000
10
11
#40000
00
01
#45000
10
11
#50000
00
01
#55000
b00000010 +
10
11
05
07
#60000
00
01
#65000
b00000001 -
b00000001 .
10
11
#70000
00
01
#75000
b00000010 -
b00000010 .
10
11
#80000
00
01
#85000
b00000011 -
b00000011 .
10
11
#90000
00
01
#95000
b00000100 -
b00000100 .
10
11
#100000
00
01
#105000
b00000011 +
b00000101 -
b00000101 .
10
11
06
08
#110000
00
01
#115000
1,
b00000110 -
b00000110 .
b00000001 /
10
11
1@
#120000
00
01
#125000
b00000111 -
b00000111 .
b00000010 /
10
11
#130000
00
01
#135000
b00001000 -
b00001000 .
b00000011 /
10
11
#140000
00
01
#145000
b00001001 -
b00001001 .
b00000100 /
10
11
#150000
00
01
#155000
b00001010 -
b00001010 .
b00000101 /
10
11
#160000
00
01
#165000
b00001011 -
b00001011 .
b00000110 /
10
11
#170000
00
01
#175000
b00001100 -
b00001100 .
b00000111 /
10
11
#180000
00
01
#185000
b00001101 -
b00001101 .
b00001000 /
10
11
#190000
00
01
#195000
b00001110 -
b00001110 .
b00001001 /
10
11
#200000
00
01
#205000
b00001111 -
b00001111 .
b00001010 /
10
11
#210000
00
01
#215000
b00010000 -
b00010000 .
b00001011 /
10
11
#220000
00
01
13
14
b01 C
b10 D
1F
1H
#225000
b00000100 +
b00010001 -
b00010001 .
b00001100 /
10
11
1A
b11 C
b11 D
1E
1G
#230000
b11000000 #
b11000000 $
b00000000000000000000000000000001 '
00
01
#235000
b00010010 -
10
11
03
04
1?
b01 C
b10 D
0E
0G
#240000
b01110000 #
b10110000 $
b00000000000000000000000000000010 '
00
01
13
14
#245000
b00010011 -
10
11
03
04
#250000
b01011100 #
b10101100 $
b00000000 &
b00000000000000000000000000000011 '
00
01
b00 C
b00 D
0F
0H
#255000
b00010100 -
10
11
#260000
b00010111 #
b00101011 $
b00000000000000000000000000010000 %
b00000000000000000000000000000100 '
00
01
1>
#265000
b00010101 -
10
11
#270000
b00000101 #
b00001010 $
b00000000000000000000000000000001 '
b0000000000001010000001010000000000000000 (
b00000101 *
00
01
#275000
b00010110 -
10
11
#280000
b00000001 #
b00000010 $
b00000000000000000000000000000010 '
00
01
#285000
b00010111 -
10
11
#290000
b00000000 #
b00000000 $
b00000000000000000000000000000011 '
00
01
#295000
b00011000 -
10
11
#300000
b00000000000000000000000000000100 '
00
01
#305000
b00011001 -
10
11
#310000
b00000000000000000000000000000001 '
b0000000000000000000000000000101000000101 (
b00110011 *
00
01
#315000
b00011010 -
10
11
#320000
b00000000000000000000000000000010 '
00
01
#325000
b00011011 -
10
11
#330000
b00000000000000000000000000000011 '
00
01
#335000
b00011100 -
10
11
#340000
b00000000000000000000000000000100 '
00
01
#345000
b00011101 -
10
11
#350000
b00000000000000000000000000000001 '
b0000000000000000000000000000000000000000 (
b00000000 *
00
01
#355000
b00011110 -
10
11
#360000
b00000000000000000000000000000010 '
00
01
#365000
b00011111 -
10
11
#370000
b00000000000000000000000000000011 '
00
01
#375000
b00100000 -
10
11
#380000
b00000000000000000000000000000100 '
00
01
#385000
b00100001 -
10
11
#390000
b00000000000000000000000000000001 '
00
01
#395000
b00100010 -
10
11
#400000
b00000000000000000000000000000010 '
00
01
#405000
b00100011 -
10
11
#410000
b00000000000000000000000000000011 '
00
01
#415000
b00100100 -
10
11
#420000
b00000000000000000000000000000100 '
00
01
#425000
b00100101 -
10
11
#430000
b00000000000000000000000000000001 '
00
01
#435000
b00100110 -
10
11
#440000
b00000000000000000000000000000010 '
00
01
#445000
b00100111 -
10
11
#450000
b00000000000000000000000000000011 '
00
01
#455000
b00101000 -
10
11
#460000
b00000000000000000000000000000100 '
00
01
#465000
b00101001 -
10
11
#470000
b00000000000000000000000000000001 '
00
01
#475000
b00101010 -
10
11
#480000
b00000000000000000000000000000010 '
00
01
#485000
b00101011 -
10
11
#490000
b00000000000000000000000000000011 '
00
01
#495000
b00101100 -
10
11
#500000
b00000000000000000000000000000100 '
00
01
#505000
b00101101 -
10
11
#510000
b00000000000000000000000000000001 '
00
01
#515000
b00101110 -
10
11
#520000
b00000000000000000000000000000010 '
00
01
#525000
b00101111 -
10
11
#530000
b00000000000000000000000000000011 '
00
01
#535000
b00110000 -
10
11
#540000
b00000000000000000000000000000100 '
00
01
#545000
b00110001 -
10
11
#550000
b00000000000000000000000000000001 '
00
01
#555000
b00110010 -
10
11
#560000
b00000000000000000000000000000010 '
00
01
#565000
b00110011 -
10
11
#570000
b00000000000000000000000000000011 '
00
01
#575000
b00110100 -
10
11
#580000
b00000000000000000000000000000100 '
00
01
#585000
b00110101 -
10
11
#590000
b00000000000000000000000000000001 '
00
01
#595000
b00110110 -
10
11
#600000
b00000000000000000000000000000010 '
00
01
#605000
b00110111 -
10
11
#610000
b00000000000000000000000000000011 '
00
01
#615000
b00111000 -
10
11
#620000
b00000000000000000000000000000100 '
00
01
#625000
b00111001 -
10
11
#630000
b00000000000000000000000000000001 '
00
01
#635000
b00111010 -
10
11
#640000
b00000000000000000000000000000010 '
00
01
#645000
b00111011 -
10
11
#650000
b00000000000000000000000000000011 '
00
01
#655000
b00111100 -
10
11
#660000
b00000000000000000000000000000100 '
00
01
#665000
b00111101 -
10
11
#670000
b00000000000000000000000000000001 '
00
01
#675000
b00111110 -
10
11
#680000
b00000000000000000000000000000010 '
00
01
#685000
b00111111 -
10
11
#690000
b00000000000000000000000000000011 '
00
01
#695000
b01000000 -
10
11
#700000
b00000000000000000000000000000100 '
00
01
#705000
b01000001 -
10
11
#710000
b00000000000000000000000000000001 '
00
01
#715000
b01000010 -
10
11
#720000
b00000000000000000000000000000010 '
00
01
#725000
b01000011 -
10
11
#730000
b00000000000000000000000000000011 '
00
01
#735000
b01000100 -
10
11
#740000
b00000000000000000000000000000100 '
00
01
#745000
b01000101 -
10
11
#750000
b00000000000000000000000000000001 '
00
01
#755000
b01000110 -
10
11
#760000
b00000000000000000000000000000010 '
00
01
#765000
b01000111 -
10
11
#770000
b00000000000000000000000000000011 '
00
01
#775000
b01001000 -
10
11
#780000
b00000000000000000000000000000100 '
00
01
#785000
b01001001 -
10
11
#790000
b00000000000000000000000000000001 '
00
01
#795000
b01001010 -
10
11
#800000
b00000000000000000000000000000010 '
00
01
#805000
b01001011 -
10
11
#810000
b00000000000000000000000000000011 '
00
01
#815000
b01001100 -
10
11
#820000
b00000000000000000000000000000100 '
00
01
#825000
b01001101 -
10
11
#830000
b00000000000000000000000000000001 '
00
01
#835000
b01001110 -
10
11
#840000
b00000000000000000000000000000010 '
00
01
#845000
b01001111 -
10
11
#850000
b00000000000000000000000000000011 '
00
01
#855000
b01010000 -
10
11
#860000
b00000000000000000000000000000100 '
00
01
#865000
b01010001 -
10
11
#870000
b00000000000000000000000000000001 '
00
01
#875000
b01010010 -
10
11
#880000
b00000000000000000000000000000010 '
00
01
#885000
b01010011 -
10
11
#890000
b00000000000000000000000000000011 '
00
01
#895000
b01010100 -
10
11
#900000
b00000000000000000000000000000100 '
00
01
#905000
b01010101 -
10
11
#910000
b00000000000000000000000000000001 '
00
01
#915000
b01010110 -
10
11
#920000
b00000000000000000000000000000010 '
00
01
#925000
b01010111 -
10
11
#930000
b00000000000000000000000000000011 '
00
01
#935000
b01011000 -
10
11
#940000
b00000000000000000000000000000100 '
00
01
#945000
b01011001 -
10
11
#950000
b00000000000000000000000000000001 '
00
01
#955000
b01011010 -
10
11
#960000
b00000000000000000000000000000010 '
00
01
#965000
b01011011 -
10
11
#970000
b00000000000000000000000000000011 '
00
01
#975000
b01011100 -
10
11
#980000
b00000000000000000000000000000100 '
00
01
#985000
b01011101 -
10
11
#990000
b00000000000000000000000000000001 '
00
01
#995000
b01011110 -
10
11
#1000000
b00000000000000000000000000000010 '
00
01
#1005000
b01011111 -
10
11
#1010000
b00000000000000000000000000000011 '
00
01
#1015000
b01100000 -
10
11
#1020000
b00000000000000000000000000000100 '
00
01
#1025000
b01100001 -
10
11
#1030000
b00000000000000000000000000000001 '
00
01
#1035000
b01100010 -
10
11
#1040000
b00000000000000000000000000000010 '
00
01
#1045000
b01100011 -
10
11
#1050000
b00000000000000000000000000000011 '
00
01
#1055000
b01100100 -
10
11
#1060000
b00000000000000000000000000000100 '
00
01
#1065000
b01100101 -
10
11
#1070000
b00000000000000000000000000000001 '
00
01
#1075000
b01100110 -
10
11
#1080000
b00000000000000000000000000000010 '
00
01
#1085000
b01100111 -
10
11
#1090000
b00000000000000000000000000000011 '
00
01
#1095000
b01101000 -
10
11
#1100000
b00000000000000000000000000000100 '
00
01
#1105000
b01101001 -
10
11
#1110000
b00000000000000000000000000000001 '
00
01
#1115000
b01101010 -
10
11
#1120000
b00000000000000000000000000000010 '
00
01
#1125000
b01101011 -
10
11
#1130000
b00000000000000000000000000000011 '
00
01
#1135000
b01101100 -
10
11
#1140000
b00000000000000000000000000000100 '
00
01
#1145000
b01101101 -
10
11
#1150000
b00000000000000000000000000000001 '
00
01
#1155000
b01101110 -
10
11
#1160000
b00000000000000000000000000000010 '
00
01
#1165000
b01101111 -
10
11
#1170000
b00000000000000000000000000000011 '
00
01
#1175000
b01110000 -
10
11
#1180000
b00000000000000000000000000000100 '
00
01
#1185000
b01110001 -
10
11
#1190000
b00000000000000000000000000000001 '
00
01
#1195000
b01110010 -
10
11
#1200000
b00000000000000000000000000000010 '
00
01
#1205000
b01110011 -
10
11
#1210000
b00000000000000000000000000000011 '
00
01
#1215000
b01110100 -
10
11
#1220000
b00000000000000000000000000000100 '
00
01
#1225000
b01110101 -
10
11
#1230000
b00000000000000000000000000000001 '
00
01
#1235000
b01110110 -
10
11
#1240000
b00000000000000000000000000000010 '
00
01
#1245000
b01110111 -
10
11
#1250000
b00000000000000000000000000000011 '
00
01
#1255000
b01111000 -
10
11
#1260000
b00000000000000000000000000000100 '
00
01
#1265000
b01111001 -
10
11
#1270000
b00000000000000000000000000000001 '
00
01
#1275000
b01111010 -
10
11
#1280000
b00000000000000000000000000000010 '
00
01
#1285000
b01111011 -
10
11
#1290000
b00000000000000000000000000000011 '
00
01
#1295000
b01111100 -
10
11
#1300000
b00000000000000000000000000000100 '
00
01
#1305000
b01111101 -
10
11
#1310000
b00000000000000000000000000000001 '
00
01
#1315000
b01111110 -
10
11
#1320000
b00000000000000000000000000000010 '
00
01
#1325000
b01111111 -
10
11
#1330000
b00000000000000000000000000000011 '
00
01
#1335000
b10000000 -
10
11
#1340000
b00000000000000000000000000000100 '
00
01
#1345000
b10000001 -
10
11
#1350000
b00000000000000000000000000000001 '
00
01
#1355000
b10000010 -
10
11
#1360000
b00000000000000000000000000000010 '
00
01
#1365000
b10000011 -
10
11
#1370000
b00000000000000000000000000000011 '
00
01
#1375000
b10000100 -
10
11
#1380000
b00000000000000000000000000000100 '
00
01
#1385000
b10000101 -
10
11
#1390000
b00000000000000000000000000000001 '
00
01
#1395000
b10000110 -
10
11
#1400000
b00000000000000000000000000000010 '
00
01
#1405000
b10000111 -
10
11
#1410000
b00000000000000000000000000000011 '
00
01
#1415000
b10001000 -
10
11
#1420000
b00000000000000000000000000000100 '
00
01
#1425000
b10001001 -
10
11
#1430000
b00000000000000000000000000000001 '
00
01
#1435000
b10001010 -
10
11
#1440000
b00000000000000000000000000000010 '
00
01
#1445000
b10001011 -
10
11
#1450000
b00000000000000000000000000000011 '
00
01
#1455000
b10001100 -
10
11
#1460000
b00000000000000000000000000000100 '
00
01
#1465000
b10001101 -
10
11
#1470000
b00000000000000000000000000000001 '
00
01
#1475000
b10001110 -
10
11
#1480000
b00000000000000000000000000000010 '
00
01
#1485000
b10001111 -
10
11
#1490000
b00000000000000000000000000000011 '
00
01
#1495000
b10010000 -
10
11
#1500000
b00000000000000000000000000000100 '
00
01
#1505000
b10010001 -
10
11
#1510000
b00000000000000000000000000000001 '
00
01
#1515000
b10010010 -
10
11
#1520000
b00000000000000000000000000000010 '
00
01
#1525000
b10010011 -
10
11
#1530000
b00000000000000000000000000000011 '
00
01
#1535000
b10010100 -
10
11
#1540000
b00000000000000000000000000000100 '
00
01
#1545000
b10010101 -
10
11
#1550000
b00000000000000000000000000000001 '
00
01
#1555000
b10010110 -
10
11
#1560000
b00000000000000000000000000000010 '
00
01
#1565000
b10010111 -
10
11
#1570000
b00000000000000000000000000000011 '
00
01
#1575000
b10011000 -
10
11
#1580000
b00000000000000000000000000000100 '
00
01
#1585000
b10011001 -
10
11
#1590000
b00000000000000000000000000000001 '
00
01
#1595000
b10011010 -
10
11
#1600000
b00000000000000000000000000000010 '
00
01
#1605000
b10011011 -
10
11
#1610000
b00000000000000000000000000000011 '
00
01
#1615000
b10011100 -
10
11
#1620000
b00000000000000000000000000000100 '
00
01
#1625000
b10011101 -
10
11
#1630000
b00000000000000000000000000000001 '
00
01
#1635000
b10011110 -
10
11
#1640000
b00000000000000000000000000000010 '
00
01
#1645000
b10011111 -
10
11
#1650000
b00000000000000000000000000000011 '
00
01
#1655000
b10100000 -
10
11
#1660000
b00000000000000000000000000000100 '
00
01
#1665000
b10100001 -
10
11
#1670000
b00000000000000000000000000000001 '
00
01
#1675000
b10100010 -
10
11
#1680000
b00000000000000000000000000000010 '
00
01
#1685000
b10100011 -
10
11
#1690000
b00000000000000000000000000000011 '
00
01
#1695000
b10100100 -
10
11
#1700000
b00000000000000000000000000000100 '
00
01
#1705000
b10100101 -
10
11
#1710000
b00000000000000000000000000000001 '
00
01
#1715000
b10100110 -
10
11
#1720000
b00000000000000000000000000000010 '
00
01
#1725000
b10100111 -
10
11
#1730000
b00000000000000000000000000000011 '
00
01
#1735000
b10101000 -
10
11
#1740000
b00000000000000000000000000000100 '
00
01
#1745000
b10101001 -
10
11
#1750000
b00000000000000000000000000000001 '
00
01
#1755000
b10101010 -
10
11
#1760000
b00000000000000000000000000000010 '
00
01
#1765000
b10101011 -
10
11
#1770000
b00000000000000000000000000000011 '
00
01
#1775000
b10101100 -
10
11
#1780000
b00000000000000000000000000000100 '
00
01
#1785000
b10101101 -
10
11
#1790000
b00000000000000000000000000000001 '
00
01
#1795000
b10101110 -
10
11
#1800000
b00000000000000000000000000000010 '
00
01
#1805000
b10101111 -
10
11
#1810000
b00000000000000000000000000000011 '
00
01
#1815000
b10110000 -
10
11
#1820000
b00000000000000000000000000000100 '
00
01
#1825000
b10110001 -
10
11
#1830000
b00000000000000000000000000000001 '
00
01
#1835000
b10110010 -
10
11
#1840000
b00000000000000000000000000000010 '
00
01
#1845000
b10110011 -
10
11
#1850000
b00000000000000000000000000000011 '
00
01
#1855000
b10110100 -
10
11
#1860000
b00000000000000000000000000000100 '
00
01
#1865000
b10110101 -
10
11
#1870000
b00000000000000000000000000000001 '
00
01
#1875000
b10110110 -
10
11
#1880000
b00000000000000000000000000000010 '
00
01
#1885000
b10110111 -
10
11
#1890000
b00000000000000000000000000000011 '
00
01
#1895000
b10111000 -
10
11
#1900000
b00000000000000000000000000000100 '
00
01
#1905000
b10111001 -
10
11
#1910000
b00000000000000000000000000000001 '
00
01
#1915000
b10111010 -
10
11
#1920000
b00000000000000000000000000000010 '
00
01
#1925000
b10111011 -
10
11
#1930000
b00000000000000000000000000000011 '
00
01
#1935000
b10111100 -
10
11
#1940000
b00000000000000000000000000000100 '
00
01
#1945000
b10111101 -
10
11
#1950000
b00000000000000000000000000000001 '
00
01
#1955000
b10111110 -
10
11
#1960000
b00000000000000000000000000000010 '
00
01
#1965000
b10111111 -
10
11
#1970000
b00000000000000000000000000000011 '
00
01
#1975000
b11000000 -
10
11
#1980000
b00000000000000000000000000000100 '
00
01
#1985000
b11000001 -
10
11
#1990000
b00000000000000000000000000000001 '
00
01
#1995000
b11000010 -
10
11
#2000000
b00000000000000000000000000000010 '
00
01
#2005000
b11000011 -
10
11
#2010000
b00000000000000000000000000000011 '
00
01
#2015000
b11000100 -
10
11
#2020000
b00000000000000000000000000000100 '
00
01
#2025000
b11000101 -
10
11
#2030000
b00000000000000000000000000000001 '
00
01
#2035000
b11000110 -
10
11
#2040000
b00000000000000000000000000000010 '
00
01
#2045000
b11000111 -
10
11
#2050000
b00000000000000000000000000000011 '
00
01
#2055000
b11001000 -
10
11
#2060000
b00000000000000000000000000000100 '
00
01
#2065000
b11001001 -
10
11
#2070000
b00000000000000000000000000000001 '
00
01
#2075000
b11001010 -
10
11
#2080000
b00000000000000000000000000000010 '
00
01
#2085000
b11001011 -
10
11
#2090000
b00000000000000000000000000000011 '
00
01
#2095000
b11001100 -
10
11
#2100000
b00000000000000000000000000000100 '
00
01
#2105000
b11001101 -
10
11
#2110000
b00000000000000000000000000000001 '
00
01
#2115000
b11001110 -
10
11
#2120000
b00000000000000000000000000000010 '
00
01
#2125000
b11001111 -
10
11
#2130000
b00000000000000000000000000000011 '
00
01
#2135000
b11010000 -
10
11
