Componets/MIPI-CSI-Transciever/MIPI_Reciever/MIPI_Reciever.v
module MIPI_Reciever(input sys_clk,reset,lane0_d,mipi_clk,mipi_clk_8,lane1_d,inout lane0_p,lane0_n,lane1_p,lane1_n,output[31:0] data_o,output[31:0] adress_out,output ram_clk,output reg debug0,debug1,debug2,output termination,rec_data_o,output[31:0] cX,cY);
    
	wire stop_clk, rec_data;
	wire[7:0] lane0byte,lane1byte;	 	
    SoTFSM RxFSM(.rec_data(rec_data),.clk100MHz(sys_clk),.reset(reset),.lane0_p(lane0_p),.lane0_n(lane0_n),.lane1_p(lane1_p),.lane1_n(lane1_n),.stop_rx(stop_clk),.term(termination),.debug0(debug0));
	wire[3:0]q_o_0,q_o_1;
	wire[1:0] ov_fl_0,ov_fl_1;
	wire even,sync;
	//assign debug1=even;
	wire sync_mipi_clk,sync_mipi_clk_2,sync_mipi_clk_4,sync_mipi_clk_8;
	//assign debug2=termination_r;


	ECLKSYNCB SYNC(.ECLKI(mipi_clk),.STOP(stop_clk),.ECLKO(sync_mipi_clk));	
	CLKDIVF div2 (.CLKI(sync_mipi_clk),.RST(reset),.CDIVX(sync_mipi_clk_2));
	CLKDIVF div4 (.CLKI(sync_mipi_clk_2),.RST(reset),.CDIVX(sync_mipi_clk_4));
	CLKDIVF div8 (.CLKI(sync_mipi_clk_4),.RST(reset),.CDIVX(sync_mipi_clk_8));

	/*wire mipi_clk_2,mipi_clk_4,mipi_clk_8;
	CLKDIVF div21 (.CLKI(mipi_clk),.RST(reset),.CDIVX(mipi_clk_2));
	CLKDIVF div41 (.CLKI(mipi_clk_2),.RST(reset),.CDIVX(mipi_clk_4));
	CLKDIVF div81 (.CLKI(mipi_clk_4),.RST(reset),.CDIVX(mipi_clk_8));
	*/
	


    IDDR2 lane0 (.lane(lane0_d),.sync_mipi_clk(sync_mipi_clk),.sync_mipi_clk_2(sync_mipi_clk_2),.reset(reset),.stop(stop_clk),.even(even),.sync(sync),.q_o(q_o_0),.ov_fl(ov_fl_0));
	IDDR2 lane1 (.lane(lane1_d),.sync_mipi_clk(sync_mipi_clk),.sync_mipi_clk_2(sync_mipi_clk_2),.reset(reset),.stop(stop_clk),/*.even(even),.sync(sync),*/.q_o(q_o_1),.ov_fl(ov_fl_1));
	
	wire[7:0] byte_e_0,byte_ue_0,byte_e_1,byte_ue_1;
	Byte_Arrange BA0 (.reset(reset),.stop(stop_clk),.mipi_clk_2(sync_mipi_clk_2),.q_o(q_o_0),.ov_fl(ov_fl_0),.byte_e(byte_e_0),.byte_ue(byte_ue_0));
	Byte_Arrange BA1 (.reset(reset),.stop(stop_clk),.mipi_clk_2(sync_mipi_clk_2),.q_o(q_o_1),.ov_fl(ov_fl_1),.byte_e(byte_e_1),.byte_ue(byte_ue_1));
	
	wire[7:0] byte_o_0,byte_o_1;
	Byte_Alligner BAL0(.reset(reset),.stop(stop_clk),.mipi_clk_2(sync_mipi_clk_2),.sync(sync),.even(even),.byte_e(byte_e_0),.byte_ue(byte_ue_0),.byte_o(byte_o_0));
	Byte_Alligner BAL1(.reset(reset),.stop(stop_clk),.mipi_clk_2(sync_mipi_clk_2),.sync(sync),.even(even),.byte_e(byte_e_1),.byte_ue(byte_ue_1),.byte_o(byte_o_1));

	wire [31:0] data;
	wire valid;
	wire[5:0] type_w;
	wire[15:0] wordcount;
	DATA_Encoder DE (.mipi_clk_4(sync_mipi_clk_4),.reset(reset),.stop(stop_clk),.sync(sync),.byte_in0(byte_o_0),.data(data),.type_o(type_w),.wordcount(wordcount),.byte_in1(byte_o_1),.valid(valid));
	
	
	Protocoll Prot (.mipi_clk_8(sync_mipi_clk_8),.stop(stop_clk),.reset(reset),.valid(valid),.type_i(type_w),.wordcount(wordcount),.data_o(data_o),.data(data),.rec_data(rec_data),.adress_o(adress_out),.cX(cX),.cY(cY));
	assign rec_data_o=rec_data;
	assign debug1=rec_data;
	assign ram_clk=sync_mipi_clk_8;
endmodule

module IDDR2 (input lane,sync_mipi_clk,sync_mipi_clk_2,input reset,stop,output[3:0] q_o,output[1:0] ov_fl,output even,output sync);
	wire[3:0] ddr;
	reg sync_r,even_r;
	reg[3:0] q_o_r;
	reg[1:0] ov_fl_r0;
	reg[1:0] ov_fl_r1;
	reg[7:0] syncbyte=0;
	assign sync=sync_r&(!stop);
	assign even=even_r;
	assign ov_fl=ov_fl_r1;
	assign q_o=q_o_r;	
	//wire one_bit_error_e,one_bit_error_ue;
	wire[7:0] detect_e,detect_ue;	
	
	assign detect_e=syncbyte^8'b10111000;
	assign detect_ue=((8'b00111111)&syncbyte)^8'b00101110;
	//assign one_bit_error_e=(detect_e==1)||(detect_e==2)||(detect_e==4)||(detect_e==8)||(detect_e==16)||(detect_e==32)||(detect_e==64)||(detect_e==128);
	//assign one_bit_error_ue=(detect_ue==1)||(detect_ue==2)||(detect_ue==4)||(detect_ue==8)||(detect_ue==16)||(detect_ue==32)||(detect_ue==64)||(detect_ue==128);
	IDDRX2F IDDR (.D(lane),.ECLK(sync_mipi_clk),.SCLK(sync_mipi_clk_2),.RST(reset),.Q0(ddr[0]),.Q1(ddr[1]),.Q2(ddr[2]),.Q3(ddr[3]));	
	always @(posedge sync_mipi_clk_2) begin
		if(reset||stop)begin
			sync_r<=0;
			even_r<=0;
			ov_fl_r0<=0;
			ov_fl_r1<=0;			
			q_o_r<=0;
			syncbyte=0;
		end else begin				
			syncbyte={ddr,syncbyte[7:4]};			
			sync_r<=(detect_e==0||detect_ue==0)?1:sync_r;
			if(detect_e==0)begin
				even_r<=1;
			end
			if (detect_ue==0) begin
				even_r<=0;
			end
			q_o_r<=ddr;
			ov_fl_r0<=ddr[3:2];
			ov_fl_r1<=ov_fl_r0;
		end
	end

endmodule

module Byte_Arrange(input reset,stop,mipi_clk_2,input[3:0] q_o,input[1:0] ov_fl,output[7:0] byte_e,output[7:0]byte_ue);
	reg[7:0] byte0_r,byte1_r;
	assign byte_e=byte0_r;
	assign byte_ue=byte1_r;	
	always @(posedge mipi_clk_2) begin
		if(reset||stop)begin
			byte0_r<=0;
			byte1_r<=0;
		end else begin				
			byte0_r<={q_o,byte0_r[7:4]};
			byte1_r<={q_o[1:0],ov_fl,byte1_r[7:4]};		
		end
end
endmodule

module Byte_Alligner(input reset,stop,mipi_clk_2,sync,even,input[7:0] byte_e,input[7:0] byte_ue,output[7:0] byte_o);
	reg[7:0] byte_o_r;
	assign byte_o=byte_o_r;	
	reg[7:0]counter;
	wire[7:0] byte_o_eu;
	assign byte_o_eu=(even)?byte_e:byte_ue;
	always @(posedge mipi_clk_2) begin
		if(reset||stop)begin
			byte_o_r<=0;			
			counter<=0;			
		end else begin			
			if(sync)begin
				counter<=counter+1;
				byte_o_r<=(counter[0]==1)?byte_o_eu:byte_o_r;///////////////////////change to ==0 for real worls!!!!!!!!!!!!!!!!!!!!!!!!
				//byte_o_r<=byte_o_eu;
				
			end
		end
	end
endmodule


module DATA_Encoder(input mipi_clk_4,reset,stop,sync,input[7:0] byte_in0,byte_in1,output[31:0]data,output valid,output[5:0] type_o,output[15:0] wordcount);

	reg[31:0] out_r;
	reg valid_r,start;
	assign valid=valid_r;	
	reg[7:0] counter;
	wire[31:0] regheader;
	assign regheader=out_r;
	wire[7:0] ecc;
	reg [31:0] data_r;
	reg[5:0] type_o_r;
	reg[15:0] wordcount_r;
	assign data=data_r;
	assign type_o=type_o_r;
	assign wordcount=wordcount_r;
	assign ecc[0]=regheader[0]^regheader[1]^regheader[2]^regheader[4]^regheader[5]^regheader[7]^regheader[10]^regheader[11]^regheader[13]^regheader[16]^
		regheader[20]^regheader[21]^regheader[22]^regheader[23];
	assign ecc[1]=regheader[0]^regheader[1]^regheader[3]^regheader[4]^regheader[6]^regheader[8]^regheader[10]^regheader[12]^regheader[14]^regheader[17]^
		regheader[20]^regheader[21]^regheader[22]^regheader[23];
	assign ecc[2]=regheader[0]^regheader[2]^regheader[3]^regheader[5]^regheader[6]^regheader[9]^regheader[11]^regheader[12]^regheader[15]^regheader[18]^
		regheader[20]^regheader[21]^regheader[22];
	assign ecc[3]=regheader[1]^regheader[2]^regheader[3]^regheader[7]^regheader[8]^regheader[9]^regheader[13]^regheader[14]^regheader[15]^regheader[19]^
		regheader[20]^regheader[21]^regheader[23];
	assign ecc[4]=regheader[4]^regheader[5]^regheader[6]^regheader[7]^regheader[8]^regheader[9]^regheader[16]^regheader[17]^regheader[18]^regheader[19]^
		regheader[20]^regheader[22]^regheader[23];
	assign ecc[5]=regheader[10]^regheader[11]^regheader[12]^regheader[13]^regheader[14]^regheader[15]^regheader[16]^regheader[17]^regheader[18]^regheader[19]^
		regheader[21]^regheader[22]^regheader[23];	
	assign ecc[6]=0;
	assign ecc[7]=0;
	wire syndrom,one_bit_error;
	assign syndrom=ecc^regheader[31:24];

	assign one_bit_error=(syndrom==8'h07)||(syndrom==8'h0B)||(syndrom==8'h0D)||(syndrom==8'h0E)||(syndrom==8'h13)||(syndrom==8'h15)|
	(syndrom==8'h16)||(syndrom==8'h19)||(syndrom==8'h1A)||(syndrom==8'h1C)||(syndrom==8'h23)||(syndrom==8'h25)||
	(syndrom==8'h26)||(syndrom==8'h29)||(syndrom==8'h2A)||(syndrom==8'h2C)||(syndrom==8'h31)||(syndrom==8'h32)||
	(syndrom==8'h34)||(syndrom==8'h38)||(syndrom==8'h1F)||(syndrom==8'h2F)||(syndrom==8'h37)||(syndrom==8'h3B);

	always @(posedge mipi_clk_4) begin
		if(reset||stop)begin
			out_r<=0;	
			valid_r<=0;		
			start=0;
			counter<=0;
			data_r<=0;
			type_o_r<=0;
			wordcount_r<=0;
		end else begin			
			if(sync)begin
				out_r<={byte_in1,byte_in0,out_r[31:16]};
				valid_r<=(ecc==out_r[31:24]&&out_r!=0)?1:valid_r;
				start=(ecc==out_r[31:24]&&out_r!=0)?1:start;
				type_o_r<=(ecc==out_r[31:24]&&out_r!=0)?out_r[5:0]:type_o_r;
				wordcount_r<=(ecc==out_r[31:24]&&out_r!=0)?out_r[23:8]:wordcount_r;
				if(start)begin
					counter<=counter+1;
					if(counter>1)begin
						counter<=1;
						data_r<=out_r;
					end else begin
						counter<=counter+1;
					end
				end						
			end
		end
	end
endmodule

module SoTFSM(input clk100MHz,reset,rec_data,lane0_p,lane0_n,lane1_p,lane1_n,stop_tran,output stop_rx,term,debug0,debug1);
	///////////////////States for long and short Packet Recieve
	localparam reg[7:0] TIMEOUT=0;
	localparam reg[7:0] LP11=1;
	localparam reg[7:0] LP01=2;
	localparam reg[7:0] LP00=3;
	localparam reg[7:0] SYNC=4;
	localparam reg[7:0] HEADER=5;
	localparam reg[7:0] DATA=6;	
	///////////////////Const for Timing 
	localparam integer Tlpx=2;
	localparam integer Timeout=20;
	localparam integer Tdterm=2;
	localparam integer Thssettle=4;
	///////////////////
	reg[7:0] state_mipi=TIMEOUT;	
	reg stop_rx_r,term_r,debug0_r,debug1_r;
	assign stop_rx=stop_rx_r;
	assign term=term_r;
	assign debug0=debug0_r;
	assign debug1=debug1_r;	

	integer timer_tou,timer_term,timer_hs;	
	///////////////////////////////////////////////FSM
	always @(posedge clk100MHz) begin
		if(reset==1) begin
			state_mipi<=TIMEOUT;
			timer_tou<=0;
			timer_term<=0;
			timer_hs<=0;			
			term_r<=0;
			stop_rx_r<=1;
		end else begin
			case (state_mipi)
				TIMEOUT: begin
					state_mipi<=(lane0_p==1 && lane0_n==1 &&lane1_p==1 &&lane1_n==1)?LP11:TIMEOUT; 				
					timer_tou<=0;
					timer_term<=0;
					timer_hs<=0;			
					term_r<=0;
					debug0_r<=0;
					stop_rx_r<=1;	
				end
				LP11:begin					
					state_mipi<=(lane0_p==0 && lane0_n==1 &&lane1_p==0 &&lane1_n==1)?LP01:LP11;	
					debug0_r<=0;
					stop_rx_r<=1;	
				end
				LP01:begin
					if(timer_tou>=Timeout) begin
						state_mipi<=TIMEOUT;
					end else begin
						if(lane0_p==0 && lane0_n==0 &&lane1_p==0 &&lane1_n==0)begin
							state_mipi<=LP00;
							timer_tou<=0;					 
						end					
					end						
					timer_tou<=timer_tou+1;
					timer_term<=timer_term+1;	
					stop_rx_r<=1;			
				end
				LP00:begin
					stop_rx_r<=1;	
					if(timer_term>=Tdterm) begin					
						term_r<=1;					
					end 
					if(timer_hs>=Thssettle) begin
						state_mipi<=SYNC;
						timer_tou<=0;	
						stop_rx_r<=0;
					end
					if(timer_tou>=Timeout)begin
						state_mipi<=TIMEOUT;
					end
					timer_tou<=timer_tou+1;
					timer_term<=timer_term+1;
					timer_hs<=timer_hs+1;					
				end
				SYNC:begin		
					debug0_r<=1;
					if(timer_tou>=4*Timeout)begin
						state_mipi<=TIMEOUT;
						stop_rx_r<=1;					
					end				
					timer_tou<=timer_tou+1;
					if(rec_data==1)begin
						state_mipi<=HEADER;
						timer_tou<=0;
					end				
				end	
				HEADER:begin					
					timer_tou<=timer_tou+1;
					if(rec_data==0||timer_tou>180)begin
						state_mipi<=TIMEOUT;
						term_r<=0;
						//stop_rx_r<=1;	
					end	
				end		
				default: begin
				end
			endcase		
		end	   
	end
endmodule

module Protocoll(input mipi_clk_8,stop,reset,valid,input[5:0] type_i,input[15:0] wordcount,input[31:0] data,output[31:0] data_o,output[31:0]adress_o,output rec_data,output reg debug,output[31:0] cX,cY);
	reg rec_data_r,state,valid_old;
	reg[31:0] counter,count_val,data_o_r,counter_addr,cX_r,cY_r;
	assign data_o=data_o_r;
	assign rec_data=rec_data_r&&(!stop);
	assign adress_o=counter_addr;
	assign cX=cX_r;
	assign cY=cY_r;
	always @(posedge mipi_clk_8) begin
		if(reset)begin
			rec_data_r<=0;
			state<=0;
			data_o_r<=0;
			counter_addr<=0;
			valid_old<=0;
			cX_r<=0;
			cY_r<=0;
			//counter<=0;
			//count_val<=0;			
		end	else begin
			valid_old<=valid;			
			case (state)
				0:begin
					if((valid==1&&valid_old==0)&&type_i=='h2a&&wordcount=='h0280)begin
						state<=1;
						count_val<=160-2;
						cY_r<=cY_r+640;
						cX_r<=0;						
					end					
					//count_val<=120;
					if((valid==1&&valid_old==0)&&type_i=='h00)begin
						counter_addr<=0;								
						cX_r<=0;
						cY_r<=0;						
					end													
				end 
				1:begin
					if(counter<count_val)begin
						cX_r<=cX_r+1;
						counter<=counter+1;
						rec_data_r<=1;						
						counter_addr<=counter_addr+1;
						data_o_r<=data;						
					end else begin
						rec_data_r<=0;
						state<=0;
						counter<=0;
					end
				end
				default:begin					
				end 
			endcase
		end
	end

endmodule







module ECLKSYNCB (input ECLKI,STOP,output ECLKO);
		assign ECLKO=STOP?0:ECLKI;
endmodule

module CLKDIVF(input CLKI,RST,output CDIVX);
	reg[7:0] counter;
	assign CDIVX=counter[0];
	always @(posedge CLKI) begin
		if(RST==1)begin
			counter<=0;
		end else begin
			counter<=counter+1;
		end
	end

endmodule

module IDDRX1F(input D,input SCLK,input RST,output Q0,output Q1);
	reg Q0_r,Q1_r;
	always @(posedge SCLK) begin
		Q0_r<=D;
	end
	always @(negedge SCLK) begin
		Q1_r<=D;
	end	
	assign Q1=Q1_r;
	assign Q0=Q0_r;
	
endmodule

module IDDRX2F (input D,ECLK,SCLK,RST,output Q0,Q1,Q2,Q3);
	reg A,B,C,D1;
	assign Q0=A;
	assign Q1=B;
	assign Q2=C;
	assign Q3=D1;

	always @(posedge ECLK ) begin
		
		if(SCLK==0)begin
			A<=D;
		end
		if(SCLK==1)begin
			C<=D;
		end
	end
	always @(negedge ECLK) begin
		if(SCLK==1)begin
			B<=D;
		end
		if(SCLK==0)begin
			D1<=D;
		end
	end
	

endmodule

Componets/MIPI-CSI-Transciever/MIPI_Reciever/blinky.vcd
$version Generated by VerilatedVcd $end
$date Sun Feb 19 22:18:20 2023
 $end
$timescale   1ps $end

 $scope module TOP $end
  $var wire 32 n adress_out [31:0] $end
  $var wire 32 u cX [31:0] $end
  $var wire 32 v cY [31:0] $end
  $var wire 32 m data_o [31:0] $end
  $var wire  1 p debug0 $end
  $var wire  1 q debug1 $end
  $var wire  1 r debug2 $end
  $var wire  1 e lane0_d $end
  $var wire  1 j lane0_n $end
  $var wire  1 i lane0_p $end
  $var wire  1 h lane1_d $end
  $var wire  1 l lane1_n $end
  $var wire  1 k lane1_p $end
  $var wire  1 f mipi_clk $end
  $var wire  1 g mipi_clk_8 $end
  $var wire  1 o ram_clk $end
  $var wire  1 t rec_data_o $end
  $var wire  1 d reset $end
  $var wire  1 c sys_clk $end
  $var wire  1 s termination $end
  $scope module MIPI_Reciever $end
   $var wire 32 n adress_out [31:0] $end
   $var wire  8 6 byte_e_0 [7:0] $end
   $var wire  8 8 byte_e_1 [7:0] $end
   $var wire  8 x byte_o_0 [7:0] $end
   $var wire  8 y byte_o_1 [7:0] $end
   $var wire  8 7 byte_ue_0 [7:0] $end
   $var wire  8 9 byte_ue_1 [7:0] $end
   $var wire 32 u cX [31:0] $end
   $var wire 32 v cY [31:0] $end
   $var wire 32 S data [31:0] $end
   $var wire 32 m data_o [31:0] $end
   $var wire  1 p debug0 $end
   $var wire  1 q debug1 $end
   $var wire  1 r debug2 $end
   $var wire  1 4 even $end
   $var wire  1 e lane0_d $end
   $var wire  1 j lane0_n $end
   $var wire  1 i lane0_p $end
   $var wire  8 ~ lane0byte [7:0] $end
   $var wire  1 h lane1_d $end
   $var wire  1 l lane1_n $end
   $var wire  1 k lane1_p $end
   $var wire  8 !! lane1byte [7:0] $end
   $var wire  1 f mipi_clk $end
   $var wire  1 g mipi_clk_8 $end
   $var wire  2 2 ov_fl_0 [1:0] $end
   $var wire  2 3 ov_fl_1 [1:0] $end
   $var wire  4 0 q_o_0 [3:0] $end
   $var wire  4 1 q_o_1 [3:0] $end
   $var wire  1 o ram_clk $end
   $var wire  1 # rec_data $end
   $var wire  1 t rec_data_o $end
   $var wire  1 d reset $end
   $var wire  1 \ stop_clk $end
   $var wire  1 $ sync $end
   $var wire  1 % sync_mipi_clk $end
   $var wire  1 & sync_mipi_clk_2 $end
   $var wire  1 5 sync_mipi_clk_4 $end
   $var wire  1 w sync_mipi_clk_8 $end
   $var wire  1 c sys_clk $end
   $var wire  1 s termination $end
   $var wire  6 U type_w [5:0] $end
   $var wire  1 T valid $end
   $var wire 16 V wordcount [15:0] $end
   $scope module BA0 $end
    $var wire  8 6 byte0_r [7:0] $end
    $var wire  8 7 byte1_r [7:0] $end
    $var wire  8 6 byte_e [7:0] $end
    $var wire  8 7 byte_ue [7:0] $end
    $var wire  1 & mipi_clk_2 $end
    $var wire  2 2 ov_fl [1:0] $end
    $var wire  4 0 q_o [3:0] $end
    $var wire  1 d reset $end
    $var wire  1 \ stop $end
   $upscope $end
   $scope module BA1 $end
    $var wire  8 8 byte0_r [7:0] $end
    $var wire  8 9 byte1_r [7:0] $end
    $var wire  8 8 byte_e [7:0] $end
    $var wire  8 9 byte_ue [7:0] $end
    $var wire  1 & mipi_clk_2 $end
    $var wire  2 3 ov_fl [1:0] $end
    $var wire  4 1 q_o [3:0] $end
    $var wire  1 d reset $end
    $var wire  1 \ stop $end
   $upscope $end
   $scope module BAL0 $end
    $var wire  8 6 byte_e [7:0] $end
    $var wire  8 x byte_o [7:0] $end
    $var wire  8 G byte_o_eu [7:0] $end
    $var wire  8 x byte_o_r [7:0] $end
    $var wire  8 7 byte_ue [7:0] $end
    $var wire  8 F counter [7:0] $end
    $var wire  1 4 even $end
    $var wire  1 & mipi_clk_2 $end
    $var wire  1 d reset $end
    $var wire  1 \ stop $end
    $var wire  1 $ sync $end
   $upscope $end
   $scope module BAL1 $end
    $var wire  8 8 byte_e [7:0] $end
    $var wire  8 y byte_o [7:0] $end
    $var wire  8 I byte_o_eu [7:0] $end
    $var wire  8 y byte_o_r [7:0] $end
    $var wire  8 9 byte_ue [7:0] $end
    $var wire  8 H counter [7:0] $end
    $var wire  1 4 even $end
    $var wire  1 & mipi_clk_2 $end
    $var wire  1 d reset $end
    $var wire  1 \ stop $end
    $var wire  1 $ sync $end
   $upscope $end
   $scope module DE $end
    $var wire  8 x byte_in0 [7:0] $end
    $var wire  8 y byte_in1 [7:0] $end
    $var wire  8 Y counter [7:0] $end
    $var wire 32 S data [31:0] $end
    $var wire 32 S data_r [31:0] $end
    $var wire  8 Z ecc [7:0] $end
    $var wire  1 5 mipi_clk_4 $end
    $var wire  1 .! one_bit_error $end
    $var wire 32 W out_r [31:0] $end
    $var wire 32 W regheader [31:0] $end
    $var wire  1 d reset $end
    $var wire  1 X start $end
    $var wire  1 \ stop $end
    $var wire  1 $ sync $end
    $var wire  1 [ syndrom $end
    $var wire  6 U type_o [5:0] $end
    $var wire  6 U type_o_r [5:0] $end
    $var wire  1 T valid $end
    $var wire  1 T valid_r $end
    $var wire 16 V wordcount [15:0] $end
    $var wire 16 V wordcount_r [15:0] $end
   $upscope $end
   $scope module Prot $end
    $var wire 32 n adress_o [31:0] $end
    $var wire 32 u cX [31:0] $end
    $var wire 32 Q cX_r [31:0] $end
    $var wire 32 v cY [31:0] $end
    $var wire 32 R cY_r [31:0] $end
    $var wire 32 N count_val [31:0] $end
    $var wire 32 M counter [31:0] $end
    $var wire 32 P counter_addr [31:0] $end
    $var wire 32 S data [31:0] $end
    $var wire 32 m data_o [31:0] $end
    $var wire 32 O data_o_r [31:0] $end
    $var wire  1 /! debug $end
    $var wire  1 w mipi_clk_8 $end
    $var wire  1 # rec_data $end
    $var wire  1 J rec_data_r $end
    $var wire  1 d reset $end
    $var wire  1 K state $end
    $var wire  1 \ stop $end
    $var wire  6 U type_i [5:0] $end
    $var wire  1 T valid $end
    $var wire  1 L valid_old $end
    $var wire 16 V wordcount [15:0] $end
   $upscope $end
   $scope module RxFSM $end
    $var wire  8 *! DATA [7:0] $end
    $var wire  8 )! HEADER [7:0] $end
    $var wire  8 '! LP00 [7:0] $end
    $var wire  8 &! LP01 [7:0] $end
    $var wire  8 %! LP11 [7:0] $end
    $var wire  8 (! SYNC [7:0] $end
    $var wire  8 $! TIMEOUT [7:0] $end
    $var wire 32 +! Tdterm [31:0] $end
    $var wire 32 -! Thssettle [31:0] $end
    $var wire 32 ,! Timeout [31:0] $end
    $var wire 32 +! Tlpx [31:0] $end
    $var wire  1 c clk100MHz $end
    $var wire  1 p debug0 $end
    $var wire  1 _ debug0_r $end
    $var wire  1 #! debug1 $end
    $var wire  1 #! debug1_r $end
    $var wire  1 j lane0_n $end
    $var wire  1 i lane0_p $end
    $var wire  1 l lane1_n $end
    $var wire  1 k lane1_p $end
    $var wire  1 # rec_data $end
    $var wire  1 d reset $end
    $var wire  8 ] state_mipi [7:0] $end
    $var wire  1 \ stop_rx $end
    $var wire  1 \ stop_rx_r $end
    $var wire  1 "! stop_tran $end
    $var wire  1 s term $end
    $var wire  1 ^ term_r $end
    $var wire 32 b timer_hs [31:0] $end
    $var wire 32 a timer_term [31:0] $end
    $var wire 32 ` timer_tou [31:0] $end
   $upscope $end
   $scope module SYNC $end
    $var wire  1 f ECLKI $end
    $var wire  1 % ECLKO $end
    $var wire  1 \ STOP $end
   $upscope $end
   $scope module div2 $end
    $var wire  1 & CDIVX $end
    $var wire  1 % CLKI $end
    $var wire  1 d RST $end
    $var wire  8 ' counter [7:0] $end
   $upscope $end
   $scope module div4 $end
    $var wire  1 5 CDIVX $end
    $var wire  1 & CLKI $end
    $var wire  1 d RST $end
    $var wire  8 : counter [7:0] $end
   $upscope $end
   $scope module div8 $end
    $var wire  1 w CDIVX $end
    $var wire  1 5 CLKI $end
    $var wire  1 d RST $end
    $var wire  8 z counter [7:0] $end
   $upscope $end
   $scope module lane0 $end
    $var wire  4 { ddr [3:0] $end
    $var wire  8 > detect_e [7:0] $end
    $var wire  8 ? detect_ue [7:0] $end
    $var wire  1 4 even $end
    $var wire  1 4 even_r $end
    $var wire  1 e lane $end
    $var wire  2 2 ov_fl [1:0] $end
    $var wire  2 < ov_fl_r0 [1:0] $end
    $var wire  2 2 ov_fl_r1 [1:0] $end
    $var wire  4 0 q_o [3:0] $end
    $var wire  4 0 q_o_r [3:0] $end
    $var wire  1 d reset $end
    $var wire  1 \ stop $end
    $var wire  1 $ sync $end
    $var wire  1 % sync_mipi_clk $end
    $var wire  1 & sync_mipi_clk_2 $end
    $var wire  1 ; sync_r $end
    $var wire  8 = syncbyte [7:0] $end
    $scope module IDDR $end
     $var wire  1 ( A $end
     $var wire  1 , B $end
     $var wire  1 ) C $end
     $var wire  1 e D $end
     $var wire  1 - D1 $end
     $var wire  1 % ECLK $end
     $var wire  1 ( Q0 $end
     $var wire  1 , Q1 $end
     $var wire  1 ) Q2 $end
     $var wire  1 - Q3 $end
     $var wire  1 d RST $end
     $var wire  1 & SCLK $end
    $upscope $end
   $upscope $end
   $scope module lane1 $end
    $var wire  4 } ddr [3:0] $end
    $var wire  8 D detect_e [7:0] $end
    $var wire  8 E detect_ue [7:0] $end
    $var wire  1 @ even $end
    $var wire  1 @ even_r $end
    $var wire  1 h lane $end
    $var wire  2 3 ov_fl [1:0] $end
    $var wire  2 B ov_fl_r0 [1:0] $end
    $var wire  2 3 ov_fl_r1 [1:0] $end
    $var wire  4 1 q_o [3:0] $end
    $var wire  4 1 q_o_r [3:0] $end
    $var wire  1 d reset $end
    $var wire  1 \ stop $end
    $var wire  1 | sync $end
    $var wire  1 % sync_mipi_clk $end
    $var wire  1 & sync_mipi_clk_2 $end
    $var wire  1 A sync_r $end
    $var wire  8 C syncbyte [7:0] $end
    $scope module IDDR $end
     $var wire  1 * A $end
     $var wire  1 . B $end
     $var wire  1 + C $end
     $var wire  1 h D $end
     $var wire  1 / D1 $end
     $var wire  1 % ECLK $end
     $var wire  1 * Q0 $end
     $var wire  1 . Q1 $end
     $var wire  1 + Q2 $end
     $var wire  1 / Q3 $end
     $var wire  1 d RST $end
     $var wire  1 & SCLK $end
    $upscope $end
   $upscope $end
  $upscope $end
 $upscope $end
$enddefinitions $end


#5000
0#
0$
0%
1&
b00000001 '
0(
0)
0*
0+
0,
0-
0.
0/
b0000 0
b0000 1
b00 2
b00 3
04
15
b00000000 6
b00000000 7
b00000000 8
b00000000 9
b00000001 :
0;
b00 <
b00000000 =
b10111000 >
b00101110 ?
0@
0A
b00 B
b00000000 C
b10111000 D
b00101110 E
b00000000 F
b00000000 G
b00000000 H
b00000000 I
0J
0K
0L
b00000000000000000000000000000000 M
b00000000000000000000000000000000 N
b00000000000000000000000000000000 O
b00000000000000000000000000000000 P
b00000000000000000000000000000000 Q
b00000000000000000000000000000000 R
b00000000000000000000000000000000 S
0T
b000000 U
b0000000000000000 V
b00000000000000000000000000000000 W
0X
b00000000 Y
b00000000 Z
0[
1\
b00000001 ]
0^
0_
b00000000000000000000000000000000 `
b00000000000000000000000000000000 a
b00000000000000000000000000000000 b
1c
0d
0e
1f
0g
0h
1i
1j
1k
1l
b00000000000000000000000000000000 m
b00000000000000000000000000000000 n
1o
0p
0q
0r
0s
0t
b00000000000000000000000000000000 u
b00000000000000000000000000000000 v
1w
b00000000 x
b00000000 y
b00000001 z
b0000 {
0|
b0000 }
b00000000 ~
b00000000 !!
0"!
0#!
b00000000 $!
b00000001 %!
b00000010 &!
b00000011 '!
b00000100 (!
b00000101 )!
b00000110 *!
b00000000000000000000000000000010 +!
b00000000000000000000000000010100 ,!
b00000000000000000000000000000100 -!
0.!
0/!
#10000
0f
#15000
1f
#20000
0f
#25000
1f
#30000
0f
#35000
1f
#40000
0f
#45000
0c
1f
#50000
0f
#55000
1f
0i
0k
#60000
0f
#65000
1f
#70000
0f
#75000
1f
#80000
0f
#85000
b00000010 ]
1c
1f
#90000
0f
#95000
1f
#100000
0f
#105000
1f
0j
0l
#110000
0f
#115000
1f
#120000
0f
#125000
0c
1f
#130000
0f
#135000
1f
#140000
0f
#145000
1f
#150000
0f
#155000
1f
#160000
0f
#165000
b00000011 ]
b00000000000000000000000000000001 `
b00000000000000000000000000000001 a
1c
1f
#170000
0f
#175000
1f
#180000
0f
#185000
1f
#190000
0f
#195000
1f
#200000
0f
#205000
0c
1f
#210000
0f
#215000
1f
#220000
0f
#225000
1f
#230000
0f
#235000
1f
#240000
0f
#245000
b00000000000000000000000000000010 `
b00000000000000000000000000000010 a
b00000000000000000000000000000001 b
1c
1f
#250000
0f
#255000
1f
#260000
0f
#265000
1f
#270000
0f
#275000
1f
#280000
0f
#285000
0c
1f
#290000
0f
#295000
1f
#300000
0f
#305000
1f
#310000
0f
#315000
1f
#320000
0f
#325000
1^
b00000000000000000000000000000011 `
b00000000000000000000000000000011 a
b00000000000000000000000000000010 b
1c
1f
1s
#330000
0f
#335000
1f
#340000
0f
#345000
1f
#350000
0f
#355000
1f
#360000
0f
#365000
0c
1f
#370000
0f
#375000
1f
#380000
0f
#385000
1f
#390000
0f
#395000
1f
#400000
0f
#405000
b00000000000000000000000000000100 `
b00000000000000000000000000000100 a
b00000000000000000000000000000011 b
1c
1f
#410000
0f
#415000
1f
#420000
0f
#425000
1f
#430000
0f
#435000
1f
#440000
0f
#445000
0c
1f
#450000
0f
#455000
1f
#460000
0f
#465000
1f
#470000
0f
#475000
1f
#480000
0f
#485000
b00000000000000000000000000000101 `
b00000000000000000000000000000101 a
b00000000000000000000000000000100 b
1c
1f
#490000
0f
#495000
1f
#500000
0f
#505000
1f
#510000
0f
#515000
1f
#520000
0f
#525000
0c
1f
#530000
0f
#535000
1f
#540000
0f
#545000
1f
#550000
0f
#555000
1f
#560000
0f
#565000
1%
0&
b00000010 '
0\
b00000100 ]
b00000000000000000000000000000110 `
b00000000000000000000000000000110 a
b00000000000000000000000000000101 b
1c
1f
#570000
0%
0f
#575000
1%
1&
b00000011 '
05
b00000010 :
1f
#580000
0%
0f
#585000
1%
0&
b00000100 '
1f
#590000
0%
0f
