Componets/MIPI-CSI-Transciever/MIPI_Reciever/MIPI_Reciever.v
module MIPI_Reciever(input sys_clk,mipi_clk,reset,lane0_d,lane1_d,inout lane0_p,lane0_n,lane1_p,lane1_n,output[7:0] red,output[7:0] green,output[7:0] blue,output[7:0] adress_out,output reg debug0,debug1,debug2,output termination);
    reg termination_r;
	wire stop_clk;
	wire[7:0] lane0byte,lane1byte;
	assign termination=termination_r;
	reg[31:0] timer0,timer1,timer2,timer3;//timeout termination hs-prepare
   	wire sync_detect;
	wire mipi_clk0_25_sync;
   	wire[31:0] regheader;
    LaneRx lane0(.lane_d(lane0_d),.stop(stop_clk),.mipi_clk(mipi_clk),.sync(sync_detect),.byte0(lane0byte));
    LaneRx lane1(.lane_d(lane1_d),.stop(stop_clk),.mipi_clk(mipi_clk),.sync(debug0),.byte0(lane1byte));    
    SoTFSM RxFSM(.clk100MHz(sys_clk),.reset(reset),.lane0_p(lane0_p),.lane0_n(lane0_n),.lane1_p(lane1_p),.lane1_n(lane1_n),.stop_rx(stop_clk),.term(termination_r),.debug0(debug1));
    ByteAlligner all(.mipi_clk(mipi_clk),.reset(reset),.stop(stop_clk),.sync(sync_detect),.lane0(lane0byte),.lane1(lane1byte),.out(regheader));
	wire debug2_w;
	reg sync_detect_3,sync_detect_2,sync_detect_1,sync_detect_0;
	always @(posedge mipi_clk) begin	
		sync_detect_0<=sync_detect;
		sync_detect_1<=sync_detect_0;
		sync_detect_2<=sync_detect_1;
		sync_detect_3<=sync_detect_2;		
	end
	LowProtocoll LP(.clk(mipi_clk),.reset(reset),.sync(sync_detect),.in(regheader),.stop(stop_clk),.valid(debug2_w));	
	wire sync_detect_w;
	Pulsedelay delay(.clk(mipi_clk),.in(debug2_w),.out(debug2));
endmodule
module Pulsedelay(input clk,in,output out);
reg[64:0] data=0;
	always @(posedge clk) begin
		data<={in,data[64:1]};
	end
	assign out=(data!=0)||in;
endmodule

module LaneRx(input lane_d,stop,mipi_clk,output sync,output[7:0] byte0);
	IDDRX1F l0(.D(lane_d),.SCLK(mipi_clk),.Q0(ddr[0]),.Q1(ddr[1]),.RST('b0));
	reg[7:0] byte_r;
	reg sync_r=0;
	assign sync=sync_r;
	assign byte0=byte_r;
	wire[1:0] ddr;
	always @(posedge mipi_clk or posedge stop) begin
		if(stop==1)begin
			byte_r<=0;
			sync_r<=0;
		end else begin
			byte_r<={ddr,byte_r[7:2]};
			sync_r<=(byte_r[7:0]==8'b10111000)?1:sync_r;
		end
	end
endmodule

module SoTFSM(input clk100MHz,reset,lane0_p,lane0_n,lane1_p,lane1_n,stop_tran,output reg stop_rx,term,debug0,debug1);
	///////////////////States for long and short Packet Recieve
	localparam reg[7:0] TIMEOUT=0;
	localparam reg[7:0] LP11=1;
	localparam reg[7:0] LP01=2;
	localparam reg[7:0] LP00=3;
	localparam reg[7:0] SYNC=4;
	localparam reg[7:0] HEADER=5;
	localparam reg[7:0] DATA=6;	
	///////////////////Const for Timing 
	localparam integer Tlpx=5;
	localparam integer Timeout=40;
	localparam integer Tdterm=5;
	localparam integer Thssettle=10;
	///////////////////
	reg[7:0] state_mipi=TIMEOUT;	
	integer timer_tou,timer_term,timer_hs;	
	///////////////////////////////////////////////FSM
	always @(posedge clk100MHz) begin
		if(reset==1) begin
			state_mipi<=TIMEOUT;
			timer_tou<=0;
			timer_term<=0;
			timer_hs<=0;			
			term<=0;
			stop_rx<=1;
		end else begin
			case (state_mipi)
				TIMEOUT: begin
					state_mipi<=(lane0_p==1 && lane0_n==1 &&lane1_p==1 &&lane1_n==1)?LP11:TIMEOUT; 				
					timer_tou<=0;
					timer_term<=0;
					timer_hs<=0;			
					term<=0;
					debug0<=0;
				end
				LP11:begin					
					state_mipi<=(lane0_p==0 && lane0_n==1 &&lane1_p==0 &&lane1_n==1)?LP01:LP11;	
					debug0<=0;
				end
				LP01:begin
					if(timer_tou>=Timeout) begin
						state_mipi<=TIMEOUT;
					end else begin
						if(lane0_p==0 && lane0_n==0 &&lane1_p==0 &&lane1_n==0)begin
							state_mipi<=LP00;
							timer_tou<=0;					 
						end					
					end						
					timer_tou<=timer_tou+1;
					timer_term<=timer_term+1;			
				end
				LP00:begin
					if(timer_term>=Tdterm) begin					
						term<=1;					
					end 
					if(timer_hs>=Thssettle) begin
						state_mipi<=SYNC;
						timer_tou<=0;	
						stop_rx<=0;
					end
					if(timer_tou>=Timeout)begin
						state_mipi<=TIMEOUT;
					end
					timer_tou<=timer_tou+1;
					timer_term<=timer_term+1;
					timer_hs<=timer_hs+1;					
				end
				SYNC:begin		
					debug0<=1;
					if(timer_tou>=4*Timeout)begin
						state_mipi<=TIMEOUT;
						stop_rx<=1;					
					end				
					timer_tou<=timer_tou+1;				
				end			
				default: begin
				end
			endcase		
		end	   
	end
endmodule

module ByteAlligner(input mipi_clk,reset,stop,sync,input[7:0] lane0,input[7:0] lane1,output[31:0] out);
	reg[31:0] out_r;
	assign out=out_r;
	reg start=0;
	reg[7:0] counter;
	always @(posedge mipi_clk) begin
		if(reset==1||stop==1)begin
			out_r<=0;
			start=0;
			counter<=0;
			end else begin
			start=sync?1:start;
			if(start)begin				
				if(counter<3)begin
					counter<=counter+1;
				end else begin
					counter<=0;
					out_r<={lane1,lane0,out_r[31:16]};
				end
			end
		end
	end
endmodule

module LowProtocoll(input clk,input reset,sync,input[31:0] in,input stop,output valid);
	wire[31:0] regheader;
	assign regheader=in;
	wire[7:0] ecc;
	assign ecc[0]=regheader[0]^regheader[1]^regheader[2]^regheader[4]^regheader[5]^regheader[7]^regheader[10]^regheader[11]^regheader[13]^regheader[16]^
		regheader[20]^regheader[21]^regheader[22]^regheader[23];
	assign ecc[1]=regheader[0]^regheader[1]^regheader[3]^regheader[4]^regheader[6]^regheader[8]^regheader[10]^regheader[12]^regheader[14]^regheader[17]^
		regheader[20]^regheader[21]^regheader[22]^regheader[23];
	assign ecc[2]=regheader[0]^regheader[2]^regheader[3]^regheader[5]^regheader[6]^regheader[9]^regheader[11]^regheader[12]^regheader[15]^regheader[18]^
		regheader[20]^regheader[21]^regheader[22];
	assign ecc[3]=regheader[1]^regheader[2]^regheader[3]^regheader[7]^regheader[8]^regheader[9]^regheader[13]^regheader[14]^regheader[15]^regheader[19]^
		regheader[20]^regheader[21]^regheader[23];
	assign ecc[4]=regheader[4]^regheader[5]^regheader[6]^regheader[7]^regheader[8]^regheader[9]^regheader[16]^regheader[17]^regheader[18]^regheader[19]^
		regheader[20]^regheader[22]^regheader[23];
	assign ecc[5]=regheader[10]^regheader[11]^regheader[12]^regheader[13]^regheader[14]^regheader[15]^regheader[16]^regheader[17]^regheader[18]^regheader[19]^
		regheader[21]^regheader[22]^regheader[23];	
	assign ecc[6]=0;
	assign ecc[7]=0;
	reg valid_r=0;
	reg start=0;
	reg[7:0] counter;	
	assign valid=valid_r;
	always @(posedge clk ) begin		
		if(reset==1||stop==1)begin			
			valid_r<=0;	
			start=0;
			counter<=0;			
			end else begin
			start=sync?1:start;
			if(start)begin		
				//valid_r<=((ecc==in[31:24])&&(in!=0)&&in[5:0]=='h2a)?1:0;		
				if(counter<11)begin
					counter<=counter+1;					
				end else begin
					counter<=4;					
					valid_r<=((ecc==in[31:24])&&(in!=0)&&in[5:0]=='h2a)?1:0;					
				end
			end
		end
	end	
endmodule


/*
module IDDRX1F(input D,input SCLK,input RST,output Q0,output Q1);
	reg Q0_r,Q1_r;
	always @(posedge SCLK) begin
		Q0_r<=D;
	end
	always @(negedge SCLK) begin
		Q1_r<=D;
	end	
	assign Q1=Q1_r;
	assign Q0=Q0_r;
	
endmodule

module ECLKSYNCB(input ECLKI,STOP,output ECLKO);
	integer counterP=0;
	integer counterN=0;
	reg clk;
	assign ECLKO=clk?0:ECLKI;
	always @(negedge ECLKI) begin
		if(STOP==1)begin
			counterN<=0;
			counterP<=counterP+1;
			clk<=counterP>=3?1:0;
		end else begin
			counterP<=0;
			counterN<=counterN+1;
			clk<=counterN>=3?0:1;
		end
	
	end
endmodule

module simpll(input clk,output oclk);
reg[7:0] data=0;
always @(posedge clk) begin
	data<=data+1;
end
assign oclk=data[1];
endmodule

Componets/MIPI-CSI-Transciever/MIPI_Reciever/blinky.vcd
$version Generated by VerilatedVcd $end
$date Mon Feb 13 17:49:16 2023
 $end
$timescale   1ps $end

 $scope module TOP $end
  $var wire  8 I adress_out [7:0] $end
  $var wire  8 H blue [7:0] $end
  $var wire  1 J debug0 $end
  $var wire  1 K debug1 $end
  $var wire  1 L debug2 $end
  $var wire  8 G green [7:0] $end
  $var wire  1 @ lane0_d $end
  $var wire  1 C lane0_n $end
  $var wire  1 B lane0_p $end
  $var wire  1 A lane1_d $end
  $var wire  1 E lane1_n $end
  $var wire  1 D lane1_p $end
  $var wire  1 > mipi_clk $end
  $var wire  8 F red [7:0] $end
  $var wire  1 ? reset $end
  $var wire  1 = sys_clk $end
  $var wire  1 M termination $end
  $scope module MIPI_Reciever $end
   $var wire  8 I adress_out [7:0] $end
   $var wire  8 H blue [7:0] $end
   $var wire  1 J debug0 $end
   $var wire  1 K debug1 $end
   $var wire  1 L debug2 $end
   $var wire  1 $ debug2_w $end
   $var wire  8 G green [7:0] $end
   $var wire  1 @ lane0_d $end
   $var wire  1 C lane0_n $end
   $var wire  1 B lane0_p $end
   $var wire  8 3 lane0byte [7:0] $end
   $var wire  1 A lane1_d $end
   $var wire  1 E lane1_n $end
   $var wire  1 D lane1_p $end
   $var wire  8 4 lane1byte [7:0] $end
   $var wire  1 > mipi_clk $end
   $var wire  1 V mipi_clk0_25_sync $end
   $var wire  8 F red [7:0] $end
   $var wire 32 # regheader [31:0] $end
   $var wire  1 ? reset $end
   $var wire  1 8 stop_clk $end
   $var wire  1 5 sync_detect $end
   $var wire  1 ( sync_detect_0 $end
   $var wire  1 ' sync_detect_1 $end
   $var wire  1 & sync_detect_2 $end
   $var wire  1 % sync_detect_3 $end
   $var wire  1 W sync_detect_w $end
   $var wire  1 = sys_clk $end
   $var wire  1 M termination $end
   $var wire  1 7 termination_r $end
   $var wire 32 R timer0 [31:0] $end
   $var wire 32 S timer1 [31:0] $end
   $var wire 32 T timer2 [31:0] $end
   $var wire 32 U timer3 [31:0] $end
   $scope module LP $end
    $var wire  1 > clk $end
    $var wire  8 / counter [7:0] $end
    $var wire  8 - ecc [7:0] $end
    $var wire 32 # in [31:0] $end
    $var wire 32 # regheader [31:0] $end
    $var wire  1 ? reset $end
    $var wire  1 . start $end
    $var wire  1 8 stop $end
    $var wire  1 5 sync $end
    $var wire  1 $ valid $end
    $var wire  1 $ valid_r $end
   $upscope $end
   $scope module RxFSM $end
    $var wire  8 a DATA [7:0] $end
    $var wire  8 ` HEADER [7:0] $end
    $var wire  8 ^ LP00 [7:0] $end
    $var wire  8 ] LP01 [7:0] $end
    $var wire  8 \ LP11 [7:0] $end
    $var wire  8 _ SYNC [7:0] $end
    $var wire  8 [ TIMEOUT [7:0] $end
    $var wire 32 b Tdterm [31:0] $end
    $var wire 32 d Thssettle [31:0] $end
    $var wire 32 c Timeout [31:0] $end
    $var wire 32 b Tlpx [31:0] $end
    $var wire  1 = clk100MHz $end
    $var wire  1 K debug0 $end
    $var wire  1 Z debug1 $end
    $var wire  1 C lane0_n $end
    $var wire  1 B lane0_p $end
    $var wire  1 E lane1_n $end
    $var wire  1 D lane1_p $end
    $var wire  1 ? reset $end
    $var wire  8 9 state_mipi [7:0] $end
    $var wire  1 8 stop_rx $end
    $var wire  1 Y stop_tran $end
    $var wire  1 7 term $end
    $var wire 32 < timer_hs [31:0] $end
    $var wire 32 ; timer_term [31:0] $end
    $var wire 32 : timer_tou [31:0] $end
   $upscope $end
   $scope module all $end
    $var wire  8 , counter [7:0] $end
    $var wire  8 3 lane0 [7:0] $end
    $var wire  8 4 lane1 [7:0] $end
    $var wire  1 > mipi_clk $end
    $var wire 32 # out [31:0] $end
    $var wire 32 # out_r [31:0] $end
    $var wire  1 ? reset $end
    $var wire  1 + start $end
    $var wire  1 8 stop $end
    $var wire  1 5 sync $end
   $upscope $end
   $scope module delay $end
    $var wire  1 > clk $end
    $var wire 65 0 data [64:0] $end
    $var wire  1 $ in $end
    $var wire  1 L out $end
   $upscope $end
   $scope module lane0 $end
    $var wire  8 3 byte0 [7:0] $end
    $var wire  8 3 byte_r [7:0] $end
    $var wire  2 N ddr [1:0] $end
    $var wire  1 @ lane_d $end
    $var wire  1 > mipi_clk $end
    $var wire  1 8 stop $end
    $var wire  1 5 sync $end
    $var wire  1 5 sync_r $end
    $scope module l0 $end
     $var wire  1 @ D $end
     $var wire  1 ) Q0 $end
     $var wire  1 ) Q0_r $end
     $var wire  1 O Q1 $end
     $var wire  1 O Q1_r $end
     $var wire  1 X RST $end
     $var wire  1 > SCLK $end
    $upscope $end
   $upscope $end
   $scope module lane1 $end
    $var wire  8 4 byte0 [7:0] $end
    $var wire  8 4 byte_r [7:0] $end
    $var wire  2 P ddr [1:0] $end
    $var wire  1 A lane_d $end
    $var wire  1 > mipi_clk $end
    $var wire  1 8 stop $end
    $var wire  1 J sync $end
    $var wire  1 6 sync_r $end
    $scope module l0 $end
     $var wire  1 A D $end
     $var wire  1 * Q0 $end
     $var wire  1 * Q0_r $end
     $var wire  1 Q Q1 $end
     $var wire  1 Q Q1_r $end
     $var wire  1 X RST $end
     $var wire  1 > SCLK $end
    $upscope $end
   $upscope $end
  $upscope $end
 $upscope $end
$enddefinitions $end


#5000
b00000000000000000000000000000000 #
0$
0%
0&
0'
0(
0)
0*
0+
b00000000 ,
b00000000 -
0.
b00000000 /
b00000000000000000000000000000000000000000000000000000000000000000 0
b00000000 3
b00000000 4
05
06
07
08
b00000001 9
b00000000000000000000000000000000 :
b00000000000000000000000000000000 ;
b00000000000000000000000000000000 <
1=
1>
0?
0@
0A
1B
1C
1D
1E
b00000000 F
b00000000 G
b00000000 H
b00000000 I
0J
0K
0L
0M
b00 N
0O
b00 P
0Q
b00000000000000000000000000000000 R
b00000000000000000000000000000000 S
b00000000000000000000000000000000 T
b00000000000000000000000000000000 U
0V
0W
0X
0Y
0Z
b00000000 [
b00000001 \
b00000010 ]
b00000011 ^
b00000100 _
b00000101 `
b00000110 a
b00000000000000000000000000000101 b
b00000000000000000000000000101000 c
b00000000000000000000000000001010 d
#10000
0=
0>
#15000
1=
1>
#20000
0=
0>
#25000
1=
1>
#30000
0=
0>
#35000
1=
1>
#40000
0=
0>
#45000
1=
1>
#50000
0=
0>
#55000
b00000010 9
1=
1>
0B
0D
#60000
0=
0>
#65000
b00000000000000000000000000000001 :
b00000000000000000000000000000001 ;
1=
1>
#70000
0=
0>
#75000
b00000000000000000000000000000010 :
b00000000000000000000000000000010 ;
1=
1>
#80000
0=
0>
#85000
b00000000000000000000000000000011 :
b00000000000000000000000000000011 ;
1=
1>
#90000
0=
0>
#95000
b00000000000000000000000000000100 :
b00000000000000000000000000000100 ;
1=
1>
#100000
0=
0>
#105000
b00000011 9
b00000000000000000000000000000101 :
b00000000000000000000000000000101 ;
1=
1>
0C
0E
#110000
0=
0>
#115000
17
b00000000000000000000000000000110 :
b00000000000000000000000000000110 ;
b00000000000000000000000000000001 <
1=
1>
1M
#120000
0=
0>
#125000
b00000000000000000000000000000111 :
b00000000000000000000000000000111 ;
b00000000000000000000000000000010 <
1=
1>
#130000
0=
0>
#135000
b00000000000000000000000000001000 :
b00000000000000000000000000001000 ;
b00000000000000000000000000000011 <
1=
1>
#140000
0=
0>
#145000
b00000000000000000000000000001001 :
b00000000000000000000000000001001 ;
b00000000000000000000000000000100 <
1=
1>
#150000
0=
0>
#155000
b00000000000000000000000000001010 :
b00000000000000000000000000001010 ;
b00000000000000000000000000000101 <
1=
1>
#160000
0=
0>
#165000
b00000000000000000000000000001011 :
b00000000000000000000000000001011 ;
b00000000000000000000000000000110 <
1=
1>
#170000
0=
0>
#175000
b00000000000000000000000000001100 :
b00000000000000000000000000001100 ;
b00000000000000000000000000000111 <
1=
1>
#180000
0=
0>
#185000
b00000000000000000000000000001101 :
b00000000000000000000000000001101 ;
b00000000000000000000000000001000 <
1=
1>
#190000
0=
0>
#195000
b00000000000000000000000000001110 :
b00000000000000000000000000001110 ;
b00000000000000000000000000001001 <
1=
1>
#200000
0=
0>
#205000
b00000000000000000000000000001111 :
b00000000000000000000000000001111 ;
b00000000000000000000000000001010 <
1=
1>
#210000
0=
0>
#215000
b00000100 9
b00000000000000000000000000010000 :
b00000000000000000000000000010000 ;
b00000000000000000000000000001011 <
1=
1>
#220000
0=
0>
#225000
b00000000000000000000000000010001 :
1=
1>
1K
#230000
0=
0>
#235000
b00000000000000000000000000010010 :
1=
1>
#240000
0=
0>
#245000
b00000000000000000000000000010011 :
1=
1>
#250000
0=
0>
#255000
b00000000000000000000000000010100 :
1=
1>
#260000
0=
0>
#265000
b00000000000000000000000000010101 :
1=
1>
#270000
0=
0>
1@
1A
b10 N
1O
b10 P
1Q
#275000
1)
1*
b10000000 3
b10000000 4
b00000000000000000000000000010110 :
1=
1>
b11 N
b11 P
#280000
0=
0>
#285000
0)
0*
b11100000 3
b11100000 4
b00000000000000000000000000010111 :
1=
1>
0@
0A
b10 N
b10 P
#290000
0=
0>
1@
1A
#295000
1)
b10111000 3
b10111000 4
b00000000000000000000000000011000 :
1=
1>
0A
b11 N
#300000
0=
0>
b00 P
0Q
#305000
b11101110 3
b00101110 4
15
16
b00000000000000000000000000011001 :
1=
1>
1J
#310000
0=
0>
0@
b01 N
0O
#315000
1(
1*
1+
b00000001 ,
1.
b00000001 /
b01111011 3
b00001011 4
b00000000000000000000000000011010 :
1=
1>
1@
1A
b01 P
#320000
0=
0>
b11 N
1O
b11 P
1Q
#325000
1'
0)
b00000010 ,
b00000010 /
b11011110 3
b11000010 4
b00000000000000000000000000011011 :
1=
1>
0@
b10 N
#330000
0=
0>
b00 N
0O
#335000
1&
1)
b00000011 ,
b00000011 /
b00110111 3
b11110000 4
b00000000000000000000000000011100 :
1=
1>
1@
b01 N
#340000
0=
0>
0@
#345000
b11110000001101110000000000000000 #
1%
0)
b00000000 ,
b00000111 -
b00000100 /
b01001101 3
b11111100 4
b00000000000000000000000000011101 :
1=
1>
b00 N
#350000
0=
0>
#355000
b00000001 ,
b00000101 /
b00010011 3
b11111111 4
b00000000000000000000000000011110 :
1=
1>
#360000
0=
0>
#365000
0*
b00000010 ,
b00000110 /
b00000100 3
b00000000000000000000000000011111 :
1=
1>
0A
b10 P
#370000
0=
0>
b00 P
0Q
#375000
b00000011 ,
b00000111 /
b00000001 3
b00111111 4
b00000000000000000000000000100000 :
1=
1>
#380000
0=
0>
#385000
b00111111000000011111000000110111 #
b00000000 ,
b00111111 -
b00001000 /
b00000000 3
b00001111 4
b00000000000000000000000000100001 :
1=
1>
#390000
0=
0>
#395000
b00000001 ,
b00001001 /
b00000011 4
b00000000000000000000000000100010 :
1=
1>
#400000
0=
0>
#405000
b00000010 ,
b00001010 /
b00000000 4
b00000000000000000000000000100011 :
1=
1>
#410000
0=
0>
#415000
b00000011 ,
b00001011 /
b00000000000000000000000000100100 :
1=
1>
#420000
0=
0>
#425000
b00000000000000000011111100000001 #
1$
b00000000 ,
b00001000 -
b00000100 /
b00000000000000000000000000100101 :
1=
1>
1L
#430000
0=
0>
#435000
b00000001 ,
b00000101 /
b10000000000000000000000000000000000000000000000000000000000000000 0
b00000000000000000000000000100110 :
1=
1>
#440000
0=
0>
#445000
b00000010 ,
b00000110 /
b11000000000000000000000000000000000000000000000000000000000000000 0
b00000000000000000000000000100111 :
1=
1>
#450000
0=
0>
#455000
b00000011 ,
b00000111 /
b11100000000000000000000000000000000000000000000000000000000000000 0
b00000000000000000000000000101000 :
1=
1>
#460000
0=
0>
#465000
b00000000000000000000000000000000 #
b00000000 ,
b00000000 -
b00001000 /
b11110000000000000000000000000000000000000000000000000000000000000 0
b00000000000000000000000000101001 :
1=
1>
#470000
0=
0>
#475000
b00000001 ,
b00001001 /
b11111000000000000000000000000000000000000000000000000000000000000 0
b00000000000000000000000000101010 :
1=
1>
#480000
0=
0>
#485000
b00000010 ,
b00001010 /
b11111100000000000000000000000000000000000000000000000000000000000 0
b00000000000000000000000000101011 :
1=
1>
#490000
0=
0>
#495000
b00000011 ,
b00001011 /
b11111110000000000000000000000000000000000000000000000000000000000 0
b00000000000000000000000000101100 :
1=
1>
#500000
0=
0>
#505000
0$
b00000000 ,
b00000100 /
b11111111000000000000000000000000000000000000000000000000000000000 0
b00000000000000000000000000101101 :
1=
1>
#510000
0=
0>
#515000
b00000001 ,
b00000101 /
b01111111100000000000000000000000000000000000000000000000000000000 0
b00000000000000000000000000101110 :
1=
1>
#520000
0=
0>
#525000
b00000010 ,
b00000110 /
b00111111110000000000000000000000000000000000000000000000000000000 0
b00000000000000000000000000101111 :
1=
1>
#530000
0=
0>
#535000
b00000011 ,
b00000111 /
b00011111111000000000000000000000000000000000000000000000000000000 0
b00000000000000000000000000110000 :
1=
1>
#540000
0=
0>
#545000
b00000000 ,
b00001000 /
b00001111111100000000000000000000000000000000000000000000000000000 0
b00000000000000000000000000110001 :
1=
1>
#550000
0=
0>
#555000
b00000001 ,
b00001001 /
b00000111111110000000000000000000000000000000000000000000000000000 0
b00000000000000000000000000110010 :
1=
1>
#560000
0=
0>
#565000
b00000010 ,
b00001010 /
b00000011111111000000000000000000000000000000000000000000000000000 0
b00000000000000000000000000110011 :
1=
1>
#570000
0=
0>
#575000
b00000011 ,
b00001011 /
b00000001111111100000000000000000000000000000000000000000000000000 0
b00000000000000000000000000110100 :
1=
1>
#580000
0=
0>
#585000
b00000000 ,
b00000100 /
b00000000111111110000000000000000000000000000000000000000000000000 0
b00000000000000000000000000110101 :
1=
1>
#590000
0=
0>
#595000
b00000001 ,
b00000101 /
b00000000011111111000000000000000000000000000000000000000000000000 0
b00000000000000000000000000110110 :
1=
1>
#600000
0=
0>
#605000
b00000010 ,
b00000110 /
b00000000001111111100000000000000000000000000000000000000000000000 0
b00000000000000000000000000110111 :
1=
1>
#610000
0=
0>
#615000
b00000011 ,
b00000111 /
b00000000000111111110000000000000000000000000000000000000000000000 0
b00000000000000000000000000111000 :
1=
1>
#620000
0=
0>
#625000
b00000000 ,
b00001000 /
b00000000000011111111000000000000000000000000000000000000000000000 0
b00000000000000000000000000111001 :
1=
1>
#630000
0=
0>
#635000
b00000001 ,
b00001001 /
b00000000000001111111100000000000000000000000000000000000000000000 0
b00000000000000000000000000111010 :
1=
1>
#640000
0=
0>
#645000
b00000010 ,
b00001010 /
b00000000000000111111110000000000000000000000000000000000000000000 0
b00000000000000000000000000111011 :
1=
1>
#650000
0=
0>
#655000
b00000011 ,
b00001011 /
b00000000000000011111111000000000000000000000000000000000000000000 0
b00000000000000000000000000111100 :
1=
1>
#660000
0=
0>
#665000
b00000000 ,
b00000100 /
b00000000000000001111111100000000000000000000000000000000000000000 0
b00000000000000000000000000111101 :
1=
1>
#670000
0=
0>
#675000
b00000001 ,
b00000101 /
b00000000000000000111111110000000000000000000000000000000000000000 0
b00000000000000000000000000111110 :
1=
1>
#680000
0=
0>
#685000
b00000010 ,
b00000110 /
b00000000000000000011111111000000000000000000000000000000000000000 0
b00000000000000000000000000111111 :
1=
1>
#690000
0=
0>
#695000
b00000011 ,
b00000111 /
b00000000000000000001111111100000000000000000000000000000000000000 0
b00000000000000000000000001000000 :
1=
1>
#700000
0=
0>
#705000
b00000000 ,
b00001000 /
b00000000000000000000111111110000000000000000000000000000000000000 0
b00000000000000000000000001000001 :
1=
1>
#710000
0=
0>
#715000
b00000001 ,
b00001001 /
b00000000000000000000011111111000000000000000000000000000000000000 0
b00000000000000000000000001000010 :
1=
1>
#720000
0=
0>
#725000
b00000010 ,
b00001010 /
b00000000000000000000001111111100000000000000000000000000000000000 0
b00000000000000000000000001000011 :
1=
1>
#730000
0=
0>
#735000
b00000011 ,
b00001011 /
b00000000000000000000000111111110000000000000000000000000000000000 0
b00000000000000000000000001000100 :
1=
1>
#740000
0=
0>
#745000
b00000000 ,
b00000100 /
b00000000000000000000000011111111000000000000000000000000000000000 0
b00000000000000000000000001000101 :
1=
1>
#750000
0=
0>
#755000
b00000001 ,
b00000101 /
b00000000000000000000000001111111100000000000000000000000000000000 0
b00000000000000000000000001000110 :
1=
1>
#760000
0=
0>
#765000
b00000010 ,
b00000110 /
b00000000000000000000000000111111110000000000000000000000000000000 0
b00000000000000000000000001000111 :
1=
1>
#770000
0=
0>
#775000
b00000011 ,
b00000111 /
b00000000000000000000000000011111111000000000000000000000000000000 0
b00000000000000000000000001001000 :
1=
1>
#780000
0=
0>
#785000
b00000000 ,
b00001000 /
b00000000000000000000000000001111111100000000000000000000000000000 0
b00000000000000000000000001001001 :
1=
1>
#790000
0=
0>
#795000
b00000001 ,
b00001001 /
b00000000000000000000000000000111111110000000000000000000000000000 0
b00000000000000000000000001001010 :
1=
1>
#800000
0=
0>
#805000
b00000010 ,
b00001010 /
b00000000000000000000000000000011111111000000000000000000000000000 0
b00000000000000000000000001001011 :
1=
1>
#810000
0=
0>
#815000
b00000011 ,
b00001011 /
b00000000000000000000000000000001111111100000000000000000000000000 0
b00000000000000000000000001001100 :
1=
1>
#820000
0=
0>
#825000
b00000000 ,
b00000100 /
b00000000000000000000000000000000111111110000000000000000000000000 0
b00000000000000000000000001001101 :
1=
1>
#830000
0=
0>
#835000
b00000001 ,
b00000101 /
b00000000000000000000000000000000011111111000000000000000000000000 0
b00000000000000000000000001001110 :
1=
1>
#840000
0=
0>
#845000
b00000010 ,
b00000110 /
b00000000000000000000000000000000001111111100000000000000000000000 0
b00000000000000000000000001001111 :
1=
1>
#850000
0=
0>
#855000
b00000011 ,
b00000111 /
b00000000000000000000000000000000000111111110000000000000000000000 0
b00000000000000000000000001010000 :
1=
1>
#860000
0=
0>
#865000
b00000000 ,
b00001000 /
b00000000000000000000000000000000000011111111000000000000000000000 0
b00000000000000000000000001010001 :
1=
1>
#870000
0=
0>
#875000
b00000001 ,
b00001001 /
b00000000000000000000000000000000000001111111100000000000000000000 0
b00000000000000000000000001010010 :
1=
1>
#880000
0=
0>
#885000
b00000010 ,
b00001010 /
b00000000000000000000000000000000000000111111110000000000000000000 0
b00000000000000000000000001010011 :
1=
1>
#890000
0=
0>
#895000
b00000011 ,
b00001011 /
b00000000000000000000000000000000000000011111111000000000000000000 0
b00000000000000000000000001010100 :
1=
1>
#900000
0=
0>
#905000
b00000000 ,
b00000100 /
b00000000000000000000000000000000000000001111111100000000000000000 0
b00000000000000000000000001010101 :
1=
1>
#910000
0=
0>
#915000
b00000001 ,
b00000101 /
b00000000000000000000000000000000000000000111111110000000000000000 0
b00000000000000000000000001010110 :
1=
1>
#920000
0=
0>
#925000
b00000010 ,
b00000110 /
b00000000000000000000000000000000000000000011111111000000000000000 0
b00000000000000000000000001010111 :
1=
1>
#930000
0=
0>
#935000
b00000011 ,
b00000111 /
b00000000000000000000000000000000000000000001111111100000000000000 0
b00000000000000000000000001011000 :
1=
1>
#940000
0=
0>
#945000
b00000000 ,
b00001000 /
b00000000000000000000000000000000000000000000111111110000000000000 0
b00000000000000000000000001011001 :
1=
1>
#950000
0=
0>
#955000
b00000001 ,
b00001001 /
b00000000000000000000000000000000000000000000011111111000000000000 0
b00000000000000000000000001011010 :
1=
1>
#960000
0=
0>
#965000
b00000010 ,
b00001010 /
b00000000000000000000000000000000000000000000001111111100000000000 0
b00000000000000000000000001011011 :
1=
1>
#970000
0=
0>
#975000
b00000011 ,
b00001011 /
b00000000000000000000000000000000000000000000000111111110000000000 0
b00000000000000000000000001011100 :
1=
1>
#980000
0=
0>
#985000
b00000000 ,
b00000100 /
b00000000000000000000000000000000000000000000000011111111000000000 0
b00000000000000000000000001011101 :
1=
1>
#990000
0=
0>
#995000
b00000001 ,
b00000101 /
b00000000000000000000000000000000000000000000000001111111100000000 0
b00000000000000000000000001011110 :
1=
1>
#1000000
0=
0>
#1005000
b00000010 ,
b00000110 /
b00000000000000000000000000000000000000000000000000111111110000000 0
b00000000000000000000000001011111 :
1=
1>
#1010000
0=
0>
#1015000
b00000011 ,
b00000111 /
b00000000000000000000000000000000000000000000000000011111111000000 0
b00000000000000000000000001100000 :
1=
1>
#1020000
0=
0>
#1025000
b00000000 ,
b00001000 /
b00000000000000000000000000000000000000000000000000001111111100000 0
b00000000000000000000000001100001 :
1=
1>
#1030000
0=
0>
#1035000
b00000001 ,
b00001001 /
b00000000000000000000000000000000000000000000000000000111111110000 0
b00000000000000000000000001100010 :
1=
1>
#1040000
0=
0>
#1045000
b00000010 ,
b00001010 /
b00000000000000000000000000000000000000000000000000000011111111000 0
b00000000000000000000000001100011 :
1=
1>
#1050000
0=
0>
#1055000
b00000011 ,
b00001011 /
b00000000000000000000000000000000000000000000000000000001111111100 0
b00000000000000000000000001100100 :
1=
1>
#1060000
0=
0>
#1065000
b00000000 ,
b00000100 /
b00000000000000000000000000000000000000000000000000000000111111110 0
b00000000000000000000000001100101 :
1=
1>
#1070000
0=
0>
#1075000
b00000001 ,
b00000101 /
b00000000000000000000000000000000000000000000000000000000011111111 0
b00000000000000000000000001100110 :
1=
1>
#1080000
0=
0>
#1085000
b00000010 ,
b00000110 /
b00000000000000000000000000000000000000000000000000000000001111111 0
b00000000000000000000000001100111 :
1=
1>
#1090000
0=
0>
#1095000
b00000011 ,
b00000111 /
b00000000000000000000000000000000000000000000000000000000000111111 0
b00000000000000000000000001101000 :
1=
1>
#1100000
0=
0>
#1105000
b00000000 ,
b00001000 /
b00000000000000000000000000000000000000000000000000000000000011111 0
b00000000000000000000000001101001 :
1=
1>
#1110000
0=
0>
#1115000
b00000001 ,
b00001001 /
b00000000000000000000000000000000000000000000000000000000000001111 0
b00000000000000000000000001101010 :
1=
1>
