Componets/MIPI-CSI-Transciever/MIPI_Reciever/MIPI_Reciever.v
module MIPI_Reciever(input byte_clk,bit_clk,pixclk,reset,lane0,lane1,output[7:0] red,output[7:0] green,output[7:0] blue,output[24:0] address_out,output reg [2:0] led);
reg[7:0] bytereg0=0;
reg[7:0] bytereg1=0;
reg[7:0] counter=0;
integer mipi_cnt=0;
reg[7:0] data_id=0;
reg[15:0] word_cnt;
reg FS,FE,PIX;
reg[7:0] state_byte=idle_bitclk;
reg[7:0] state_mipi=idle_mipi;
reg ena_byte8=0;
reg[24:0] addres=0;
reg[31:0] regheader0;
reg[31:0] regheader1;
wire[7:0] ecc;
reg[31:0] wordcount;
wire[1:0] lane0ddr;
wire[1:0] lane1ddr;

    IDDRX1F l0(.D(lane0),.SCLK(bit_clk),.Q0(lane0ddr[0]),.Q1(lane0ddr[1]),.RST(reset));
    IDDRX1F l1(.D(lane1),.SCLK(bit_clk),.Q0(lane1ddr[0]),.Q1(lane1ddr[1]),.RST(reset));
    assign ecc[0]=regheader0[0]^regheader0[1]^regheader0[2]^regheader0[4]^regheader0[5]^regheader0[7]^regheader0[10]^regheader0[11]^regheader0[13]^regheader0[16]^
		regheader0[20]^regheader0[21]^regheader0[22]^regheader0[23];
	assign ecc[1]=regheader0[0]^regheader0[1]^regheader0[3]^regheader0[4]^regheader0[6]^regheader0[8]^regheader0[10]^regheader0[12]^regheader0[14]^regheader0[17]^
		regheader0[20]^regheader0[21]^regheader0[22]^regheader0[23];
	assign ecc[2]=regheader0[0]^regheader0[2]^regheader0[3]^regheader0[5]^regheader0[6]^regheader0[9]^regheader0[11]^regheader0[12]^regheader0[15]^regheader0[18]^
		regheader0[20]^regheader0[21]^regheader0[22];
	assign ecc[3]=regheader0[1]^regheader0[2]^regheader0[3]^regheader0[7]^regheader0[8]^regheader0[9]^regheader0[13]^regheader0[14]^regheader0[15]^regheader0[19]^
		regheader0[20]^regheader0[21]^regheader0[23];
	assign ecc[4]=regheader0[4]^regheader0[5]^regheader0[6]^regheader0[7]^regheader0[8]^regheader0[9]^regheader0[16]^regheader0[17]^regheader0[18]^regheader0[19]^
		regheader0[20]^regheader0[22]^regheader0[23];
	assign ecc[5]=regheader0[10]^regheader0[11]^regheader0[12]^regheader0[13]^regheader0[14]^regheader0[15]^regheader0[16]^regheader0[17]^regheader0[18]^regheader0[19]^
		regheader0[21]^regheader0[22]^regheader0[23];	
	assign ecc[6]=0;
	assign ecc[7]=0;



////////////////////States for byteclk datasample
localparam reg[7:0] idle_bitclk=0;
localparam reg[7:0] bitclk=1;
///////////////////States for long and short Packet Recieve
localparam reg[7:0] idle_mipi=2;
localparam reg[7:0] PH_mipi=3;
localparam reg[7:0] data_mipi=4;
localparam reg[7:0] PF_mipi=5;
//////////////////Const for Data_id
localparam reg[5:0] FS_const=6'h00;//Framestart
localparam reg[5:0] FE_const=6'h01;//Frameend
localparam reg[5:0] ED_const=6'h12;//Embedded data
localparam reg[5:0] RAW8_const=6'h2A;//Embedded data
localparam reg[5:0] RAW10_const=6'h2B;//Embedded data
///////////////////////FSM byte/bitclk
always@(posedge bit_clk)begin
	if(reset==1) begin
	end else begin
		case (state_byte)
			idle_bitclk: begin
				regheader0<={lane0ddr,regheader0[31:2]};
				regheader1<={lane1ddr,regheader1[31:2]};
				bytereg0<={lane0ddr,bytereg0[7:2]};
				bytereg1<={lane1ddr,bytereg1[7:2]};
			end			
			default: begin
			end
		endcase
	end
end
//////////////////////////
always @(posedge bit_clk or posedge reset) begin
	if(reset==1)begin
		state_mipi<=idle_mipi;
		led<=0;
	end else begin
		case (state_mipi)
			idle_mipi: begin							
				FS<=0;
				FE<=0;
				PIX<=0;
				led<=0;		
				/*if(regheader0[7:6]=='h00&&regheader0[5:0]==FS_const[5:0]&&regheader0[31:24]==ecc)begin
					FS<=1;//Frame start
					led[0]<=1;
					addres<=0;
				end/* else if(regheader0[7:6]=='h00&&regheader0[5:0]==FE_const[5:0]&&regheader0[31:24]==ecc)begin
					//led[1]<=1;//Frame end					
				end */ if(regheader0[5:0]==RAW8_const[5:0]&&regheader0[31:24]==ecc)begin
					PIX<=1;
					led[1]<=1;
					//state_mipi<=data_mipi;
					mipi_cnt=0;
					wordcount<=(regheader0[23:8])*4;
				end				
			end			
			data_mipi: begin
				if(mipi_cnt<=wordcount-1) begin
					mipi_cnt=mipi_cnt+1;
					addres<=(mipi_cnt)/8;
				end else begin
					state_mipi<=idle_mipi;
					mipi_cnt=0;
				end
			end
			PF_mipi: begin
				state_mipi<=idle_mipi;
			end
			default: begin
			end
		endcase
	end	
end
endmodule

/*module IDDRX1F(input D,input SCLK,input RST,output Q0,output Q1);
	reg Q0_r,Q1_r;
	always @(posedge SCLK) begin
		Q0_r<=D;
	end
	always @(negedge SCLK) begin
		Q1_r<=D;
	end	
	assign Q1=Q1_r;
	assign Q0=Q0_r;
	
endmodule

Componets/MIPI-CSI-Transciever/MIPI_Reciever/blinky.vcd
$version Generated by VerilatedVcd $end
$date Mon Dec 12 17:57:22 2022
 $end
$timescale   1ps $end

 $scope module TOP $end
  $var wire 25 8 address_out [24:0] $end
  $var wire  1 0 bit_clk $end
  $var wire  8 7 blue [7:0] $end
  $var wire  1 / byte_clk $end
  $var wire  8 6 green [7:0] $end
  $var wire  1 3 lane0 $end
  $var wire  1 4 lane1 $end
  $var wire  3 9 led [2:0] $end
  $var wire  1 1 pixclk $end
  $var wire  8 5 red [7:0] $end
  $var wire  1 2 reset $end
  $scope module MIPI_Reciever $end
   $var wire  6 J ED_const [5:0] $end
   $var wire  1 * FE $end
   $var wire  6 I FE_const [5:0] $end
   $var wire  1 ) FS $end
   $var wire  6 H FS_const [5:0] $end
   $var wire  8 G PF_mipi [7:0] $end
   $var wire  8 E PH_mipi [7:0] $end
   $var wire  1 + PIX $end
   $var wire  6 L RAW10_const [5:0] $end
   $var wire  6 K RAW8_const [5:0] $end
   $var wire 25 - addres [24:0] $end
   $var wire 25 8 address_out [24:0] $end
   $var wire  1 0 bit_clk $end
   $var wire  8 C bitclk [7:0] $end
   $var wire  8 7 blue [7:0] $end
   $var wire  1 / byte_clk $end
   $var wire  8 # bytereg0 [7:0] $end
   $var wire  8 $ bytereg1 [7:0] $end
   $var wire  8 @ counter [7:0] $end
   $var wire  8 @ data_id [7:0] $end
   $var wire  8 F data_mipi [7:0] $end
   $var wire  8 ; ecc [7:0] $end
   $var wire  1 B ena_byte8 $end
   $var wire  8 6 green [7:0] $end
   $var wire  8 @ idle_bitclk [7:0] $end
   $var wire  8 D idle_mipi [7:0] $end
   $var wire  1 3 lane0 $end
   $var wire  2 < lane0ddr [1:0] $end
   $var wire  1 4 lane1 $end
   $var wire  2 = lane1ddr [1:0] $end
   $var wire  3 9 led [2:0] $end
   $var wire 32 ( mipi_cnt [31:0] $end
   $var wire  1 1 pixclk $end
   $var wire  8 5 red [7:0] $end
   $var wire 32 : regheader0 [31:0] $end
   $var wire 32 % regheader1 [31:0] $end
   $var wire  1 2 reset $end
   $var wire  8 @ state_byte [7:0] $end
   $var wire  8 , state_mipi [7:0] $end
   $var wire 16 A word_cnt [15:0] $end
   $var wire 32 . wordcount [31:0] $end
   $scope module l0 $end
    $var wire  1 3 D $end
    $var wire  1 & Q0 $end
    $var wire  1 & Q0_r $end
    $var wire  1 > Q1 $end
    $var wire  1 > Q1_r $end
    $var wire  1 2 RST $end
    $var wire  1 0 SCLK $end
   $upscope $end
   $scope module l1 $end
    $var wire  1 4 D $end
    $var wire  1 ' Q0 $end
    $var wire  1 ' Q0_r $end
    $var wire  1 ? Q1 $end
    $var wire  1 ? Q1_r $end
    $var wire  1 2 RST $end
    $var wire  1 0 SCLK $end
   $upscope $end
  $upscope $end
 $upscope $end
$enddefinitions $end


#10
b00000000 #
b00000000 $
b00000000000000000000000000000000 %
1&
0'
b00000000000000000000000000000000 (
0)
0*
0+
b00000010 ,
b0000000000000000000000000 -
b00000000000000000000000000000000 .
0/
10
01
02
13
04
b00000000 5
b00000000 6
b00000000 7
b0000000000000000000000000 8
b000 9
b00000000000000000000000000000000 :
b00000000 ;
b01 <
b00 =
0>
0?
b00000000 @
b0000000000000000 A
0B
b00000001 C
b00000010 D
b00000011 E
b00000100 F
b00000101 G
b000000 H
b000001 I
b010010 J
b101010 K
b101011 L
#15
#20
00
b11 <
1>
#25
#30
b11000000 #
0&
10
03
b11000000000000000000000000000000 :
b10 <
#35
#40
00
13
#45
#50
b10110000 #
10
03
b10110000000000000000000000000000 :
#55
#60
00
13
#65
#70
b10101100 #
10
03
b10101100000000000000000000000000 :
#75
#80
00
b00 <
0>
#85
#90
b00101011 #
10
b00101011000000000000000000000000 :
#95
#100
00
#105
#110
b00001010 #
10
b00001010110000000000000000000000 :
b00001100 ;
#115
#120
00
#125
#130
b00000010 #
1&
10
13
b00000010101100000000000000000000 :
b00001011 ;
b01 <
#135
#140
00
b11 <
1>
#145
#150
b11000000 #
10
b11000000101011000000000000000000 :
b00011000 ;
#155
#160
00
#165
#170
b11110000 #
10
b11110000001010110000000000000000 :
b00010100 ;
#175
#180
00
#185
#190
b11111100 #
0&
10
03
b11111100000010101100000000000000 :
b00001100 ;
b10 <
#195
#200
00
b00 <
0>
#205
#210
b00111111 #
10
b00111111000000101011000000000000 :
b00010001 ;
#215
#220
00
#225
#230
b00001111 #
10
b00001111110000001010110000000000 :
b00001111 ;
#235
#240
00
#245
#250
b00000011 #
1&
10
13
b00000011111100000010101100000000 :
b00110110 ;
b01 <
#255
#260
00
03
#265
#270
b01000000 #
10
13
b01000000111111000000101011000000 :
b00000110 ;
#275
#280
00
b11 <
1>
#285
#290
b11010000 #
10
b11010000001111110000001010110000 :
b00111100 ;
#295
#300
00
03
b01 <
0>
#305
#310
b01110100 #
0&
10
b01110100000011111100000010101100 :
b00000110 ;
b00 <
#315
#320
00
#325
#330
b00011101 #
10
b00011101000000111111000000101011 :
b00011101 ;
#335
#340
00
#345
#350
b00000111 #
1+
b00000100 ,
b00000000000000000000111111000000 .
10
b010 9
b00000111010000001111110000001010 :
b00111101 ;
#355
#360
00
#365
#370
b00000001 #
b00000000000000000000000000000001 (
10
b00000001110100000011111100000010 :
b00010111 ;
#375
#380
00
#385
#390
b00000000 #
b00000000000000000000000000000010 (
10
b00000000011101000000111111000000 :
b00111100 ;
#395
#400
00
#405
#410
b00000000000000000000000000000011 (
10
b00000000000111010000001111110000 :
b00101101 ;
#415
#420
00
#425
#430
b00000000000000000000000000000100 (
10
b00000000000001110100000011111100 :
b00010111 ;
#435
#440
00
#445
#450
b00000000000000000000000000000101 (
10
b00000000000000011101000000111111 :
b00011000 ;
#455
#460
00
#465
#470
b00000000000000000000000000000110 (
10
b00000000000000000111010000001111 :
b00001001 ;
#475
#480
00
#485
#490
b00000000000000000000000000000111 (
10
b00000000000000000001110100000011 :
b00110110 ;
#495
#500
00
#505
#510
b00000000000000000000000000001000 (
b0000000000000000000000001 -
10
b00000000000000000000011101000000 :
b00110011 ;
#515
#520
00
#525
#530
b00000000000000000000000000001001 (
10
b00000000000000000000000111010000 :
b00000110 ;
#535
#540
00
#545
#550
b00000000000000000000000000001010 (
10
b00000000000000000000000001110100 :
b00011101 ;
#555
#560
00
#565
#570
b00000000000000000000000000001011 (
10
b00000000000000000000000000011101 :
b00010111 ;
#575
#580
00
#585
#590
b00000000000000000000000000001100 (
10
b00000000000000000000000000000111 :
b00000001 ;
#595
#600
00
#605
#610
b00000000000000000000000000001101 (
10
b00000000000000000000000000000001 :
b00000111 ;
#615
#620
00
#625
#630
b00000000000000000000000000001110 (
10
b00000000000000000000000000000000 :
b00000000 ;
#635
#640
00
#645
#650
b00000000000000000000000000001111 (
10
#655
#660
00
#665
#670
b00000000000000000000000000010000 (
b0000000000000000000000010 -
10
#675
#680
00
#685
#690
b00000000000000000000000000010001 (
10
#695
#700
00
#705
#710
b00000000000000000000000000010010 (
10
#715
#720
00
#725
#730
b00000000000000000000000000010011 (
10
#735
#740
00
#745
#750
b00000000000000000000000000010100 (
10
#755
#760
00
#765
#770
b00000000000000000000000000010101 (
10
#775
#780
00
#785
#790
b00000000000000000000000000010110 (
10
#795
#800
00
#805
#810
b00000000000000000000000000010111 (
10
#815
#820
00
#825
#830
b00000000000000000000000000011000 (
b0000000000000000000000011 -
10
#835
#840
00
#845
#850
b00000000000000000000000000011001 (
10
#855
#860
00
#865
#870
b00000000000000000000000000011010 (
10
#875
#880
00
#885
#890
b00000000000000000000000000011011 (
10
#895
#900
00
#905
#910
b00000000000000000000000000011100 (
10
#915
#920
00
#925
#930
b00000000000000000000000000011101 (
10
#935
#940
00
#945
#950
b00000000000000000000000000011110 (
10
#955
#960
00
#965
#970
b00000000000000000000000000011111 (
10
#975
#980
00
#985
#990
b00000000000000000000000000100000 (
b0000000000000000000000100 -
10
#995
#1000
00
#1005
#1010
b00000000000000000000000000100001 (
10
#1015
#1020
00
#1025
#1030
b00000000000000000000000000100010 (
10
#1035
#1040
00
#1045
#1050
b00000000000000000000000000100011 (
10
#1055
#1060
00
#1065
#1070
b00000000000000000000000000100100 (
10
#1075
#1080
00
#1085
#1090
b00000000000000000000000000100101 (
10
#1095
#1100
00
#1105
#1110
b00000000000000000000000000100110 (
10
#1115
#1120
00
#1125
#1130
b00000000000000000000000000100111 (
10
#1135
#1140
00
#1145
#1150
b00000000000000000000000000101000 (
b0000000000000000000000101 -
10
#1155
#1160
00
#1165
#1170
b00000000000000000000000000101001 (
10
#1175
#1180
00
#1185
#1190
b00000000000000000000000000101010 (
10
#1195
#1200
00
#1205
#1210
b00000000000000000000000000101011 (
10
#1215
#1220
00
#1225
#1230
b00000000000000000000000000101100 (
10
#1235
#1240
00
#1245
#1250
b00000000000000000000000000101101 (
10
#1255
#1260
00
#1265
#1270
b00000000000000000000000000101110 (
10
#1275
#1280
00
#1285
#1290
b00000000000000000000000000101111 (
10
#1295
#1300
00
#1305
#1310
b00000000000000000000000000110000 (
b0000000000000000000000110 -
10
#1315
#1320
00
#1325
#1330
b00000000000000000000000000110001 (
10
#1335
#1340
00
#1345
#1350
b00000000000000000000000000110010 (
10
#1355
#1360
00
#1365
#1370
b00000000000000000000000000110011 (
10
#1375
#1380
00
#1385
#1390
b00000000000000000000000000110100 (
10
#1395
#1400
00
#1405
#1410
b00000000000000000000000000110101 (
10
#1415
#1420
00
#1425
#1430
b00000000000000000000000000110110 (
10
#1435
#1440
00
#1445
#1450
b00000000000000000000000000110111 (
10
#1455
#1460
00
#1465
#1470
b00000000000000000000000000111000 (
b0000000000000000000000111 -
10
#1475
#1480
00
#1485
#1490
b00000000000000000000000000111001 (
10
#1495
#1500
00
#1505
#1510
b00000000000000000000000000111010 (
10
#1515
#1520
00
#1525
#1530
b00000000000000000000000000111011 (
10
#1535
#1540
00
#1545
#1550
b00000000000000000000000000111100 (
10
#1555
#1560
00
#1565
#1570
b00000000000000000000000000111101 (
10
#1575
#1580
00
#1585
#1590
b00000000000000000000000000111110 (
10
#1595
#1600
00
#1605
#1610
b00000000000000000000000000111111 (
10
#1615
#1620
00
#1625
#1630
b00000000000000000000000001000000 (
b0000000000000000000001000 -
10
#1635
#1640
00
#1645
#1650
b00000000000000000000000001000001 (
10
#1655
#1660
00
#1665
#1670
b00000000000000000000000001000010 (
10
#1675
#1680
00
#1685
#1690
b00000000000000000000000001000011 (
10
#1695
#1700
00
#1705
#1710
b00000000000000000000000001000100 (
10
#1715
#1720
00
#1725
#1730
b00000000000000000000000001000101 (
10
#1735
#1740
00
#1745
#1750
b00000000000000000000000001000110 (
10
#1755
#1760
00
#1765
#1770
b00000000000000000000000001000111 (
10
#1775
#1780
00
#1785
#1790
b00000000000000000000000001001000 (
b0000000000000000000001001 -
10
#1795
#1800
00
#1805
#1810
b00000000000000000000000001001001 (
10
#1815
#1820
00
#1825
#1830
b00000000000000000000000001001010 (
10
#1835
#1840
00
#1845
#1850
b00000000000000000000000001001011 (
10
#1855
#1860
00
#1865
#1870
b00000000000000000000000001001100 (
10
#1875
#1880
00
#1885
#1890
b00000000000000000000000001001101 (
10
#1895
#1900
00
#1905
#1910
b00000000000000000000000001001110 (
10
#1915
#1920
00
#1925
#1930
b00000000000000000000000001001111 (
10
#1935
#1940
00
#1945
#1950
b00000000000000000000000001010000 (
b0000000000000000000001010 -
10
#1955
#1960
00
#1965
#1970
b00000000000000000000000001010001 (
10
#1975
#1980
00
#1985
#1990
b00000000000000000000000001010010 (
10
#1995
#2000
00
#2005
#2010
b00000000000000000000000001010011 (
10
#2015
#2020
00
#2025
#2030
b00000000000000000000000001010100 (
10
#2035
#2040
00
#2045
#2050
b00000000000000000000000001010101 (
10
#2055
#2060
00
#2065
#2070
b00000000000000000000000001010110 (
10
#2075
#2080
00
#2085
#2090
b00000000000000000000000001010111 (
10
#2095
#2100
00
#2105
#2110
b00000000000000000000000001011000 (
b0000000000000000000001011 -
10
#2115
#2120
00
#2125
#2130
b00000000000000000000000001011001 (
10
#2135
#2140
00
#2145
#2150
b00000000000000000000000001011010 (
10
#2155
#2160
00
#2165
#2170
b00000000000000000000000001011011 (
10
#2175
#2180
00
#2185
#2190
b00000000000000000000000001011100 (
10
#2195
#2200
00
#2205
#2210
b00000000000000000000000001011101 (
10
#2215
#2220
00
#2225
#2230
b00000000000000000000000001011110 (
10
#2235
#2240
00
#2245
#2250
b00000000000000000000000001011111 (
10
#2255
#2260
00
#2265
#2270
b00000000000000000000000001100000 (
b0000000000000000000001100 -
10
#2275
#2280
00
#2285
#2290
b00000000000000000000000001100001 (
10
#2295
#2300
00
#2305
#2310
b00000000000000000000000001100010 (
10
#2315
#2320
00
#2325
#2330
b00000000000000000000000001100011 (
10
#2335
#2340
00
#2345
#2350
b00000000000000000000000001100100 (
10
#2355
#2360
00
#2365
#2370
b00000000000000000000000001100101 (
10
#2375
#2380
00
#2385
#2390
b00000000000000000000000001100110 (
10
#2395
#2400
00
#2405
#2410
b00000000000000000000000001100111 (
10
#2415
#2420
00
#2425
#2430
b00000000000000000000000001101000 (
b0000000000000000000001101 -
10
#2435
#2440
00
#2445
#2450
b00000000000000000000000001101001 (
10
#2455
#2460
00
#2465
#2470
b00000000000000000000000001101010 (
10
#2475
#2480
00
#2485
#2490
b00000000000000000000000001101011 (
10
#2495
#2500
00
#2505
#2510
b00000000000000000000000001101100 (
10
#2515
#2520
00
#2525
#2530
b00000000000000000000000001101101 (
10
#2535
#2540
00
#2545
#2550
b00000000000000000000000001101110 (
10
#2555
#2560
00
#2565
#2570
b00000000000000000000000001101111 (
10
#2575
#2580
00
#2585
#2590
b00000000000000000000000001110000 (
b0000000000000000000001110 -
10
#2595
#2600
00
#2605
#2610
b00000000000000000000000001110001 (
10
#2615
#2620
00
#2625
#2630
b00000000000000000000000001110010 (
10
#2635
#2640
00
#2645
#2650
b00000000000000000000000001110011 (
10
#2655
#2660
00
#2665
#2670
b00000000000000000000000001110100 (
10
#2675
#2680
00
#2685
#2690
b00000000000000000000000001110101 (
10
#2695
#2700
00
#2705
#2710
b00000000000000000000000001110110 (
10
#2715
#2720
00
#2725
#2730
b00000000000000000000000001110111 (
10
#2735
#2740
00
#2745
#2750
b00000000000000000000000001111000 (
b0000000000000000000001111 -
10
#2755
#2760
00
#2765
#2770
b00000000000000000000000001111001 (
10
#2775
#2780
00
#2785
#2790
b00000000000000000000000001111010 (
10
#2795
#2800
00
#2805
#2810
b00000000000000000000000001111011 (
10
#2815
#2820
00
#2825
#2830
b00000000000000000000000001111100 (
10
#2835
#2840
00
#2845
#2850
b00000000000000000000000001111101 (
10
#2855
#2860
00
#2865
#2870
b00000000000000000000000001111110 (
10
#2875
#2880
00
#2885
#2890
b00000000000000000000000001111111 (
10
#2895
#2900
00
#2905
#2910
b00000000000000000000000010000000 (
b0000000000000000000010000 -
10
#2915
#2920
00
#2925
#2930
b00000000000000000000000010000001 (
10
#2935
#2940
00
#2945
#2950
b00000000000000000000000010000010 (
10
#2955
#2960
00
#2965
#2970
b00000000000000000000000010000011 (
10
#2975
#2980
00
#2985
#2990
b00000000000000000000000010000100 (
10
#2995
#3000
00
#3005
#3010
b00000000000000000000000010000101 (
10
#3015
#3020
00
#3025
#3030
b00000000000000000000000010000110 (
10
#3035
#3040
00
#3045
#3050
b00000000000000000000000010000111 (
10
#3055
#3060
00
#3065
#3070
b00000000000000000000000010001000 (
b0000000000000000000010001 -
10
#3075
#3080
00
#3085
#3090
b00000000000000000000000010001001 (
10
#3095
#3100
00
#3105
#3110
b00000000000000000000000010001010 (
10
#3115
#3120
00
#3125
#3130
b00000000000000000000000010001011 (
10
#3135
#3140
00
#3145
#3150
b00000000000000000000000010001100 (
10
#3155
#3160
00
#3165
#3170
b00000000000000000000000010001101 (
10
#3175
#3180
00
#3185
#3190
b00000000000000000000000010001110 (
10
#3195
#3200
00
#3205
#3210
b00000000000000000000000010001111 (
10
#3215
#3220
00
#3225
#3230
b00000000000000000000000010010000 (
b0000000000000000000010010 -
10
#3235
#3240
00
#3245
#3250
b00000000000000000000000010010001 (
10
#3255
#3260
00
#3265
#3270
b00000000000000000000000010010010 (
10
#3275
#3280
00
#3285
#3290
b00000000000000000000000010010011 (
10
#3295
#3300
00
#3305
#3310
b00000000000000000000000010010100 (
10
#3315
#3320
00
#3325
#3330
b00000000000000000000000010010101 (
10
#3335
#3340
00
#3345
#3350
b00000000000000000000000010010110 (
10
#3355
#3360
00
#3365
#3370
b00000000000000000000000010010111 (
10
#3375
#3380
00
#3385
#3390
b00000000000000000000000010011000 (
b0000000000000000000010011 -
10
#3395
#3400
00
#3405
#3410
b00000000000000000000000010011001 (
10
#3415
#3420
00
#3425
#3430
b00000000000000000000000010011010 (
10
#3435
#3440
00
#3445
#3450
b00000000000000000000000010011011 (
10
#3455
#3460
00
#3465
#3470
b00000000000000000000000010011100 (
10
#3475
#3480
00
#3485
#3490
b00000000000000000000000010011101 (
10
#3495
#3500
00
#3505
#3510
b00000000000000000000000010011110 (
10
#3515
#3520
00
#3525
#3530
b00000000000000000000000010011111 (
10
#3535
#3540
00
#3545
#3550
b00000000000000000000000010100000 (
b0000000000000000000010100 -
10
#3555
#3560
00
#3565
#3570
b00000000000000000000000010100001 (
10
#3575
#3580
00
#3585
#3590
b00000000000000000000000010100010 (
10
#3595
#3600
00
#3605
#3610
b00000000000000000000000010100011 (
10
#3615
#3620
00
#3625
#3630
b00000000000000000000000010100100 (
10
#3635
#3640
00
#3645
#3650
b00000000000000000000000010100101 (
10
#3655
#3660
00
#3665
#3670
b00000000000000000000000010100110 (
10
#3675
#3680
00
#3685
#3690
b00000000000000000000000010100111 (
10
#3695
#3700
00
#3705
#3710
b00000000000000000000000010101000 (
b0000000000000000000010101 -
10
#3715
#3720
00
#3725
#3730
b00000000000000000000000010101001 (
10
#3735
#3740
00
#3745
#3750
b00000000000000000000000010101010 (
10
#3755
#3760
00
#3765
#3770
b00000000000000000000000010101011 (
10
#3775
#3780
00
#3785
#3790
b00000000000000000000000010101100 (
10
#3795
#3800
00
#3805
#3810
b00000000000000000000000010101101 (
10
#3815
#3820
00
#3825
#3830
b00000000000000000000000010101110 (
10
#3835
#3840
00
#3845
#3850
b00000000000000000000000010101111 (
10
#3855
#3860
00
#3865
#3870
b00000000000000000000000010110000 (
b0000000000000000000010110 -
10
#3875
#3880
00
#3885
#3890
b00000000000000000000000010110001 (
10
#3895
#3900
00
#3905
#3910
b00000000000000000000000010110010 (
10
#3915
#3920
00
#3925
#3930
b00000000000000000000000010110011 (
10
#3935
#3940
00
#3945
#3950
b00000000000000000000000010110100 (
10
#3955
#3960
00
#3965
#3970
b00000000000000000000000010110101 (
10
#3975
#3980
00
#3985
#3990
b00000000000000000000000010110110 (
10
#3995
#4000
00
#4005
#4010
b00000000000000000000000010110111 (
10
#4015
#4020
00
#4025
#4030
b00000000000000000000000010111000 (
b0000000000000000000010111 -
10
#4035
#4040
00
#4045
#4050
b00000000000000000000000010111001 (
10
#4055
#4060
00
#4065
#4070
b00000000000000000000000010111010 (
10
#4075
#4080
00
#4085
#4090
b00000000000000000000000010111011 (
10
#4095
#4100
00
#4105
#4110
b00000000000000000000000010111100 (
10
#4115
#4120
00
#4125
#4130
b00000000000000000000000010111101 (
10
#4135
#4140
00
#4145
#4150
b00000000000000000000000010111110 (
10
#4155
#4160
00
#4165
#4170
b00000000000000000000000010111111 (
10
#4175
#4180
00
#4185
#4190
b00000000000000000000000011000000 (
b0000000000000000000011000 -
10
#4195
#4200
00
#4205
#4210
b00000000000000000000000011000001 (
10
#4215
#4220
00
#4225
#4230
b00000000000000000000000011000010 (
10
#4235
#4240
00
#4245
#4250
b00000000000000000000000011000011 (
10
#4255
#4260
00
#4265
#4270
b00000000000000000000000011000100 (
10
#4275
#4280
00
#4285
#4290
b00000000000000000000000011000101 (
10
#4295
#4300
00
#4305
#4310
b00000000000000000000000011000110 (
10
#4315
#4320
00
#4325
#4330
b00000000000000000000000011000111 (
10
#4335
#4340
00
#4345
#4350
b00000000000000000000000011001000 (
b0000000000000000000011001 -
10
#4355
#4360
00
#4365
#4370
b00000000000000000000000011001001 (
10
#4375
#4380
00
#4385
#4390
b00000000000000000000000011001010 (
10
#4395
#4400
00
#4405
#4410
b00000000000000000000000011001011 (
10
#4415
#4420
00
#4425
#4430
b00000000000000000000000011001100 (
10
#4435
#4440
00
#4445
#4450
b00000000000000000000000011001101 (
10
#4455
#4460
00
#4465
#4470
b00000000000000000000000011001110 (
10
#4475
#4480
00
#4485
#4490
b00000000000000000000000011001111 (
10
#4495
#4500
00
#4505
#4510
b00000000000000000000000011010000 (
b0000000000000000000011010 -
10
#4515
#4520
00
#4525
#4530
b00000000000000000000000011010001 (
10
#4535
#4540
00
#4545
#4550
b00000000000000000000000011010010 (
10
#4555
#4560
00
#4565
#4570
b00000000000000000000000011010011 (
10
#4575
#4580
00
#4585
#4590
b00000000000000000000000011010100 (
10
#4595
#4600
00
#4605
#4610
b00000000000000000000000011010101 (
10
#4615
#4620
00
#4625
#4630
b00000000000000000000000011010110 (
10
#4635
#4640
00
#4645
#4650
b00000000000000000000000011010111 (
10
#4655
#4660
00
#4665
#4670
b00000000000000000000000011011000 (
b0000000000000000000011011 -
10
#4675
#4680
00
#4685
#4690
b00000000000000000000000011011001 (
10
#4695
#4700
00
#4705
#4710
b00000000000000000000000011011010 (
10
#4715
#4720
00
#4725
#4730
b00000000000000000000000011011011 (
10
#4735
#4740
00
#4745
#4750
b00000000000000000000000011011100 (
10
#4755
#4760
00
#4765
#4770
b00000000000000000000000011011101 (
10
#4775
#4780
00
#4785
#4790
b00000000000000000000000011011110 (
10
#4795
#4800
00
#4805
#4810
b00000000000000000000000011011111 (
10
#4815
#4820
00
#4825
#4830
b00000000000000000000000011100000 (
b0000000000000000000011100 -
10
#4835
#4840
00
#4845
#4850
b00000000000000000000000011100001 (
10
#4855
#4860
00
#4865
#4870
b00000000000000000000000011100010 (
10
#4875
#4880
00
#4885
#4890
b00000000000000000000000011100011 (
10
#4895
#4900
00
#4905
#4910
b00000000000000000000000011100100 (
10
#4915
#4920
00
#4925
#4930
b00000000000000000000000011100101 (
10
#4935
#4940
00
#4945
#4950
b00000000000000000000000011100110 (
10
#4955
#4960
00
#4965
#4970
b00000000000000000000000011100111 (
10
#4975
#4980
00
#4985
#4990
b00000000000000000000000011101000 (
b0000000000000000000011101 -
10
#4995
#5000
00
#5005
#5010
b00000000000000000000000011101001 (
10
#5015
#5020
00
#5025
#5030
b00000000000000000000000011101010 (
10
#5035
#5040
00
#5045
#5050
b00000000000000000000000011101011 (
10
#5055
#5060
00
#5065
#5070
b00000000000000000000000011101100 (
10
#5075
#5080
00
#5085
#5090
b00000000000000000000000011101101 (
10
#5095
#5100
00
#5105
#5110
b00000000000000000000000011101110 (
10
#5115
#5120
00
#5125
#5130
b00000000000000000000000011101111 (
10
#5135
#5140
00
#5145
#5150
b00000000000000000000000011110000 (
b0000000000000000000011110 -
10
#5155
#5160
00
#5165
#5170
b00000000000000000000000011110001 (
10
#5175
#5180
00
#5185
#5190
b00000000000000000000000011110010 (
10
#5195
#5200
00
#5205
#5210
b00000000000000000000000011110011 (
10
#5215
#5220
00
#5225
#5230
b00000000000000000000000011110100 (
10
#5235
#5240
00
#5245
#5250
b00000000000000000000000011110101 (
10
#5255
#5260
00
#5265
#5270
b00000000000000000000000011110110 (
10
#5275
#5280
00
#5285
#5290
b00000000000000000000000011110111 (
10
#5295
#5300
00
#5305
#5310
b00000000000000000000000011111000 (
b0000000000000000000011111 -
10
#5315
#5320
00
#5325
#5330
b00000000000000000000000011111001 (
10
#5335
#5340
00
#5345
#5350
b00000000000000000000000011111010 (
10
#5355
#5360
00
#5365
#5370
b00000000000000000000000011111011 (
10
#5375
#5380
00
#5385
#5390
b00000000000000000000000011111100 (
10
#5395
#5400
00
#5405
#5410
b00000000000000000000000011111101 (
10
#5415
#5420
00
#5425
#5430
b00000000000000000000000011111110 (
10
#5435
#5440
00
#5445
#5450
b00000000000000000000000011111111 (
10
#5455
#5460
00
#5465
#5470
b00000000000000000000000100000000 (
b0000000000000000000100000 -
10
#5475
#5480
00
#5485
#5490
b00000000000000000000000100000001 (
10
#5495
#5500
00
#5505
#5510
b00000000000000000000000100000010 (
10
#5515
#5520
00
#5525
#5530
b00000000000000000000000100000011 (
10
#5535
#5540
00
#5545
#5550
b00000000000000000000000100000100 (
10
#5555
#5560
00
#5565
#5570
b00000000000000000000000100000101 (
10
#5575
#5580
00
#5585
#5590
b00000000000000000000000100000110 (
10
#5595
#5600
00
#5605
#5610
b00000000000000000000000100000111 (
10
#5615
#5620
00
#5625
#5630
b00000000000000000000000100001000 (
b0000000000000000000100001 -
10
#5635
#5640
00
#5645
#5650
b00000000000000000000000100001001 (
10
#5655
