Componets/MIPI-CSI-Transciever/MIPI_Reciever/MIPI_Reciever.v
module MIPI_Reciever(input byte_clk,byte_clk_8,pixclk,reset,lane0,lane1,output[7:0] red,output[7:0] green,output[7:0] blue,output[24:0] address_out,output reg [1:0] led);
reg[7:0] bytereg0=0;
reg[7:0] bytereg1=0;
reg[7:0] counter=0;
wire byte_clk8=byte_clk_8;
integer mipi_cnt=0;
reg[7:0] data_id=0;
reg[15:0] word_cnt;
reg FS,FE,PIX;
reg[7:0] state_byte=idle_bitclk;
reg[7:0] state_mipi=idle_mipi;
reg ena_byte8=0;
reg[24:0] addres=0;
reg[31:0] regheader;
wire[7:0] ecc;

reg[15:0] wordcount;


    assign ecc[0]=regheader[0]^regheader[1]^regheader[2]^regheader[4]^regheader[5]^regheader[7]^regheader[10]^regheader[11]^regheader[13]^regheader[16]^
		regheader[20]^regheader[21]^regheader[22]^regheader[23];
	assign ecc[1]=regheader[0]^regheader[1]^regheader[3]^regheader[4]^regheader[6]^regheader[8]^regheader[10]^regheader[12]^regheader[14]^regheader[17]^
		regheader[20]^regheader[21]^regheader[22]^regheader[23];
	assign ecc[2]=regheader[0]^regheader[2]^regheader[3]^regheader[5]^regheader[6]^regheader[9]^regheader[11]^regheader[12]^regheader[15]^regheader[18]^
		regheader[20]^regheader[21]^regheader[22];
	assign ecc[3]=regheader[1]^regheader[2]^regheader[3]^regheader[7]^regheader[8]^regheader[9]^regheader[13]^regheader[14]^regheader[15]^regheader[19]^
		regheader[20]^regheader[21]^regheader[23];
	assign ecc[4]=regheader[4]^regheader[5]^regheader[6]^regheader[7]^regheader[8]^regheader[9]^regheader[16]^regheader[17]^regheader[18]^regheader[19]^
		regheader[20]^regheader[22]^regheader[23];
	assign ecc[5]=regheader[10]^regheader[11]^regheader[12]^regheader[13]^regheader[14]^regheader[15]^regheader[16]^regheader[17]^regheader[18]^regheader[19]^
		regheader[21]^regheader[22]^regheader[23];	
	assign ecc[6]=0;
	assign ecc[7]=0;



////////////////////States for byteclk datasample
localparam reg[7:0] idle_bitclk=0;
localparam reg[7:0] bitclk=1;
///////////////////States for long and short Packet Recieve
localparam reg[7:0] idle_mipi=2;
localparam reg[7:0] PH_mipi=3;
localparam reg[7:0] data_mipi=4;
localparam reg[7:0] PF_mipi=5;
//////////////////Const for Data_id
localparam reg[5:0] FS_const=6'h00;//Framestart
localparam reg[5:0] FE_const=6'h01;//Frameend
localparam reg[5:0] ED_const=6'h12;//Embedded data
localparam reg[5:0] RAW8_const=6'h2A;//Embedded data
localparam reg[5:0] RAW10_const=6'h2B;//Embedded data
///////////////////////FSM byte/bitclk
always@(posedge byte_clk8)begin
	if(reset==1) begin
	end else begin
		case (state_byte)
			idle_bitclk: begin
				if(byte_clk==1)begin
					state_byte<=bitclk;
					counter<=0;
					bytereg0[0]=lane0;
					bytereg1[0]=lane1;
				end
			end
			bitclk: begin
				counter<=counter+1;
				bytereg0[counter+1]=lane0;
				bytereg1[counter+1]=lane1;
				state_byte<=counter>=6?idle_bitclk:bitclk;
				regheader<=(counter>=6)?{bytereg0,regheader[31:8]}:regheader;//(2'bx,dataid,word_count,ecc_code)	
			end
			default: begin
			end
		endcase
	end
end
//////////////////////////
always @(posedge byte_clk) begin
	if(reset==1)begin
		state_mipi<=idle_mipi;
	end else begin
		case (state_mipi)
			idle_mipi: begin							
				FS<=0;
				FE<=0;
				PIX<=0;
				led<=0;
				if(regheader[5:0]==FS_const[5:0]&&regheader[31:24]==ecc)begin
					led[0]<=1;
				end
				if(regheader[5:0]==FE_const[5:0]&&regheader[31:24]==ecc)begin
					led[1]<=1;
				end
				if(regheader[5:0]==RAW10_const[5:0]&&regheader[31:24]==ecc)begin
					led[1]<=1;
				end
				
				
				/*if(regheader[5:0]==FS_const[5:0]&&regheader[31:24]==ecc)begin
					FS<=1;//Frame start
					led[0]<=1;
				end else if(regheader[5:0]==FE_const[5:0]&&regheader[31:24]==ecc)begin
					FE<=1;//Frame end 
					led<=3;
				end else if(regheader[5:0]==RAW10_const[5:0]&&regheader[31:24]==ecc)begin
					PIX<=1;
					led[1]<=1;
					state_mipi<=data_mipi;
					mipi_cnt=0;
					wordcount<={regheader[15:8],regheader[23:16]};
				end	*/			
			end			
			data_mipi: begin
				if(mipi_cnt<=wordcount-1) begin
					mipi_cnt=mipi_cnt+1;
				end else begin
					state_mipi<=PF_mipi;
					mipi_cnt=0;
				end
			end
			PF_mipi: begin
				state_mipi<=idle_mipi;
			end
			default: begin
			end
		endcase
	end	
end


endmodule

Componets/MIPI-CSI-Transciever/MIPI_Reciever/blinky.vcd
$version Generated by VerilatedVcd $end
$date Sun Dec 11 00:41:01 2022
 $end
$timescale   1ps $end

 $scope module TOP $end
  $var wire 25 6 address_out [24:0] $end
  $var wire  8 5 blue [7:0] $end
  $var wire  1 - byte_clk $end
  $var wire  1 . byte_clk_8 $end
  $var wire  8 4 green [7:0] $end
  $var wire  1 1 lane0 $end
  $var wire  1 2 lane1 $end
  $var wire  2 7 led [1:0] $end
  $var wire  1 / pixclk $end
  $var wire  8 3 red [7:0] $end
  $var wire  1 0 reset $end
  $scope module MIPI_Reciever $end
   $var wire  6 E ED_const [5:0] $end
   $var wire  1 ) FE $end
   $var wire  6 D FE_const [5:0] $end
   $var wire  1 ( FS $end
   $var wire  6 C FS_const [5:0] $end
   $var wire  8 B PF_mipi [7:0] $end
   $var wire  8 @ PH_mipi [7:0] $end
   $var wire  1 * PIX $end
   $var wire  6 G RAW10_const [5:0] $end
   $var wire  6 F RAW8_const [5:0] $end
   $var wire 25 = addres [24:0] $end
   $var wire 25 6 address_out [24:0] $end
   $var wire  8 > bitclk [7:0] $end
   $var wire  8 5 blue [7:0] $end
   $var wire  1 - byte_clk $end
   $var wire  1 . byte_clk8 $end
   $var wire  1 . byte_clk_8 $end
   $var wire  8 # bytereg0 [7:0] $end
   $var wire  8 $ bytereg1 [7:0] $end
   $var wire  8 % counter [7:0] $end
   $var wire  8 : data_id [7:0] $end
   $var wire  8 A data_mipi [7:0] $end
   $var wire  8 9 ecc [7:0] $end
   $var wire  1 < ena_byte8 $end
   $var wire  8 4 green [7:0] $end
   $var wire  8 : idle_bitclk [7:0] $end
   $var wire  8 ? idle_mipi [7:0] $end
   $var wire  1 1 lane0 $end
   $var wire  1 2 lane1 $end
   $var wire  2 7 led [1:0] $end
   $var wire 32 ' mipi_cnt [31:0] $end
   $var wire  1 / pixclk $end
   $var wire  8 3 red [7:0] $end
   $var wire 32 8 regheader [31:0] $end
   $var wire  1 0 reset $end
   $var wire  8 & state_byte [7:0] $end
   $var wire  8 + state_mipi [7:0] $end
   $var wire 16 ; word_cnt [15:0] $end
   $var wire 16 , wordcount [15:0] $end
  $upscope $end
 $upscope $end
$enddefinitions $end


#10
b00000001 #
b00000000 $
b00000000 %
b00000001 &
b00000000000000000000000000000000 '
1(
0)
0*
b00000010 +
b0000000000000000 ,
1-
1.
0/
00
11
02
b00000000 3
b00000000 4
b00000000 5
b0000000000000000000000000 6
b01 7
b00000000000000000000000000000000 8
b00000000 9
b00000000 :
b0000000000000000 ;
0<
b0000000000000000000000000 =
b00000001 >
b00000010 ?
b00000011 @
b00000100 A
b00000101 B
b000000 C
b000001 D
b010010 E
b101010 F
b101011 G
#15
0.
#20
b00000011 #
b00000001 %
1.
#25
0.
#30
b00000010 %
1.
01
#35
0.
#40
b00001011 #
b00000011 %
1.
11
#45
0.
#50
b00000100 %
0-
1.
01
#55
0.
#60
b00101011 #
b00000101 %
1.
11
#65
0.
#70
b00000110 %
1.
01
#75
0.
#80
b00000111 %
b00000000 &
1.
b00101011000000000000000000000000 8
#85
0.
#90
b00101010 #
b00000000 %
b00000001 &
0(
1-
1.
b00 7
#95
0.
#100
b00101000 #
b00000001 %
1.
#105
0.
#110
b00000010 %
1.
#115
0.
#120
b00100000 #
b00000011 %
1.
#125
0.
#130
b00000100 %
0-
1.
#135
0.
#140
b00000000 #
b00000101 %
1.
#145
0.
#150
b00000110 %
1.
#155
0.
#160
b00000111 %
b00000000 &
1.
b00000000001010110000000000000000 8
b00010100 9
#165
0.
#170
b00000001 #
b00000000 %
b00000001 &
1-
1.
11
#175
0.
#180
b00000011 #
b00000001 %
1.
#185
0.
#190
b00000010 %
1.
01
#195
0.
#200
b00000011 %
1.
#205
0.
#210
b00000100 %
0-
1.
#215
0.
#220
b00000101 %
1.
#225
0.
#230
b00000110 %
1.
#235
0.
#240
b00000111 %
b00000000 &
1.
b00000011000000000010101100000000 8
b00001010 9
#245
0.
#250
b00000010 #
b00000000 %
b00000001 &
1-
1.
#255
0.
#260
b00000000 #
b00000001 %
1.
#265
0.
#270
b00000100 #
b00000010 %
1.
11
#275
0.
#280
b00000011 %
1.
01
#285
0.
#290
b00010100 #
b00000100 %
0-
1.
11
#295
0.
#300
b00000101 %
1.
01
#305
0.
#310
b00000110 %
1.
#315
0.
#320
b00000111 %
b00000000 &
1.
b00010100000000110000000000101011 8
b00010100 9
#325
0.
#330
b00000000 %
b00000001 &
1*
b00000100 +
b0000000000000011 ,
1-
1.
b10 7
#335
0.
#340
b00000001 %
1.
#345
0.
#350
b00010000 #
b00000010 %
1.
#355
0.
#360
b00000011 %
1.
#365
0.
#370
b00000000 #
b00000100 %
0-
1.
#375
0.
#380
b00000101 %
1.
#385
0.
#390
b00000110 %
1.
#395
0.
#400
b00000111 %
b00000000 &
1.
b00000000000101000000001100000000 8
b00101101 9
#405
0.
#410
b00000000 %
b00000001 &
b00000000000000000000000000000001 '
1-
1.
#415
0.
#420
b00000001 %
1.
#425
0.
#430
b00000010 %
1.
#435
0.
#440
b00000011 %
1.
#445
0.
#450
b00000100 %
0-
1.
#455
0.
#460
b00000101 %
1.
#465
0.
#470
b00000110 %
1.
#475
0.
#480
b00000111 %
b00000000 &
1.
b00000000000000000001010000000011 8
b00001001 9
#485
0.
#490
b00000000 %
b00000001 &
b00000000000000000000000000000010 '
1-
1.
#495
0.
#500
b00000001 %
1.
#505
0.
#510
b00000010 %
1.
#515
0.
#520
b00000011 %
1.
#525
0.
#530
b00000100 %
0-
1.
#535
0.
#540
b00000101 %
1.
#545
0.
#550
b00000110 %
1.
#555
0.
#560
b00000111 %
b00000000 &
1.
b00000000000000000000000000010100 8
b00011110 9
#565
0.
#570
b00000000 %
b00000001 &
b00000000000000000000000000000011 '
1-
1.
#575
0.
#580
b00000001 %
1.
#585
0.
#590
b00000010 %
1.
#595
0.
#600
b00000011 %
1.
#605
0.
#610
b00000100 %
0-
1.
#615
0.
#620
b00000101 %
1.
#625
0.
#630
b00000110 %
1.
#635
0.
#640
b00000111 %
b00000000 &
1.
b00000000000000000000000000000000 8
b00000000 9
#645
0.
#650
b00000000 %
b00000001 &
b00000000000000000000000000000000 '
b00000101 +
1-
1.
#655
0.
#660
b00000001 %
1.
#665
0.
#670
b00000010 %
1.
#675
0.
#680
b00000011 %
1.
#685
0.
#690
b00000100 %
0-
1.
#695
0.
#700
b00000101 %
1.
#705
0.
#710
b00000110 %
1.
#715
0.
#720
b00000111 %
b00000000 &
1.
#725
0.
#730
b00000000 %
b00000001 &
b00000010 +
1-
1.
#735
0.
#740
b00000001 %
1.
#745
0.
#750
b00000010 %
1.
#755
0.
#760
b00000011 %
1.
#765
0.
#770
b00000100 %
0-
1.
#775
0.
#780
b00000101 %
1.
#785
0.
#790
b00000110 %
1.
#795
0.
#800
b00000111 %
b00000000 &
1.
#805
0.
#810
b00000000 %
b00000001 &
1(
0*
1-
1.
b01 7
#815
0.
#820
b00000001 %
1.
#825
0.
#830
b00000010 %
1.
#835
0.
#840
b00000011 %
1.
#845
0.
#850
b00000100 %
0-
1.
#855
0.
#860
b00000101 %
1.
#865
0.
#870
b00000110 %
1.
#875
0.
#880
b00000111 %
b00000000 &
1.
#885
0.
#890
b00000000 %
b00000001 &
1-
1.
#895
0.
#900
b00000001 %
1.
#905
0.
#910
b00000010 %
1.
#915
0.
#920
b00000011 %
1.
#925
0.
#930
b00000100 %
0-
1.
#935
0.
#940
b00000101 %
1.
#945
0.
#950
b00000110 %
1.
#955
0.
#960
b00000111 %
b00000000 &
1.
#965
0.
#970
b00000000 %
b00000001 &
1-
1.
#975
0.
#980
b00000001 %
1.
#985
0.
#990
b00000010 %
1.
#995
0.
#1000
b00000011 %
1.
#1005
0.
#1010
b00000100 %
0-
1.
#1015
0.
#1020
b00000101 %
1.
#1025
0.
#1030
b00000110 %
1.
#1035
0.
#1040
b00000111 %
b00000000 &
1.
#1045
0.
#1050
b00000000 %
b00000001 &
1-
1.
#1055
0.
#1060
b00000001 %
1.
#1065
0.
#1070
b00000010 %
1.
#1075
0.
#1080
b00000011 %
1.
#1085
0.
#1090
b00000100 %
0-
1.
#1095
0.
#1100
b00000101 %
1.
#1105
0.
#1110
b00000110 %
1.
#1115
0.
#1120
b00000111 %
b00000000 &
1.
#1125
0.
#1130
b00000000 %
b00000001 &
1-
1.
#1135
0.
#1140
b00000001 %
1.
#1145
0.
#1150
b00000010 %
1.
#1155
0.
#1160
b00000011 %
1.
#1165
0.
#1170
b00000100 %
0-
1.
#1175
0.
#1180
b00000101 %
1.
#1185
0.
#1190
b00000110 %
1.
#1195
0.
#1200
b00000111 %
b00000000 &
1.
#1205
0.
#1210
b00000000 %
b00000001 &
1-
1.
#1215
0.
#1220
b00000001 %
1.
#1225
0.
#1230
b00000010 %
1.
#1235
0.
#1240
b00000011 %
1.
#1245
0.
#1250
b00000100 %
0-
1.
#1255
0.
#1260
b00000101 %
1.
#1265
0.
#1270
b00000110 %
1.
#1275
0.
#1280
b00000111 %
b00000000 &
1.
#1285
0.
#1290
b00000000 %
b00000001 &
1-
1.
#1295
0.
#1300
b00000001 %
1.
#1305
0.
#1310
b00000010 %
1.
#1315
0.
#1320
b00000011 %
1.
#1325
0.
#1330
b00000100 %
0-
1.
#1335
0.
#1340
b00000101 %
1.
#1345
0.
#1350
b00000110 %
1.
#1355
0.
#1360
b00000111 %
b00000000 &
1.
#1365
0.
#1370
b00000000 %
b00000001 &
1-
1.
#1375
0.
#1380
b00000001 %
1.
#1385
0.
#1390
b00000010 %
1.
#1395
0.
#1400
b00000011 %
1.
#1405
0.
#1410
b00000100 %
0-
1.
#1415
0.
#1420
b00000101 %
1.
#1425
0.
#1430
b00000110 %
1.
#1435
0.
#1440
b00000111 %
b00000000 &
1.
#1445
0.
#1450
b00000000 %
b00000001 &
1-
1.
#1455
0.
#1460
b00000001 %
1.
#1465
0.
#1470
b00000010 %
1.
#1475
0.
#1480
b00000011 %
1.
#1485
0.
#1490
b00000100 %
0-
1.
#1495
0.
#1500
b00000101 %
1.
#1505
0.
#1510
b00000110 %
1.
#1515
0.
#1520
b00000111 %
b00000000 &
1.
#1525
0.
#1530
b00000000 %
b00000001 &
1-
1.
#1535
0.
#1540
b00000001 %
1.
#1545
0.
#1550
b00000010 %
1.
#1555
0.
#1560
b00000011 %
1.
#1565
0.
#1570
b00000100 %
0-
1.
#1575
0.
#1580
b00000101 %
1.
#1585
0.
#1590
b00000110 %
1.
#1595
0.
#1600
b00000111 %
b00000000 &
1.
#1605
0.
#1610
b00000000 %
b00000001 &
1-
1.
#1615
0.
#1620
b00000001 %
1.
#1625
0.
#1630
b00000010 %
1.
#1635
0.
#1640
b00000011 %
1.
#1645
0.
#1650
b00000100 %
0-
1.
#1655
0.
#1660
b00000101 %
1.
#1665
0.
#1670
b00000110 %
1.
#1675
0.
#1680
b00000111 %
b00000000 &
1.
#1685
0.
#1690
b00000000 %
b00000001 &
1-
1.
#1695
0.
#1700
b00000001 %
1.
#1705
0.
#1710
b00000010 %
1.
#1715
0.
#1720
b00000011 %
1.
#1725
0.
#1730
b00000100 %
0-
1.
#1735
0.
#1740
b00000101 %
1.
#1745
0.
#1750
b00000110 %
1.
#1755
0.
#1760
b00000111 %
b00000000 &
1.
#1765
0.
#1770
b00000000 %
b00000001 &
1-
1.
#1775
0.
#1780
b00000001 %
1.
#1785
0.
#1790
b00000010 %
1.
#1795
0.
#1800
b00000011 %
1.
#1805
0.
#1810
b00000100 %
0-
1.
#1815
0.
#1820
b00000101 %
1.
#1825
0.
#1830
b00000110 %
1.
#1835
0.
#1840
b00000111 %
b00000000 &
1.
#1845
0.
#1850
b00000000 %
b00000001 &
1-
1.
#1855
0.
#1860
b00000001 %
1.
#1865
0.
#1870
b00000010 %
1.
#1875
0.
#1880
b00000011 %
1.
#1885
0.
#1890
b00000100 %
0-
1.
#1895
0.
#1900
b00000101 %
1.
#1905
0.
#1910
b00000110 %
1.
#1915
0.
#1920
b00000111 %
b00000000 &
1.
#1925
0.
#1930
b00000000 %
b00000001 &
1-
1.
#1935
0.
#1940
b00000001 %
1.
#1945
0.
#1950
b00000010 %
1.
#1955
0.
#1960
b00000011 %
1.
#1965
0.
#1970
b00000100 %
0-
1.
#1975
0.
#1980
b00000101 %
1.
#1985
0.
#1990
b00000110 %
1.
#1995
0.
#2000
b00000111 %
b00000000 &
1.
#2005
0.
#2010
b00000000 %
b00000001 &
1-
1.
#2015
0.
#2020
b00000001 %
1.
#2025
0.
#2030
b00000010 %
1.
#2035
0.
#2040
b00000011 %
1.
#2045
0.
#2050
b00000100 %
0-
1.
#2055
0.
#2060
b00000101 %
1.
#2065
0.
#2070
b00000110 %
1.
#2075
0.
#2080
b00000111 %
b00000000 &
1.
#2085
0.
#2090
b00000000 %
b00000001 &
1-
1.
#2095
0.
#2100
b00000001 %
1.
#2105
0.
#2110
b00000010 %
1.
#2115
0.
#2120
b00000011 %
1.
#2125
0.
#2130
b00000100 %
0-
1.
#2135
0.
#2140
b00000101 %
1.
#2145
0.
#2150
b00000110 %
1.
#2155
0.
#2160
b00000111 %
b00000000 &
1.
#2165
0.
#2170
b00000000 %
b00000001 &
1-
1.
#2175
0.
#2180
b00000001 %
1.
#2185
0.
#2190
b00000010 %
1.
#2195
0.
#2200
b00000011 %
1.
#2205
0.
#2210
b00000100 %
0-
1.
#2215
0.
#2220
b00000101 %
1.
#2225
0.
#2230
b00000110 %
1.
#2235
0.
#2240
b00000111 %
b00000000 &
1.
#2245
0.
#2250
b00000000 %
b00000001 &
1-
1.
#2255
0.
#2260
b00000001 %
1.
#2265
0.
#2270
b00000010 %
1.
#2275
0.
#2280
b00000011 %
1.
#2285
0.
#2290
b00000100 %
0-
1.
#2295
0.
#2300
b00000101 %
1.
#2305
0.
#2310
b00000110 %
1.
#2315
0.
#2320
b00000111 %
b00000000 &
1.
#2325
0.
#2330
b00000000 %
b00000001 &
1-
1.
#2335
0.
#2340
b00000001 %
1.
#2345
0.
#2350
b00000010 %
1.
#2355
0.
#2360
b00000011 %
1.
#2365
0.
#2370
b00000100 %
0-
1.
#2375
0.
#2380
b00000101 %
1.
#2385
0.
#2390
b00000110 %
1.
#2395
0.
#2400
b00000111 %
b00000000 &
1.
#2405
0.
#2410
b00000000 %
b00000001 &
1-
1.
#2415
0.
#2420
b00000001 %
1.
#2425
0.
#2430
b00000010 %
1.
#2435
0.
#2440
b00000011 %
1.
#2445
0.
#2450
b00000100 %
0-
1.
#2455
0.
#2460
b00000101 %
1.
#2465
0.
#2470
b00000110 %
1.
#2475
0.
#2480
b00000111 %
b00000000 &
1.
#2485
0.
#2490
b00000000 %
b00000001 &
1-
1.
#2495
0.
#2500
b00000001 %
1.
#2505
0.
#2510
b00000010 %
1.
#2515
0.
#2520
b00000011 %
1.
#2525
0.
#2530
b00000100 %
0-
1.
#2535
0.
#2540
b00000101 %
1.
#2545
0.
#2550
b00000110 %
1.
#2555
0.
#2560
b00000111 %
b00000000 &
1.
#2565
0.
#2570
b00000000 %
b00000001 &
1-
1.
#2575
0.
#2580
b00000001 %
1.
#2585
0.
#2590
b00000010 %
1.
#2595
0.
#2600
b00000011 %
1.
#2605
0.
#2610
b00000100 %
0-
1.
#2615
0.
#2620
b00000101 %
1.
#2625
0.
#2630
b00000110 %
1.
#2635
0.
#2640
b00000111 %
b00000000 &
1.
#2645
0.
#2650
b00000000 %
b00000001 &
1-
1.
#2655
0.
#2660
b00000001 %
1.
#2665
0.
#2670
b00000010 %
1.
#2675
0.
#2680
b00000011 %
1.
#2685
0.
#2690
b00000100 %
0-
1.
#2695
0.
#2700
b00000101 %
1.
#2705
0.
#2710
b00000110 %
1.
#2715
0.
#2720
b00000111 %
b00000000 &
1.
#2725
0.
#2730
b00000000 %
b00000001 &
1-
1.
#2735
0.
#2740
b00000001 %
1.
#2745
0.
#2750
b00000010 %
1.
#2755
0.
#2760
b00000011 %
1.
#2765
0.
#2770
b00000100 %
0-
1.
#2775
0.
#2780
b00000101 %
1.
#2785
0.
#2790
b00000110 %
1.
#2795
0.
#2800
b00000111 %
b00000000 &
1.
#2805
0.
#2810
b00000000 %
b00000001 &
1-
1.
#2815
0.
#2820
b00000001 %
1.
#2825
0.
#2830
b00000010 %
1.
#2835
0.
#2840
b00000011 %
1.
#2845
0.
#2850
b00000100 %
0-
1.
#2855
0.
#2860
b00000101 %
1.
#2865
0.
#2870
b00000110 %
1.
#2875
0.
#2880
b00000111 %
b00000000 &
1.
#2885
0.
#2890
b00000000 %
b00000001 &
1-
1.
#2895
0.
#2900
b00000001 %
1.
#2905
0.
#2910
b00000010 %
1.
#2915
0.
#2920
b00000011 %
1.
#2925
0.
#2930
b00000100 %
0-
1.
#2935
0.
#2940
b00000101 %
1.
#2945
0.
#2950
b00000110 %
1.
#2955
0.
#2960
b00000111 %
b00000000 &
1.
#2965
0.
#2970
b00000000 %
b00000001 &
1-
1.
#2975
0.
#2980
b00000001 %
1.
#2985
0.
#2990
b00000010 %
1.
#2995
0.
#3000
b00000011 %
1.
#3005
0.
#3010
b00000100 %
0-
1.
#3015
0.
#3020
b00000101 %
1.
#3025
0.
#3030
b00000110 %
1.
#3035
0.
#3040
b00000111 %
b00000000 &
1.
#3045
0.
#3050
b00000000 %
b00000001 &
1-
1.
#3055
0.
#3060
b00000001 %
1.
#3065
0.
#3070
b00000010 %
1.
#3075
0.
#3080
b00000011 %
1.
#3085
0.
#3090
b00000100 %
0-
1.
#3095
0.
#3100
b00000101 %
1.
#3105
0.
#3110
b00000110 %
1.
#3115
0.
#3120
b00000111 %
b00000000 &
1.
#3125
0.
#3130
b00000000 %
b00000001 &
1-
1.
#3135
0.
#3140
b00000001 %
1.
#3145
0.
#3150
b00000010 %
1.
#3155
0.
#3160
b00000011 %
1.
#3165
0.
#3170
b00000100 %
0-
1.
#3175
0.
#3180
b00000101 %
1.
#3185
0.
#3190
b00000110 %
1.
#3195
0.
#3200
b00000111 %
b00000000 &
1.
#3205
0.
#3210
b00000000 %
b00000001 &
1-
1.
#3215
0.
#3220
b00000001 %
1.
#3225
0.
#3230
b00000010 %
1.
#3235
0.
#3240
b00000011 %
1.
#3245
0.
#3250
b00000100 %
0-
1.
#3255
0.
#3260
b00000101 %
1.
#3265
0.
#3270
b00000110 %
1.
#3275
0.
#3280
b00000111 %
b00000000 &
1.
#3285
0.
#3290
b00000000 %
b00000001 &
1-
1.
#3295
0.
#3300
b00000001 %
1.
#3305
0.
#3310
b00000010 %
1.
#3315
0.
#3320
b00000011 %
1.
#3325
0.
#3330
b00000100 %
0-
1.
#3335
0.
#3340
b00000101 %
1.
#3345
0.
#3350
b00000110 %
1.
#3355
0.
#3360
b00000111 %
b00000000 &
1.
#3365
0.
#3370
b00000000 %
b00000001 &
1-
1.
#3375
0.
#3380
b00000001 %
1.
#3385
0.
#3390
b00000010 %
1.
#3395
0.
#3400
b00000011 %
1.
#3405
0.
#3410
b00000100 %
0-
1.
#3415
0.
#3420
b00000101 %
1.
#3425
0.
#3430
b00000110 %
1.
#3435
0.
#3440
b00000111 %
b00000000 &
1.
#3445
0.
#3450
b00000000 %
b00000001 &
1-
1.
#3455
0.
#3460
b00000001 %
1.
#3465
0.
#3470
b00000010 %
1.
#3475
0.
#3480
b00000011 %
1.
#3485
0.
#3490
b00000100 %
0-
1.
#3495
0.
#3500
b00000101 %
1.
#3505
0.
#3510
b00000110 %
1.
#3515
0.
#3520
b00000111 %
b00000000 &
1.
#3525
0.
#3530
b00000000 %
b00000001 &
1-
1.
#3535
0.
#3540
b00000001 %
1.
#3545
0.
#3550
b00000010 %
1.
#3555
0.
#3560
b00000011 %
1.
#3565
0.
#3570
b00000100 %
0-
1.
#3575
0.
#3580
b00000101 %
1.
#3585
0.
#3590
b00000110 %
1.
#3595
0.
#3600
b00000111 %
b00000000 &
1.
#3605
0.
#3610
b00000000 %
b00000001 &
1-
1.
#3615
0.
#3620
b00000001 %
1.
#3625
0.
#3630
b00000010 %
1.
#3635
0.
#3640
b00000011 %
1.
#3645
0.
#3650
b00000100 %
0-
1.
#3655
0.
#3660
b00000101 %
1.
#3665
0.
#3670
b00000110 %
1.
#3675
0.
#3680
b00000111 %
b00000000 &
1.
#3685
0.
#3690
b00000000 %
b00000001 &
1-
1.
#3695
0.
#3700
b00000001 %
1.
#3705
0.
#3710
b00000010 %
1.
#3715
0.
#3720
b00000011 %
1.
#3725
0.
#3730
b00000100 %
0-
1.
#3735
0.
#3740
b00000101 %
1.
#3745
0.
#3750
b00000110 %
1.
#3755
0.
#3760
b00000111 %
b00000000 &
1.
#3765
0.
#3770
b00000000 %
b00000001 &
1-
1.
#3775
0.
#3780
b00000001 %
1.
#3785
0.
#3790
b00000010 %
1.
#3795
0.
#3800
b00000011 %
1.
#3805
0.
#3810
b00000100 %
0-
1.
#3815
0.
#3820
b00000101 %
1.
#3825
0.
#3830
b00000110 %
1.
#3835
0.
#3840
b00000111 %
b00000000 &
1.
#3845
0.
#3850
b00000000 %
b00000001 &
1-
1.
#3855
0.
#3860
b00000001 %
1.
#3865
0.
#3870
b00000010 %
1.
#3875
0.
#3880
b00000011 %
1.
#3885
0.
#3890
b00000100 %
0-
1.
#3895
0.
#3900
b00000101 %
1.
#3905
0.
#3910
b00000110 %
1.
#3915
0.
#3920
b00000111 %
b00000000 &
1.
#3925
0.
#3930
b00000000 %
b00000001 &
1-
1.
#3935
0.
#3940
b00000001 %
1.
#3945
0.
#3950
b00000010 %
1.
#3955
0.
#3960
b00000011 %
1.
#3965
0.
#3970
b00000100 %
0-
1.
#3975
0.
#3980
b00000101 %
1.
#3985
0.
#3990
b00000110 %
1.
#3995
0.
#4000
b00000111 %
b00000000 &
1.
#4005
0.
#4010
b00000000 %
b00000001 &
1-
1.
#4015
0.
#4020
b00000001 %
1.
#4025
0.
#4030
b00000010 %
1.
#4035
0.
#4040
b00000011 %
1.
#4045
0.
#4050
b00000100 %
0-
1.
#4055
0.
#4060
b00000101 %
1.
#4065
0.
#4070
b00000110 %
1.
#4075
0.
#4080
b00000111 %
b00000000 &
1.
#4085
0.
#4090
b00000000 %
b00000001 &
1-
1.
#4095
0.
#4100
b00000001 %
1.
#4105
0.
#4110
b00000010 %
1.
#4115
0.
#4120
b00000011 %
1.
#4125
0.
#4130
b00000100 %
0-
1.
#4135
0.
#4140
b00000101 %
1.
#4145
0.
#4150
b00000110 %
1.
#4155
0.
#4160
b00000111 %
b00000000 &
1.
#4165
0.
#4170
b00000000 %
b00000001 &
1-
1.
#4175
0.
#4180
b00000001 %
1.
#4185
0.
#4190
b00000010 %
1.
#4195
0.
#4200
b00000011 %
1.
#4205
0.
#4210
b00000100 %
0-
1.
#4215
0.
#4220
b00000101 %
1.
#4225
0.
#4230
b00000110 %
1.
#4235
0.
#4240
b00000111 %
b00000000 &
1.
#4245
0.
#4250
b00000000 %
b00000001 &
1-
1.
#4255
0.
#4260
b00000001 %
1.
#4265
0.
#4270
b00000010 %
1.
#4275
0.
#4280
b00000011 %
1.
#4285
0.
#4290
b00000100 %
0-
1.
#4295
0.
#4300
b00000101 %
1.
#4305
0.
#4310
b00000110 %
1.
#4315
0.
#4320
b00000111 %
b00000000 &
1.
#4325
0.
#4330
b00000000 %
b00000001 &
1-
1.
#4335
0.
#4340
b00000001 %
1.
#4345
0.
#4350
b00000010 %
1.
#4355
0.
#4360
b00000011 %
1.
#4365
0.
#4370
b00000100 %
0-
1.
#4375
0.
#4380
b00000101 %
1.
#4385
0.
#4390
b00000110 %
1.
#4395
0.
#4400
b00000111 %
b00000000 &
1.
#4405
0.
#4410
b00000000 %
b00000001 &
1-
1.
#4415
0.
#4420
b00000001 %
1.
#4425
0.
#4430
b00000010 %
1.
#4435
0.
#4440
b00000011 %
1.
#4445
0.
#4450
b00000100 %
0-
1.
#4455
0.
#4460
b00000101 %
1.
#4465
0.
#4470
b00000110 %
1.
#4475
0.
#4480
b00000111 %
b00000000 &
1.
#4485
0.
#4490
b00000000 %
b00000001 &
1-
1.
#4495
0.
#4500
b00000001 %
1.
#4505
0.
#4510
b00000010 %
1.
#4515
0.
#4520
b00000011 %
1.
#4525
0.
#4530
b00000100 %
0-
1.
#4535
0.
#4540
b00000101 %
1.
#4545
0.
#4550
b00000110 %
1.
#4555
0.
#4560
b00000111 %
b00000000 &
1.
#4565
0.
#4570
b00000000 %
b00000001 &
1-
1.
#4575
0.
#4580
b00000001 %
1.
#4585
0.
#4590
b00000010 %
1.
#4595
0.
#4600
b00000011 %
1.
#4605
0.
#4610
b00000100 %
0-
1.
#4615
0.
#4620
b00000101 %
1.
#4625
0.
#4630
b00000110 %
1.
#4635
0.
#4640
b00000111 %
b00000000 &
1.
#4645
0.
#4650
b00000000 %
b00000001 &
1-
1.
#4655
0.
#4660
b00000001 %
1.
#4665
0.
#4670
b00000010 %
1.
#4675
0.
#4680
b00000011 %
1.
#4685
0.
#4690
b00000100 %
0-
1.
#4695
0.
#4700
b00000101 %
1.
#4705
0.
#4710
b00000110 %
1.
#4715
0.
#4720
b00000111 %
b00000000 &
1.
#4725
0.
#4730
b00000000 %
b00000001 &
1-
1.
#4735
0.
#4740
b00000001 %
1.
