Componets/MIPI-CSI-Transciever/Cam_Init/Cam_I2C.v
module Cam_I2C(output valid,input clk400kHz,clk1_6MHz,reset,send_data,r_w,input[7:0] datain,input[15:0] register_in,input[6:0] slave_addr,input ackn,inout scl,inout  sda, output ready);
	localparam reg[7:0] idle=0;
	localparam reg[7:0] start=1;
	localparam reg[7:0] send=2;
	localparam reg[7:0] reg0=3;
	localparam reg[7:0] reg1=4;
	localparam reg[7:0] data=5;
	localparam reg[7:0] stop=6;
	
	reg valid_r;
	reg[7:0] state=idle;
	reg send_data_old=0;
	reg rising_edge=0;
	integer counter =0;
	reg sda0=1;
	assign sda=sda0;
	reg sending=0;
	reg[36:0] i2cdata={slave_addr,1'b0,1'b1,register_in[15:8],1'b1,register_in[7:0],1'b1,datain,1'b1,1'b0};
	reg [36:0] i2cin=0;
	reg ready0;
	assign valid=valid_r;
	always @(posedge clk400kHz) begin
		if (reset==1) begin
			state<=0;		
			sda0<=1;
			counter=0;
			valid_r=0;			
		end else begin
			//sda=1;
			send_data_old<=send_data;
			rising_edge=(send_data==1&&send_data_old==0)?1:0;			
			case (state)
				idle: begin
					valid_r=0;
					ready0<=1;
					sda0<=1;
					sending=0;
					if(rising_edge==1) begin
						state<=start;
						ready0<=0;
						counter=0;
						sda0<=0;
						//sending=1;
					end
				end	
				start: begin
					sending=(counter>=36)?0:1;
					sda0<=(counter>=36)?0:i2cdata[36-counter];				
					counter=(counter>=36)?0:counter+1;
					state<=(counter>=36)?stop:start;		
					
				end
				stop: begin					
					state<=idle;
					sda0<=0;
					if(i2cin[1]==0&&i2cin[10]==0&&i2cin[19]==0&&i2cin[28]==0)begin
						valid_r=1;
					end
				end
				default: begin
				end
			endcase
		end
	end
	reg [7:0]clkcount=0;
	reg clkdelay0;
	reg clkdelay1;	
	reg scl0,scl1,scl2;	
	assign scl=sending?~clk400kHz:1;
	assign ready=ready0;
	always @(posedge clk1_6MHz) begin
		clkcount=clkcount+1;			
		//scl0<=;
		//scl1<=scl0;
		//scl2<=scl1;		
	end
	//ODDRX2F ddr1(.D0(0),.D1(1),.D2(1),.D3(0),.ECLK(clk400kHz),.SCLK(clk200kHz),.Q(scl));
	
	
endmodule

Componets/MIPI-CSI-Transciever/Cam_Init/Cam_Init.v
module Cam_Init(input clk25,input clk400,input clk1_6,input reset,input init,inout sda,scl,output cam_ready);	
	reg send_data,cam_ready_r,ready,ready_old,cam_ready0;
	reg[7:0] datain,slave_addr,state;
	reg[15:0] register_in;
	reg initia=1;
	reg init_old=0;
	integer counter;
	
	
	Cam_I2C cam0 (.clk400kHz(clk400),.scl(scl),.sda(sda),.clk1_6MHz(clk1_6),.reset(reset)
			,.send_data(send_data),.datain(datain),.register_in(register_in),.slave_addr(slave_addr),.ackn(1'b0),.ready(ready));
	localparam reg[7:0] idle=0;
	localparam reg[7:0] init_s=1;
	localparam reg[7:0] wakeup=2;
	
	assign cam_ready=cam_ready0;
	integer dataint=7;
	
	reg[23:0] data_init [0:55];
	initial $readmemh("initdata.mem",data_init);
		/*	{8'h00,8'h05,8'h0c,8'hff,8'hff,
			 8'h05,8'h09,8'h01,8'h00,
			 8'h18,8'h00,8'h0d,8'h78,
			 8'h03,8'he8,8'h08,8'he7,
			 8'h02,8'hf0,8'h06,8'haf,
			 8'h02,8'h80,8'h01,8'he0,
			 8'h01,8'h01,8'h03,8'h03,
			 8'h05,8'h01,8'h03,8'h03,
			 8'h00,8'h39,8'h01,8'h00,
			 8'h72,8'h06,8'h68,8'h04,
			 8'hd0,8'h00,8'h4b,8'h0f,
			 8'h14,8'h00,8'h14,8'h30,
			 8'h10,8'h10,8'h10,8'h0e,
			 8'h0e,8'h01};*/
	reg[15:0] reg_init[0:58];
	initial $readmemh("initreg.mem",reg_init);
	/*   {16'h0100,16'h30eb,16'h30eb,16'h300a,
	   	16'h300b,16'h30eb,16'h30eb,16'h0114,
	   	16'h0128,16'h012a,16'h012b,16'h0164,
	   	16'h0165,16'h0166,16'h0167,16'h0168,
	   	16'h0169,16'h016a,16'h016b,16'h016c,
	   	16'h016d,16'h016e,16'h016f,16'h0170,
	   	16'h0171,16'h0174,16'h0175,16'h0301,
	   	16'h0303,16'h0304,16'h0305,16'h0306,
	   	16'h0307,16'h030b,16'h030c,16'h030d,
	   	16'h0624,16'h0625,16'h0626,16'h0627,
	   	16'h455e,16'h471e,16'h4767,16'h4750,
	   	16'h4540,16'h47b4,16'h4713,16'h478b,
	   	16'h478f,16'h4793,16'h4797,16'h479b,
		16'h0162,16'h0163,16'h0100};*/
			
	
	always @(posedge clk400) begin
		if(reset==1) begin
			state<=idle;
			send_data<=0;
			cam_ready0<=0;
			init_old<=0;
			initia<=1;
		end else begin
			init_old<=init;
			ready_old<=ready;
			case (state)
				idle: begin
					state<=(init_old==0&&init==1)?init_s:idle;
					counter<=0;
				end
				init_s:begin
					send_data<=0;
					if((ready==1&&ready_old==0)||initia)begin
						initia<=0;
						counter<=counter+1;						
						send_data<=1;
						slave_addr<=16;	
						//datain<='hff;
						//register_in<='hffff;
						datain<=data_init[counter][7:0];
						register_in<=data_init[counter][23:8];
					end					
					state<=(counter>54)?idle:init_s;
					//cam_ready0<=(counter>53)?1:0;
				end
				wakeup:begin
					send_data<=0;
					if(counter>60) begin
					state<=idle;
					send_data<=1;
					slave_addr<=16;	
					counter<=0;
					datain<=data_init[55];
					register_in<=reg_init[55];
					end;
					counter<=counter+1;
				end
				default: begin
				end
				endcase
		end
	end
	
	
endmodule

Componets/MIPI-CSI-Transciever/Cam_Init/blinky.vcd
$version Generated by VerilatedVcd $end
$date Tue Dec  6 20:51:29 2022
 $end
$timescale   1ps $end

 $scope module TOP $end
  $var wire  1 ? cam_ready $end
  $var wire  1 : clk1_6 $end
  $var wire  1 8 clk25 $end
  $var wire  1 9 clk400 $end
  $var wire  1 < init $end
  $var wire  1 ; reset $end
  $var wire  1 > scl $end
  $var wire  1 = sda $end
  $scope module Cam_Init $end
   $var wire  1 ? cam_ready $end
   $var wire  1 & cam_ready0 $end
   $var wire  1 A cam_ready_r $end
   $var wire  1 : clk1_6 $end
   $var wire  1 8 clk25 $end
   $var wire  1 9 clk400 $end
   $var wire 32 - counter [31:0] $end
   $var wire  8 ' datain [7:0] $end
   $var wire 32 E dataint [31:0] $end
   $var wire  8 B idle [7:0] $end
   $var wire  1 < init $end
   $var wire  1 , init_old $end
   $var wire  8 C init_s [7:0] $end
   $var wire  1 + initia $end
   $var wire  1 $ ready $end
   $var wire  1 % ready_old $end
   $var wire 16 * register_in [15:0] $end
   $var wire  1 ; reset $end
   $var wire  1 > scl $end
   $var wire  1 = sda $end
   $var wire  1 # send_data $end
   $var wire  8 ( slave_addr [7:0] $end
   $var wire  8 ) state [7:0] $end
   $var wire  8 D wakeup [7:0] $end
   $scope module cam0 $end
    $var wire  1 G ackn $end
    $var wire  1 : clk1_6MHz $end
    $var wire  1 9 clk400kHz $end
    $var wire  8 @ clkcount [7:0] $end
    $var wire  1 N clkdelay0 $end
    $var wire  1 O clkdelay1 $end
    $var wire 32 3 counter [31:0] $end
    $var wire  8 J data [7:0] $end
    $var wire  8 ' datain [7:0] $end
    $var wire 37 6 i2cdata [36:0] $end
    $var wire 37 L i2cin [36:0] $end
    $var wire  8 B idle [7:0] $end
    $var wire  1 F r_w $end
    $var wire  1 $ ready $end
    $var wire  1 $ ready0 $end
    $var wire  8 H reg0 [7:0] $end
    $var wire  8 I reg1 [7:0] $end
    $var wire 16 * register_in [15:0] $end
    $var wire  1 ; reset $end
    $var wire  1 2 rising_edge $end
    $var wire  1 > scl $end
    $var wire  1 P scl0 $end
    $var wire  1 Q scl1 $end
    $var wire  1 R scl2 $end
    $var wire  1 = sda $end
    $var wire  1 4 sda0 $end
    $var wire  8 D send [7:0] $end
    $var wire  1 # send_data $end
    $var wire  1 1 send_data_old $end
    $var wire  1 5 sending $end
    $var wire  7 / slave_addr [6:0] $end
    $var wire  8 C start [7:0] $end
    $var wire  8 0 state [7:0] $end
    $var wire  8 K stop [7:0] $end
    $var wire  1 . valid $end
    $var wire  1 . valid_r $end
   $upscope $end
  $upscope $end
 $upscope $end
$enddefinitions $end


#10
0#
1$
0%
0&
b00000000 '
b00000000 (
b00000000 )
b0000000000000000 *
1+
0,
b00000000000000000000000000000000 -
0.
b0000000 /
b00000000 0
01
02
b00000000000000000000000000000000 3
14
05
b0000000010000000010000000010000000010 6
08
19
1:
0;
0<
1=
1>
0?
b00000001 @
0A
b00000000 B
b00000001 C
b00000010 D
b00000000000000000000000000000111 E
0F
0G
b00000011 H
b00000100 I
b00000101 J
b00000110 K
b0000000000000000000000000000000000000 L
0N
0O
0P
0Q
0R
#15
0:
#20
1:
b00000010 @
#25
0:
#30
09
1:
b00000011 @
#35
0:
#40
1:
b00000100 @
#45
0:
#50
1%
19
1:
b00000101 @
#55
0:
#60
1:
b00000110 @
#65
0:
#70
09
1:
b00000111 @
#75
0:
#80
1:
b00001000 @
#85
0:
#90
19
1:
b00001001 @
#95
0:
#100
1:
b00001010 @
#105
0:
#110
09
1:
b00001011 @
#115
0:
#120
1:
1<
b00001100 @
#125
0:
#130
b00000001 )
1,
19
1:
b00001101 @
#135
0:
#140
1:
b00001110 @
#145
0:
#150
09
1:
b00001111 @
#155
0:
#160
1:
b00010000 @
#165
0:
#170
1#
b00010000 (
b0000000100000000 *
0+
b00000000000000000000000000000001 -
b0010000 /
b0010000010000000110000000010000000010 6
19
1:
b00010001 @
#175
0:
#180
1:
b00010010 @
#185
0:
#190
09
1:
b00010011 @
#195
0:
#200
1:
b00010100 @
#205
0:
#210
0#
0$
b00000001 0
11
12
04
19
1:
0=
b00010101 @
#215
0:
#220
1:
b00010110 @
#225
0:
#230
09
1:
b00010111 @
#235
0:
#240
1:
b00011000 @
#245
0:
#250
0%
01
02
b00000000000000000000000000000001 3
15
19
1:
0>
b00011001 @
#255
0:
#260
1:
b00011010 @
#265
0:
#270
09
1:
1>
b00011011 @
#275
0:
#280
1:
b00011100 @
#285
0:
#290
b00000000000000000000000000000010 3
19
1:
0>
b00011101 @
#295
0:
#300
1:
b00011110 @
#305
0:
#310
09
1:
1>
b00011111 @
#315
0:
#320
1:
b00100000 @
#325
0:
#330
b00000000000000000000000000000011 3
14
19
1:
1=
0>
b00100001 @
#335
0:
#340
1:
b00100010 @
#345
0:
#350
09
1:
1>
b00100011 @
#355
0:
#360
1:
b00100100 @
#365
0:
#370
b00000000000000000000000000000100 3
04
19
1:
0=
0>
b00100101 @
#375
0:
#380
1:
b00100110 @
#385
0:
#390
09
1:
1>
b00100111 @
#395
0:
#400
1:
b00101000 @
#405
0:
#410
b00000000000000000000000000000101 3
19
1:
0>
b00101001 @
#415
0:
#420
1:
b00101010 @
#425
0:
#430
09
1:
1>
b00101011 @
#435
0:
#440
1:
b00101100 @
#445
0:
#450
b00000000000000000000000000000110 3
19
1:
0>
b00101101 @
#455
0:
#460
1:
b00101110 @
#465
0:
#470
09
1:
1>
b00101111 @
#475
0:
#480
1:
b00110000 @
#485
0:
#490
b00000000000000000000000000000111 3
19
1:
0>
b00110001 @
#495
0:
#500
1:
b00110010 @
#505
0:
#510
09
1:
1>
b00110011 @
#515
0:
#520
1:
b00110100 @
#525
0:
#530
b00000000000000000000000000001000 3
19
1:
0>
b00110101 @
#535
0:
#540
1:
b00110110 @
#545
0:
#550
09
1:
1>
b00110111 @
#555
0:
#560
1:
b00111000 @
#565
0:
#570
b00000000000000000000000000001001 3
14
19
1:
1=
0>
b00111001 @
#575
0:
#580
1:
b00111010 @
#585
0:
#590
09
1:
1>
b00111011 @
#595
0:
#600
1:
b00111100 @
#605
0:
#610
b00000000000000000000000000001010 3
04
19
1:
0=
0>
b00111101 @
#615
0:
#620
1:
b00111110 @
#625
0:
#630
09
1:
1>
b00111111 @
#635
0:
#640
1:
b01000000 @
#645
0:
#650
b00000000000000000000000000001011 3
19
1:
0>
b01000001 @
#655
0:
#660
1:
b01000010 @
#665
0:
#670
09
1:
1>
b01000011 @
#675
0:
#680
1:
b01000100 @
#685
0:
#690
b00000000000000000000000000001100 3
19
1:
0>
b01000101 @
#695
0:
#700
1:
b01000110 @
#705
0:
#710
09
1:
1>
b01000111 @
#715
0:
#720
1:
b01001000 @
#725
0:
#730
b00000000000000000000000000001101 3
19
1:
0>
b01001001 @
#735
0:
#740
1:
b01001010 @
#745
0:
#750
09
1:
1>
b01001011 @
#755
0:
#760
1:
b01001100 @
#765
0:
#770
b00000000000000000000000000001110 3
19
1:
0>
b01001101 @
#775
0:
#780
1:
b01001110 @
#785
0:
#790
09
1:
1>
b01001111 @
#795
0:
#800
1:
b01010000 @
#805
0:
#810
b00000000000000000000000000001111 3
19
1:
0>
b01010001 @
#815
0:
#820
1:
b01010010 @
#825
0:
#830
09
1:
1>
b01010011 @
#835
0:
#840
1:
b01010100 @
#845
0:
#850
b00000000000000000000000000010000 3
19
1:
0>
b01010101 @
#855
0:
#860
1:
b01010110 @
#865
0:
#870
09
1:
1>
b01010111 @
#875
0:
#880
1:
b01011000 @
#885
0:
#890
b00000000000000000000000000010001 3
14
19
1:
1=
0>
b01011001 @
#895
0:
#900
1:
b01011010 @
#905
0:
#910
09
1:
1>
b01011011 @
#915
0:
#920
1:
b01011100 @
#925
0:
#930
b00000000000000000000000000010010 3
19
1:
0>
b01011101 @
#935
0:
#940
1:
b01011110 @
#945
0:
#950
09
1:
1>
b01011111 @
#955
0:
#960
1:
b01100000 @
#965
0:
#970
b00000000000000000000000000010011 3
04
19
1:
0=
0>
b01100001 @
#975
0:
#980
1:
b01100010 @
#985
0:
#990
09
1:
1>
b01100011 @
#995
0:
#1000
1:
b01100100 @
#1005
0:
#1010
b00000000000000000000000000010100 3
19
1:
0>
b01100101 @
#1015
0:
#1020
1:
b01100110 @
#1025
0:
#1030
09
1:
1>
b01100111 @
#1035
0:
#1040
1:
b01101000 @
#1045
0:
#1050
b00000000000000000000000000010101 3
19
1:
0>
b01101001 @
#1055
0:
#1060
1:
b01101010 @
#1065
0:
#1070
09
1:
1>
b01101011 @
#1075
0:
#1080
1:
b01101100 @
#1085
0:
#1090
b00000000000000000000000000010110 3
19
1:
0>
b01101101 @
#1095
0:
#1100
1:
b01101110 @
#1105
0:
#1110
09
1:
1>
b01101111 @
#1115
0:
#1120
1:
b01110000 @
#1125
0:
#1130
b00000000000000000000000000010111 3
19
1:
0>
b01110001 @
#1135
0:
#1140
1:
b01110010 @
#1145
0:
#1150
09
1:
1>
b01110011 @
#1155
0:
#1160
1:
b01110100 @
#1165
0:
#1170
b00000000000000000000000000011000 3
19
1:
0>
b01110101 @
#1175
0:
#1180
1:
b01110110 @
#1185
0:
#1190
09
1:
1>
b01110111 @
#1195
0:
#1200
1:
b01111000 @
#1205
0:
#1210
b00000000000000000000000000011001 3
19
1:
0>
b01111001 @
#1215
0:
#1220
1:
b01111010 @
#1225
0:
#1230
09
1:
1>
b01111011 @
#1235
0:
#1240
1:
b01111100 @
#1245
0:
#1250
b00000000000000000000000000011010 3
19
1:
0>
b01111101 @
#1255
0:
#1260
1:
b01111110 @
#1265
0:
#1270
09
1:
1>
b01111111 @
#1275
0:
#1280
1:
b10000000 @
#1285
0:
#1290
b00000000000000000000000000011011 3
14
19
1:
1=
0>
b10000001 @
#1295
0:
#1300
1:
b10000010 @
#1305
0:
#1310
09
1:
1>
b10000011 @
#1315
0:
#1320
1:
b10000100 @
#1325
0:
#1330
b00000000000000000000000000011100 3
04
19
1:
0=
0>
b10000101 @
#1335
0:
#1340
1:
b10000110 @
#1345
0:
#1350
09
1:
1>
b10000111 @
#1355
0:
#1360
1:
b10001000 @
#1365
0:
#1370
b00000000000000000000000000011101 3
19
1:
0>
b10001001 @
#1375
0:
#1380
1:
b10001010 @
#1385
0:
#1390
09
1:
1>
b10001011 @
#1395
0:
#1400
1:
b10001100 @
#1405
0:
#1410
b00000000000000000000000000011110 3
19
1:
0>
b10001101 @
#1415
0:
#1420
1:
b10001110 @
#1425
0:
#1430
09
1:
1>
b10001111 @
#1435
0:
#1440
1:
b10010000 @
#1445
0:
#1450
b00000000000000000000000000011111 3
19
1:
0>
b10010001 @
#1455
0:
#1460
1:
b10010010 @
#1465
0:
#1470
09
1:
1>
b10010011 @
#1475
0:
#1480
1:
b10010100 @
#1485
0:
#1490
b00000000000000000000000000100000 3
19
1:
0>
b10010101 @
#1495
0:
#1500
1:
b10010110 @
#1505
0:
#1510
09
1:
1>
b10010111 @
#1515
0:
#1520
1:
b10011000 @
#1525
0:
#1530
b00000000000000000000000000100001 3
19
1:
0>
b10011001 @
#1535
0:
#1540
1:
b10011010 @
#1545
0:
#1550
09
1:
1>
b10011011 @
#1555
0:
#1560
1:
b10011100 @
#1565
0:
#1570
b00000000000000000000000000100010 3
19
1:
0>
b10011101 @
#1575
0:
#1580
1:
b10011110 @
#1585
0:
#1590
09
1:
1>
b10011111 @
#1595
0:
#1600
1:
b10100000 @
#1605
0:
#1610
b00000000000000000000000000100011 3
19
1:
0>
b10100001 @
#1615
0:
#1620
1:
b10100010 @
#1625
0:
#1630
09
1:
1>
b10100011 @
#1635
0:
#1640
1:
b10100100 @
#1645
0:
#1650
b00000000000000000000000000100100 3
14
19
1:
1=
0>
b10100101 @
#1655
0:
#1660
1:
b10100110 @
#1665
0:
#1670
09
1:
1>
b10100111 @
#1675
0:
#1680
1:
b10101000 @
#1685
0:
#1690
b00000110 0
b00000000000000000000000000000000 3
04
05
19
1:
0=
b10101001 @
#1695
0:
#1700
1:
b10101010 @
#1705
0:
#1710
09
1:
b10101011 @
#1715
0:
#1720
1:
b10101100 @
#1725
0:
#1730
1.
b00000000 0
19
1:
b10101101 @
#1735
0:
#1740
1:
b10101110 @
#1745
0:
#1750
09
1:
b10101111 @
#1755
0:
#1760
1:
b10110000 @
#1765
0:
#1770
1$
0.
14
19
1:
1=
b10110001 @
#1775
0:
#1780
1:
b10110010 @
#1785
0:
#1790
09
1:
b10110011 @
#1795
0:
#1800
1:
b10110100 @
#1805
0:
#1810
1#
1%
b00000101 '
b0011000011101011 *
b00000000000000000000000000000010 -
b0010000010011000011110101110000010110 6
19
1:
b10110101 @
#1815
0:
#1820
1:
b10110110 @
#1825
0:
#1830
09
1:
b10110111 @
#1835
0:
#1840
1:
b10111000 @
#1845
0:
#1850
0#
0$
b00000001 0
11
12
04
19
1:
0=
b10111001 @
#1855
0:
#1860
1:
b10111010 @
#1865
0:
#1870
09
1:
b10111011 @
#1875
0:
#1880
1:
b10111100 @
#1885
0:
#1890
0%
01
02
b00000000000000000000000000000001 3
15
19
1:
0>
b10111101 @
#1895
0:
#1900
1:
b10111110 @
#1905
0:
#1910
09
1:
1>
b10111111 @
#1915
0:
#1920
1:
b11000000 @
#1925
0:
#1930
b00000000000000000000000000000010 3
19
1:
0>
b11000001 @
#1935
0:
#1940
1:
b11000010 @
#1945
0:
#1950
09
1:
1>
b11000011 @
#1955
0:
#1960
1:
b11000100 @
#1965
0:
#1970
b00000000000000000000000000000011 3
14
19
1:
1=
0>
b11000101 @
#1975
0:
#1980
1:
b11000110 @
#1985
0:
#1990
09
1:
1>
b11000111 @
#1995
0:
#2000
1:
b11001000 @
#2005
0:
#2010
b00000000000000000000000000000100 3
04
19
1:
0=
0>
b11001001 @
#2015
0:
#2020
1:
b11001010 @
#2025
0:
#2030
09
1:
1>
b11001011 @
#2035
0:
#2040
1:
b11001100 @
#2045
0:
#2050
b00000000000000000000000000000101 3
19
1:
0>
b11001101 @
#2055
0:
#2060
1:
b11001110 @
#2065
0:
#2070
09
1:
1>
b11001111 @
#2075
0:
#2080
1:
b11010000 @
#2085
0:
#2090
b00000000000000000000000000000110 3
19
1:
0>
b11010001 @
#2095
0:
#2100
1:
b11010010 @
#2105
0:
#2110
09
1:
1>
b11010011 @
#2115
0:
#2120
1:
b11010100 @
#2125
0:
#2130
b00000000000000000000000000000111 3
19
1:
0>
b11010101 @
#2135
0:
#2140
1:
b11010110 @
#2145
0:
#2150
09
1:
1>
b11010111 @
#2155
0:
#2160
1:
b11011000 @
#2165
0:
#2170
b00000000000000000000000000001000 3
19
1:
0>
b11011001 @
#2175
0:
#2180
1:
b11011010 @
#2185
0:
#2190
09
1:
1>
b11011011 @
#2195
0:
#2200
1:
b11011100 @
#2205
0:
#2210
b00000000000000000000000000001001 3
14
19
1:
1=
0>
b11011101 @
#2215
0:
#2220
1:
b11011110 @
#2225
0:
#2230
09
1:
1>
b11011111 @
#2235
0:
#2240
1:
b11100000 @
#2245
0:
#2250
b00000000000000000000000000001010 3
04
19
1:
0=
0>
b11100001 @
#2255
0:
#2260
1:
b11100010 @
#2265
0:
#2270
09
1:
1>
b11100011 @
#2275
0:
#2280
1:
b11100100 @
#2285
0:
#2290
b00000000000000000000000000001011 3
19
1:
0>
b11100101 @
#2295
0:
#2300
1:
b11100110 @
#2305
0:
#2310
09
1:
1>
b11100111 @
#2315
0:
#2320
1:
b11101000 @
#2325
0:
#2330
b00000000000000000000000000001100 3
14
19
1:
1=
0>
b11101001 @
#2335
0:
#2340
1:
b11101010 @
#2345
0:
#2350
09
1:
1>
b11101011 @
#2355
0:
#2360
1:
b11101100 @
#2365
0:
#2370
b00000000000000000000000000001101 3
19
1:
0>
b11101101 @
#2375
0:
#2380
1:
b11101110 @
#2385
0:
#2390
09
1:
1>
b11101111 @
#2395
0:
#2400
1:
b11110000 @
#2405
0:
#2410
b00000000000000000000000000001110 3
04
19
1:
0=
0>
b11110001 @
#2415
0:
#2420
1:
b11110010 @
#2425
0:
#2430
09
1:
1>
b11110011 @
#2435
0:
#2440
1:
b11110100 @
#2445
0:
#2450
b00000000000000000000000000001111 3
19
1:
0>
b11110101 @
#2455
0:
#2460
1:
b11110110 @
#2465
0:
#2470
09
1:
1>
b11110111 @
#2475
0:
#2480
1:
b11111000 @
#2485
0:
#2490
b00000000000000000000000000010000 3
19
1:
0>
b11111001 @
#2495
0:
#2500
1:
b11111010 @
#2505
0:
#2510
09
1:
1>
b11111011 @
#2515
0:
#2520
1:
b11111100 @
#2525
0:
#2530
b00000000000000000000000000010001 3
19
1:
0>
b11111101 @
#2535
0:
#2540
1:
b11111110 @
#2545
0:
#2550
09
1:
1>
b11111111 @
#2555
0:
#2560
1:
b00000000 @
#2565
0:
#2570
b00000000000000000000000000010010 3
14
19
1:
1=
0>
b00000001 @
#2575
0:
#2580
1:
b00000010 @
#2585
0:
#2590
09
1:
1>
b00000011 @
#2595
0:
#2600
1:
b00000100 @
#2605
0:
#2610
b00000000000000000000000000010011 3
19
1:
0>
b00000101 @
#2615
0:
#2620
1:
b00000110 @
#2625
0:
#2630
09
1:
1>
b00000111 @
#2635
0:
#2640
1:
b00001000 @
#2645
0:
#2650
b00000000000000000000000000010100 3
19
1:
0>
b00001001 @
#2655
0:
#2660
1:
b00001010 @
#2665
0:
#2670
09
1:
1>
b00001011 @
#2675
0:
#2680
1:
b00001100 @
#2685
0:
#2690
b00000000000000000000000000010101 3
19
1:
0>
b00001101 @
#2695
0:
#2700
1:
b00001110 @
#2705
0:
#2710
09
1:
1>
b00001111 @
#2715
0:
#2720
1:
b00010000 @
#2725
0:
#2730
b00000000000000000000000000010110 3
04
19
1:
0=
0>
b00010001 @
#2735
0:
#2740
1:
b00010010 @
#2745
0:
#2750
09
1:
1>
b00010011 @
#2755
0:
#2760
1:
b00010100 @
#2765
0:
#2770
b00000000000000000000000000010111 3
14
19
1:
1=
0>
b00010101 @
#2775
0:
#2780
1:
b00010110 @
#2785
0:
#2790
09
1:
1>
b00010111 @
#2795
0:
#2800
1:
b00011000 @
#2805
0:
#2810
b00000000000000000000000000011000 3
04
19
1:
0=
0>
b00011001 @
#2815
0:
#2820
1:
b00011010 @
#2825
0:
#2830
09
1:
1>
b00011011 @
#2835
0:
#2840
1:
b00011100 @
#2845
0:
#2850
b00000000000000000000000000011001 3
14
19
1:
1=
0>
b00011101 @
#2855
0:
#2860
1:
b00011110 @
#2865
0:
#2870
09
1:
1>
b00011111 @
#2875
0:
#2880
1:
b00100000 @
#2885
0:
#2890
b00000000000000000000000000011010 3
19
1:
0>
b00100001 @
#2895
0:
#2900
1:
b00100010 @
#2905
0:
#2910
09
1:
1>
b00100011 @
#2915
0:
#2920
1:
b00100100 @
#2925
0:
#2930
b00000000000000000000000000011011 3
19
1:
0>
b00100101 @
#2935
0:
#2940
1:
b00100110 @
#2945
0:
#2950
09
1:
1>
b00100111 @
#2955
0:
#2960
1:
b00101000 @
#2965
0:
#2970
b00000000000000000000000000011100 3
04
19
1:
0=
0>
b00101001 @
#2975
0:
#2980
1:
b00101010 @
#2985
0:
#2990
09
1:
1>
b00101011 @
#2995
0:
#3000
1:
b00101100 @
#3005
0:
#3010
b00000000000000000000000000011101 3
19
1:
0>
b00101101 @
#3015
0:
#3020
1:
b00101110 @
#3025
0:
#3030
09
1:
1>
b00101111 @
#3035
0:
#3040
1:
b00110000 @
#3045
0:
#3050
b00000000000000000000000000011110 3
19
1:
0>
b00110001 @
#3055
0:
#3060
1:
b00110010 @
#3065
0:
#3070
09
1:
1>
b00110011 @
#3075
0:
#3080
1:
b00110100 @
#3085
0:
#3090
b00000000000000000000000000011111 3
19
1:
0>
b00110101 @
#3095
0:
#3100
1:
b00110110 @
#3105
0:
#3110
09
1:
1>
b00110111 @
#3115
0:
#3120
1:
b00111000 @
#3125
0:
#3130
b00000000000000000000000000100000 3
19
1:
0>
b00111001 @
#3135
0:
#3140
1:
b00111010 @
#3145
0:
#3150
09
1:
1>
b00111011 @
#3155
0:
#3160
1:
b00111100 @
#3165
0:
#3170
b00000000000000000000000000100001 3
14
19
1:
1=
0>
b00111101 @
#3175
0:
#3180
1:
b00111110 @
#3185
0:
#3190
09
1:
1>
b00111111 @
#3195
0:
#3200
1:
b01000000 @
#3205
0:
#3210
b00000000000000000000000000100010 3
04
19
1:
0=
0>
b01000001 @
#3215
0:
#3220
1:
b01000010 @
#3225
0:
#3230
09
1:
1>
b01000011 @
#3235
0:
#3240
1:
b01000100 @
#3245
0:
#3250
b00000000000000000000000000100011 3
14
19
1:
1=
0>
b01000101 @
#3255
0:
#3260
1:
b01000110 @
#3265
0:
#3270
09
1:
1>
b01000111 @
#3275
0:
#3280
1:
b01001000 @
#3285
0:
#3290
b00000000000000000000000000100100 3
19
1:
0>
b01001001 @
#3295
0:
#3300
1:
b01001010 @
#3305
0:
#3310
09
1:
1>
b01001011 @
#3315
0:
#3320
1:
b01001100 @
#3325
0:
#3330
b00000110 0
b00000000000000000000000000000000 3
04
05
19
1:
0=
b01001101 @
#3335
0:
#3340
1:
b01001110 @
#3345
0:
#3350
09
1:
b01001111 @
#3355
0:
#3360
1:
b01010000 @
#3365
0:
#3370
1.
b00000000 0
19
1:
b01010001 @
#3375
0:
#3380
1:
b01010010 @
#3385
0:
#3390
09
1:
b01010011 @
#3395
0:
#3400
1:
b01010100 @
#3405
0:
#3410
1$
0.
14
19
1:
1=
b01010101 @
#3415
0:
#3420
1:
b01010110 @
#3425
0:
#3430
09
1:
b01010111 @
#3435
0:
#3440
1:
b01011000 @
#3445
0:
#3450
1#
1%
b00001100 '
b00000000000000000000000000000011 -
b0010000010011000011110101110000110010 6
19
1:
b01011001 @
#3455
0:
#3460
1:
b01011010 @
#3465
0:
#3470
09
1:
b01011011 @
#3475
0:
#3480
1:
b01011100 @
#3485
0:
#3490
0#
0$
b00000001 0
11
12
04
19
1:
0=
b01011101 @
#3495
0:
#3500
1:
b01011110 @
#3505
0:
#3510
09
1:
b01011111 @
#3515
0:
#3520
1:
b01100000 @
#3525
0:
#3530
0%
01
02
b00000000000000000000000000000001 3
15
19
1:
0>
b01100001 @
#3535
0:
#3540
1:
b01100010 @
#3545
0:
#3550
09
1:
1>
b01100011 @
#3555
0:
#3560
1:
b01100100 @
#3565
0:
#3570
b00000000000000000000000000000010 3
19
1:
0>
b01100101 @
#3575
0:
#3580
1:
b01100110 @
#3585
0:
#3590
09
1:
1>
b01100111 @
#3595
0:
#3600
1:
b01101000 @
#3605
0:
#3610
b00000000000000000000000000000011 3
14
19
1:
1=
0>
b01101001 @
#3615
0:
#3620
1:
b01101010 @
#3625
0:
#3630
09
1:
1>
b01101011 @
#3635
0:
#3640
1:
b01101100 @
#3645
0:
#3650
b00000000000000000000000000000100 3
04
19
1:
0=
0>
b01101101 @
#3655
0:
#3660
1:
b01101110 @
#3665
0:
#3670
09
1:
1>
b01101111 @
#3675
0:
#3680
1:
b01110000 @
#3685
0:
#3690
b00000000000000000000000000000101 3
19
1:
0>
b01110001 @
#3695
0:
#3700
1:
b01110010 @
#3705
0:
#3710
09
1:
1>
b01110011 @
#3715
0:
#3720
1:
b01110100 @
#3725
0:
#3730
b00000000000000000000000000000110 3
19
1:
0>
b01110101 @
#3735
0:
#3740
1:
b01110110 @
#3745
0:
#3750
09
1:
1>
b01110111 @
#3755
0:
#3760
1:
b01111000 @
#3765
0:
#3770
b00000000000000000000000000000111 3
19
1:
0>
b01111001 @
#3775
0:
#3780
1:
b01111010 @
#3785
0:
#3790
09
1:
1>
b01111011 @
#3795
0:
#3800
1:
b01111100 @
#3805
0:
#3810
b00000000000000000000000000001000 3
19
1:
0>
b01111101 @
#3815
0:
#3820
1:
b01111110 @
#3825
0:
#3830
09
1:
1>
b01111111 @
#3835
0:
#3840
1:
b10000000 @
#3845
0:
#3850
b00000000000000000000000000001001 3
14
19
1:
1=
0>
b10000001 @
#3855
0:
#3860
1:
b10000010 @
#3865
0:
#3870
09
1:
1>
b10000011 @
#3875
0:
#3880
1:
b10000100 @
#3885
0:
#3890
b00000000000000000000000000001010 3
04
19
1:
0=
0>
b10000101 @
#3895
0:
#3900
1:
b10000110 @
#3905
0:
#3910
09
1:
1>
b10000111 @
#3915
0:
