Componets/MIPI-CSI-Transciever/MIPI_Reciever/Cam_I2C.v
module Cam_I2C(output valid,input clk400kHz,reset,send_data,r_w,input[7:0] datain,input[15:0] register_in,input[6:0] slave_addr,input ackn,inout scl,inout  sda, output ready);
	localparam reg[7:0] idle=0;
	localparam reg[7:0] start=1;
	localparam reg[7:0] send=2;
	localparam reg[7:0] reg0=3;
	localparam reg[7:0] reg1=4;
	localparam reg[7:0] data=5;
	localparam reg[7:0] stop=6;
	
	reg valid_r;
	reg[7:0] state=idle;
	reg send_data_old=0;
	reg rising_edge=0;
	integer counter =0;
	reg sda0=1;
	assign sda=sda0;
	reg sending=0;
	reg[36:0] i2cdata={slave_addr,1'b0,1'b1,register_in[15:8],1'b1,register_in[7:0],1'b1,datain,1'b1,1'b0};
	reg [36:0] i2cin=0;
	reg ready0;
	assign valid=valid_r;
	always @(posedge clk400kHz) begin
		if (reset==1) begin
			state<=0;		
			sda0<=1;
			counter=0;
			valid_r=0;			
		end else begin
			//sda=1;
			send_data_old<=send_data;
			rising_edge=(send_data==1&&send_data_old==0)?1:0;			
			case (state)
				idle: begin
					valid_r=0;
					ready0<=1;
					sda0<=1;
					sending=0;
					if(rising_edge==1) begin
						state<=start;
						ready0<=0;
						counter=0;
						sda0<=0;
						//sending=1;
					end
				end	
				start: begin
					sending=(counter>=36)?0:1;
					sda0<=(counter>=36)?0:i2cdata[36-counter];				
					counter=(counter>=36)?0:counter+1;
					state<=(counter>=36)?stop:start;		
					
				end
				stop: begin					
					state<=idle;
					sda0<=0;
					if(i2cin[1]==0&&i2cin[10]==0&&i2cin[19]==0&&i2cin[28]==0)begin
						valid_r=1;
					end
				end
				default: begin
				end
			endcase
		end
	end
	reg [7:0]clkcount=0;
	reg clkdelay0;
	reg clkdelay1;	
	reg scl0,scl1,scl2;	
	assign scl=sending?~clk400kHz:1;
	assign ready=ready0;
	
endmodule

Componets/MIPI-CSI-Transciever/MIPI_Reciever/Cam_Init.v
module Cam_Init(input clk400,input reset,input init,inout sda,scl,output cam_ready);	
	reg send_data,cam_ready_r,ready,ready_old,cam_ready0;
	reg[7:0] datain,slave_addr,state;
	reg[15:0] register_in;
	reg initia=1;
	reg init_old=0;
	integer counter;
	
	
	Cam_I2C cam0 (.clk400kHz(clk400),.scl(scl),.sda(sda),.reset(reset)
			,.send_data(send_data),.datain(datain),.register_in(register_in),.slave_addr(slave_addr),.ackn(1'b0),.ready(ready));
	localparam reg[7:0] idle=0;
	localparam reg[7:0] init_s=1;
	localparam reg[7:0] wakeup=2;
	
	assign cam_ready=cam_ready0;
	integer dataint=7;
	
	reg[23:0] data_init [0:55];
	initial $readmemh("initdata2.mem",data_init);	
	always @(posedge clk400) begin
		if(reset==1) begin
			state<=idle;
			send_data<=0;
			cam_ready0<=0;
			init_old<=0;
			initia<=1;
		end else begin
			init_old<=init;
			ready_old<=ready;
			case (state)
				idle: begin
					state<=(init_old==0&&init==1)?init_s:idle;
					counter<=0;
				end
				init_s:begin
					send_data<=0;
					if((ready==1&&ready_old==0)||initia)begin
						initia<=0;
						counter<=counter+1;						
						send_data<=1;
						slave_addr<=16;	
						//datain<='hff;
						//register_in<='hffff;
						datain<=data_init[counter][7:0];
						register_in<=data_init[counter][23:8];
					end					
					state<=(counter>54)?idle:init_s;
					//cam_ready0<=(counter>53)?1:0;
				end
				wakeup:begin
					send_data<=0;
					if(counter>60) begin
					state<=idle;
					send_data<=1;
					slave_addr<=16;	
					counter<=0;
					datain<=data_init[55];
					register_in<=data_init[55];
					end;
					counter<=counter+1;
				end
				default: begin
				end
				endcase
		end
	end
	
	
endmodule

Componets/MIPI-CSI-Transciever/Cam_Init/blinky.vcd
$version Generated by VerilatedVcd $end
$date Wed Dec  7 21:58:00 2022
 $end
$timescale   1ps $end

 $scope module TOP $end
  $var wire  1 = cam_ready $end
  $var wire  1 8 clk400 $end
  $var wire  1 : init $end
  $var wire  1 9 reset $end
  $var wire  1 < scl $end
  $var wire  1 ; sda $end
  $scope module Cam_Init $end
   $var wire  1 = cam_ready $end
   $var wire  1 & cam_ready0 $end
   $var wire  1 > cam_ready_r $end
   $var wire  1 8 clk400 $end
   $var wire 32 - counter [31:0] $end
   $var wire  8 ' datain [7:0] $end
   $var wire 32 B dataint [31:0] $end
   $var wire  8 ? idle [7:0] $end
   $var wire  1 : init $end
   $var wire  1 , init_old $end
   $var wire  8 @ init_s [7:0] $end
   $var wire  1 + initia $end
   $var wire  1 $ ready $end
   $var wire  1 % ready_old $end
   $var wire 16 * register_in [15:0] $end
   $var wire  1 9 reset $end
   $var wire  1 < scl $end
   $var wire  1 ; sda $end
   $var wire  1 # send_data $end
   $var wire  8 ( slave_addr [7:0] $end
   $var wire  8 ) state [7:0] $end
   $var wire  8 A wakeup [7:0] $end
   $scope module cam0 $end
    $var wire  1 D ackn $end
    $var wire  1 8 clk400kHz $end
    $var wire  8 ? clkcount [7:0] $end
    $var wire  1 K clkdelay0 $end
    $var wire  1 L clkdelay1 $end
    $var wire 32 3 counter [31:0] $end
    $var wire  8 G data [7:0] $end
    $var wire  8 ' datain [7:0] $end
    $var wire 37 6 i2cdata [36:0] $end
    $var wire 37 I i2cin [36:0] $end
    $var wire  8 ? idle [7:0] $end
    $var wire  1 C r_w $end
    $var wire  1 $ ready $end
    $var wire  1 $ ready0 $end
    $var wire  8 E reg0 [7:0] $end
    $var wire  8 F reg1 [7:0] $end
    $var wire 16 * register_in [15:0] $end
    $var wire  1 9 reset $end
    $var wire  1 2 rising_edge $end
    $var wire  1 < scl $end
    $var wire  1 M scl0 $end
    $var wire  1 N scl1 $end
    $var wire  1 O scl2 $end
    $var wire  1 ; sda $end
    $var wire  1 4 sda0 $end
    $var wire  8 A send [7:0] $end
    $var wire  1 # send_data $end
    $var wire  1 1 send_data_old $end
    $var wire  1 5 sending $end
    $var wire  7 / slave_addr [6:0] $end
    $var wire  8 @ start [7:0] $end
    $var wire  8 0 state [7:0] $end
    $var wire  8 H stop [7:0] $end
    $var wire  1 . valid $end
    $var wire  1 . valid_r $end
   $upscope $end
  $upscope $end
 $upscope $end
$enddefinitions $end


#10
0#
1$
0%
0&
b00000000 '
b00000000 (
b00000000 )
b0000000000000000 *
1+
0,
b00000000000000000000000000000000 -
0.
b0000000 /
b00000000 0
01
02
b00000000000000000000000000000000 3
14
05
b0000000010000000010000000010000000010 6
18
09
0:
1;
1<
0=
0>
b00000000 ?
b00000001 @
b00000010 A
b00000000000000000000000000000111 B
0C
0D
b00000011 E
b00000100 F
b00000101 G
b00000110 H
b0000000000000000000000000000000000000 I
0K
0L
0M
0N
0O
#15
#20
#25
#30
08
#35
#40
#45
#50
1%
18
#55
#60
#65
#70
08
#75
#80
#85
#90
18
#95
#100
#105
#110
08
#115
#120
1:
#125
#130
b00000001 )
1,
18
#135
#140
#145
#150
08
#155
#160
#165
#170
1#
b00010000 (
b0000000100000000 *
0+
b00000000000000000000000000000001 -
b0010000 /
b0010000010000000110000000010000000010 6
18
#175
#180
#185
#190
08
#195
#200
#205
#210
0#
0$
b00000001 0
11
12
04
18
0;
#215
#220
#225
#230
08
#235
#240
#245
#250
0%
01
02
b00000000000000000000000000000001 3
15
18
0<
#255
#260
#265
#270
08
1<
#275
#280
#285
#290
b00000000000000000000000000000010 3
18
0<
#295
#300
#305
#310
08
1<
#315
#320
#325
#330
b00000000000000000000000000000011 3
14
18
1;
0<
#335
#340
#345
#350
08
1<
#355
#360
#365
#370
b00000000000000000000000000000100 3
04
18
0;
0<
#375
#380
#385
#390
08
1<
#395
#400
#405
#410
b00000000000000000000000000000101 3
18
0<
#415
#420
#425
#430
08
1<
#435
#440
#445
#450
b00000000000000000000000000000110 3
18
0<
#455
#460
#465
#470
08
1<
#475
#480
#485
#490
b00000000000000000000000000000111 3
18
0<
#495
#500
#505
#510
08
1<
#515
#520
#525
#530
b00000000000000000000000000001000 3
18
0<
#535
#540
#545
#550
08
1<
#555
#560
#565
#570
b00000000000000000000000000001001 3
14
18
1;
0<
#575
#580
#585
#590
08
1<
#595
#600
#605
#610
b00000000000000000000000000001010 3
04
18
0;
0<
#615
#620
#625
#630
08
1<
#635
#640
#645
#650
b00000000000000000000000000001011 3
18
0<
#655
#660
#665
#670
08
1<
#675
#680
#685
#690
b00000000000000000000000000001100 3
18
0<
#695
#700
#705
#710
08
1<
#715
#720
#725
#730
b00000000000000000000000000001101 3
18
0<
#735
#740
#745
#750
08
1<
#755
#760
#765
#770
b00000000000000000000000000001110 3
18
0<
#775
#780
#785
#790
08
1<
#795
#800
#805
#810
b00000000000000000000000000001111 3
18
0<
#815
#820
#825
#830
08
1<
#835
#840
#845
#850
b00000000000000000000000000010000 3
18
0<
#855
#860
#865
#870
08
1<
#875
#880
#885
#890
b00000000000000000000000000010001 3
14
18
1;
0<
#895
#900
#905
#910
08
1<
#915
#920
#925
#930
b00000000000000000000000000010010 3
18
0<
#935
#940
#945
#950
08
1<
#955
#960
#965
#970
b00000000000000000000000000010011 3
04
18
0;
0<
#975
#980
#985
#990
08
1<
#995
#1000
#1005
#1010
b00000000000000000000000000010100 3
18
0<
#1015
#1020
#1025
#1030
08
1<
#1035
#1040
#1045
#1050
b00000000000000000000000000010101 3
18
0<
#1055
#1060
#1065
#1070
08
1<
#1075
#1080
#1085
#1090
b00000000000000000000000000010110 3
18
0<
#1095
#1100
#1105
#1110
08
1<
#1115
#1120
#1125
#1130
b00000000000000000000000000010111 3
18
0<
#1135
#1140
#1145
#1150
08
1<
#1155
#1160
#1165
#1170
b00000000000000000000000000011000 3
18
0<
#1175
#1180
#1185
#1190
08
1<
#1195
#1200
#1205
#1210
b00000000000000000000000000011001 3
18
0<
#1215
#1220
#1225
#1230
08
1<
#1235
#1240
#1245
#1250
b00000000000000000000000000011010 3
18
0<
#1255
#1260
#1265
#1270
08
1<
#1275
#1280
#1285
#1290
b00000000000000000000000000011011 3
14
18
1;
0<
#1295
#1300
#1305
#1310
08
1<
#1315
#1320
#1325
#1330
b00000000000000000000000000011100 3
04
18
0;
0<
#1335
#1340
#1345
#1350
08
1<
#1355
#1360
#1365
#1370
b00000000000000000000000000011101 3
18
0<
#1375
#1380
#1385
#1390
08
1<
#1395
#1400
#1405
#1410
b00000000000000000000000000011110 3
18
0<
#1415
#1420
#1425
#1430
08
1<
#1435
#1440
#1445
#1450
b00000000000000000000000000011111 3
18
0<
#1455
#1460
#1465
#1470
08
1<
#1475
#1480
#1485
#1490
b00000000000000000000000000100000 3
18
0<
#1495
#1500
#1505
#1510
08
1<
#1515
#1520
#1525
#1530
b00000000000000000000000000100001 3
18
0<
#1535
#1540
#1545
#1550
08
1<
#1555
#1560
#1565
#1570
b00000000000000000000000000100010 3
18
0<
#1575
#1580
#1585
#1590
08
1<
#1595
#1600
#1605
#1610
b00000000000000000000000000100011 3
18
0<
#1615
#1620
#1625
#1630
08
1<
#1635
#1640
#1645
#1650
b00000000000000000000000000100100 3
14
18
1;
0<
#1655
#1660
#1665
#1670
08
1<
#1675
#1680
#1685
#1690
b00000110 0
b00000000000000000000000000000000 3
04
05
18
0;
#1695
#1700
#1705
#1710
08
#1715
#1720
#1725
#1730
1.
b00000000 0
18
#1735
#1740
#1745
#1750
08
#1755
#1760
#1765
#1770
1$
0.
14
18
1;
#1775
#1780
#1785
#1790
08
#1795
#1800
#1805
#1810
1#
1%
b00000101 '
b0011000011101011 *
b00000000000000000000000000000010 -
b0010000010011000011110101110000010110 6
18
#1815
#1820
#1825
#1830
08
#1835
#1840
#1845
#1850
0#
0$
b00000001 0
11
12
04
18
0;
#1855
#1860
#1865
#1870
08
#1875
#1880
#1885
#1890
0%
01
02
b00000000000000000000000000000001 3
15
18
0<
#1895
#1900
#1905
#1910
08
1<
#1915
#1920
#1925
#1930
b00000000000000000000000000000010 3
18
0<
#1935
#1940
#1945
#1950
08
1<
#1955
#1960
#1965
#1970
b00000000000000000000000000000011 3
14
18
1;
0<
#1975
#1980
#1985
#1990
08
1<
#1995
#2000
#2005
#2010
b00000000000000000000000000000100 3
04
18
0;
0<
#2015
#2020
#2025
#2030
08
1<
#2035
#2040
#2045
#2050
b00000000000000000000000000000101 3
18
0<
#2055
#2060
#2065
#2070
08
1<
#2075
#2080
#2085
#2090
b00000000000000000000000000000110 3
18
0<
#2095
#2100
#2105
#2110
08
1<
#2115
#2120
#2125
#2130
b00000000000000000000000000000111 3
18
0<
#2135
#2140
#2145
#2150
08
1<
#2155
#2160
#2165
#2170
b00000000000000000000000000001000 3
18
0<
#2175
#2180
#2185
#2190
08
1<
#2195
#2200
#2205
#2210
b00000000000000000000000000001001 3
14
18
1;
0<
#2215
#2220
#2225
#2230
08
1<
#2235
#2240
#2245
#2250
b00000000000000000000000000001010 3
04
18
0;
0<
#2255
#2260
#2265
#2270
08
1<
#2275
#2280
#2285
#2290
b00000000000000000000000000001011 3
18
0<
#2295
#2300
#2305
#2310
08
1<
#2315
#2320
#2325
#2330
b00000000000000000000000000001100 3
14
18
1;
0<
#2335
#2340
#2345
#2350
08
1<
#2355
#2360
#2365
#2370
b00000000000000000000000000001101 3
18
0<
#2375
#2380
#2385
#2390
08
1<
#2395
#2400
#2405
#2410
b00000000000000000000000000001110 3
04
18
0;
0<
#2415
#2420
#2425
#2430
08
1<
#2435
#2440
#2445
#2450
b00000000000000000000000000001111 3
18
0<
#2455
#2460
#2465
#2470
08
1<
#2475
#2480
#2485
#2490
b00000000000000000000000000010000 3
18
0<
#2495
#2500
#2505
#2510
08
1<
#2515
#2520
#2525
#2530
b00000000000000000000000000010001 3
18
0<
#2535
#2540
#2545
#2550
08
1<
#2555
#2560
#2565
#2570
b00000000000000000000000000010010 3
14
18
1;
0<
#2575
#2580
#2585
#2590
08
1<
#2595
#2600
#2605
#2610
b00000000000000000000000000010011 3
18
0<
#2615
#2620
#2625
#2630
08
1<
#2635
#2640
#2645
#2650
b00000000000000000000000000010100 3
18
0<
#2655
#2660
#2665
#2670
08
1<
#2675
#2680
#2685
#2690
b00000000000000000000000000010101 3
18
0<
#2695
#2700
#2705
#2710
08
1<
#2715
#2720
#2725
#2730
b00000000000000000000000000010110 3
04
18
0;
0<
#2735
#2740
#2745
#2750
08
1<
#2755
#2760
#2765
#2770
b00000000000000000000000000010111 3
14
18
1;
0<
#2775
#2780
#2785
#2790
08
1<
#2795
#2800
#2805
#2810
b00000000000000000000000000011000 3
04
18
0;
0<
#2815
#2820
#2825
#2830
08
1<
#2835
#2840
#2845
#2850
b00000000000000000000000000011001 3
14
18
1;
0<
#2855
#2860
#2865
#2870
08
1<
#2875
#2880
#2885
#2890
b00000000000000000000000000011010 3
18
0<
#2895
#2900
#2905
#2910
08
1<
#2915
#2920
#2925
#2930
b00000000000000000000000000011011 3
18
0<
#2935
#2940
#2945
#2950
08
1<
#2955
#2960
#2965
#2970
b00000000000000000000000000011100 3
04
18
0;
0<
#2975
#2980
#2985
#2990
08
1<
#2995
#3000
#3005
#3010
b00000000000000000000000000011101 3
18
0<
#3015
#3020
#3025
#3030
08
1<
#3035
#3040
#3045
#3050
b00000000000000000000000000011110 3
18
0<
#3055
#3060
#3065
#3070
08
1<
#3075
#3080
#3085
#3090
b00000000000000000000000000011111 3
18
0<
#3095
#3100
#3105
#3110
08
1<
#3115
#3120
#3125
#3130
b00000000000000000000000000100000 3
18
0<
#3135
#3140
#3145
#3150
08
1<
#3155
#3160
#3165
#3170
b00000000000000000000000000100001 3
14
18
1;
0<
#3175
#3180
#3185
#3190
08
1<
#3195
#3200
#3205
#3210
b00000000000000000000000000100010 3
04
18
0;
0<
#3215
#3220
#3225
#3230
08
1<
#3235
#3240
#3245
#3250
b00000000000000000000000000100011 3
14
18
1;
0<
#3255
#3260
#3265
#3270
08
1<
#3275
#3280
#3285
#3290
b00000000000000000000000000100100 3
18
0<
#3295
#3300
#3305
#3310
08
1<
#3315
#3320
#3325
#3330
b00000110 0
b00000000000000000000000000000000 3
04
05
18
0;
#3335
#3340
#3345
#3350
08
#3355
#3360
#3365
#3370
1.
b00000000 0
18
#3375
#3380
#3385
#3390
08
#3395
#3400
#3405
#3410
1$
0.
14
18
1;
#3415
#3420
#3425
#3430
08
#3435
#3440
#3445
#3450
1#
1%
b00001100 '
b00000000000000000000000000000011 -
b0010000010011000011110101110000110010 6
18
#3455
#3460
#3465
#3470
08
#3475
#3480
#3485
#3490
0#
0$
b00000001 0
11
12
04
18
0;
#3495
#3500
#3505
#3510
08
#3515
#3520
#3525
#3530
0%
01
02
b00000000000000000000000000000001 3
15
18
0<
#3535
#3540
#3545
#3550
08
1<
#3555
#3560
#3565
#3570
b00000000000000000000000000000010 3
18
0<
#3575
#3580
#3585
#3590
08
1<
#3595
#3600
#3605
#3610
b00000000000000000000000000000011 3
14
18
1;
0<
#3615
#3620
#3625
#3630
08
1<
#3635
#3640
#3645
#3650
b00000000000000000000000000000100 3
04
18
0;
0<
#3655
#3660
#3665
#3670
08
1<
#3675
#3680
#3685
#3690
b00000000000000000000000000000101 3
18
0<
#3695
#3700
#3705
#3710
08
1<
#3715
#3720
#3725
#3730
b00000000000000000000000000000110 3
18
0<
#3735
#3740
#3745
#3750
08
1<
#3755
#3760
#3765
#3770
b00000000000000000000000000000111 3
18
0<
#3775
#3780
#3785
#3790
08
1<
#3795
#3800
#3805
#3810
b00000000000000000000000000001000 3
18
0<
#3815
#3820
#3825
#3830
08
1<
#3835
#3840
#3845
#3850
b00000000000000000000000000001001 3
14
18
1;
0<
#3855
#3860
#3865
#3870
08
1<
#3875
#3880
#3885
#3890
b00000000000000000000000000001010 3
04
18
0;
0<
#3895
#3900
#3905
#3910
08
1<
#3915
#3920
#3925
#3930
b00000000000000000000000000001011 3
18
0<
#3935
#3940
#3945
#3950
08
1<
#3955
#3960
#3965
#3970
b00000000000000000000000000001100 3
14
18
1;
0<
#3975
#3980
#3985
#3990
08
1<
#3995
#4000
#4005
#4010
b00000000000000000000000000001101 3
18
0<
#4015
#4020
#4025
#4030
08
1<
#4035
#4040
#4045
#4050
b00000000000000000000000000001110 3
04
18
0;
0<
#4055
#4060
#4065
#4070
08
1<
#4075
#4080
#4085
#4090
b00000000000000000000000000001111 3
18
0<
#4095
#4100
#4105
#4110
08
1<
#4115
#4120
#4125
#4130
b00000000000000000000000000010000 3
18
0<
#4135
#4140
#4145
#4150
08
1<
#4155
#4160
#4165
#4170
b00000000000000000000000000010001 3
18
0<
#4175
#4180
#4185
#4190
08
1<
#4195
#4200
#4205
#4210
b00000000000000000000000000010010 3
14
18
1;
0<
#4215
#4220
#4225
#4230
08
1<
#4235
#4240
#4245
#4250
b00000000000000000000000000010011 3
18
0<
#4255
#4260
#4265
#4270
08
1<
#4275
#4280
#4285
#4290
b00000000000000000000000000010100 3
18
0<
#4295
#4300
#4305
#4310
08
1<
#4315
#4320
#4325
#4330
b00000000000000000000000000010101 3
18
0<
#4335
#4340
#4345
#4350
08
1<
#4355
#4360
#4365
#4370
b00000000000000000000000000010110 3
04
18
0;
0<
#4375
#4380
#4385
#4390
08
1<
#4395
#4400
#4405
#4410
b00000000000000000000000000010111 3
14
18
1;
0<
#4415
#4420
#4425
#4430
08
1<
#4435
#4440
#4445
#4450
b00000000000000000000000000011000 3
04
18
0;
0<
#4455
#4460
#4465
#4470
08
1<
#4475
#4480
#4485
#4490
b00000000000000000000000000011001 3
14
18
1;
0<
#4495
#4500
#4505
#4510
08
1<
#4515
#4520
#4525
#4530
b00000000000000000000000000011010 3
18
0<
#4535
#4540
#4545
#4550
08
1<
#4555
#4560
#4565
#4570
b00000000000000000000000000011011 3
18
0<
#4575
#4580
#4585
#4590
08
1<
#4595
#4600
#4605
#4610
b00000000000000000000000000011100 3
04
18
0;
0<
#4615
#4620
#4625
#4630
08
1<
#4635
#4640
#4645
#4650
b00000000000000000000000000011101 3
18
0<
#4655
#4660
#4665
#4670
08
1<
#4675
#4680
#4685
#4690
b00000000000000000000000000011110 3
18
0<
#4695
#4700
#4705
#4710
08
1<
#4715
#4720
#4725
#4730
b00000000000000000000000000011111 3
18
0<
#4735
#4740
#4745
#4750
08
1<
#4755
#4760
#4765
#4770
b00000000000000000000000000100000 3
14
18
1;
0<
#4775
#4780
#4785
#4790
08
1<
#4795
#4800
#4805
#4810
b00000000000000000000000000100001 3
18
0<
#4815
#4820
#4825
#4830
08
1<
#4835
#4840
#4845
#4850
b00000000000000000000000000100010 3
04
18
0;
0<
#4855
#4860
#4865
#4870
08
1<
#4875
#4880
#4885
#4890
b00000000000000000000000000100011 3
18
0<
#4895
#4900
#4905
#4910
08
1<
#4915
#4920
#4925
#4930
b00000000000000000000000000100100 3
14
18
1;
0<
#4935
#4940
#4945
#4950
08
1<
#4955
#4960
#4965
#4970
b00000110 0
b00000000000000000000000000000000 3
04
05
18
0;
#4975
#4980
#4985
#4990
08
#4995
#5000
#5005
#5010
1.
b00000000 0
18
#5015
#5020
#5025
#5030
08
#5035
#5040
#5045
#5050
1$
0.
14
18
1;
#5055
#5060
#5065
#5070
08
#5075
#5080
#5085
#5090
1#
1%
b11111111 '
b0011000000001010 *
b00000000000000000000000000000100 -
b0010000010011000010000101011111111110 6
18
#5095
#5100
#5105
#5110
08
#5115
#5120
#5125
#5130
0#
0$
b00000001 0
11
12
04
18
0;
#5135
#5140
#5145
#5150
08
#5155
#5160
#5165
#5170
0%
01
02
b00000000000000000000000000000001 3
15
18
0<
#5175
#5180
#5185
#5190
08
1<
#5195
#5200
#5205
#5210
b00000000000000000000000000000010 3
18
0<
#5215
#5220
#5225
#5230
08
1<
#5235
#5240
#5245
#5250
b00000000000000000000000000000011 3
14
18
1;
0<
#5255
#5260
#5265
#5270
08
1<
#5275
#5280
#5285
#5290
b00000000000000000000000000000100 3
04
18
0;
0<
#5295
#5300
#5305
#5310
08
1<
#5315
#5320
#5325
#5330
b00000000000000000000000000000101 3
18
0<
#5335
#5340
#5345
#5350
08
1<
#5355
#5360
#5365
#5370
b00000000000000000000000000000110 3
18
0<
#5375
#5380
#5385
#5390
08
1<
#5395
#5400
#5405
#5410
b00000000000000000000000000000111 3
18
0<
#5415
#5420
#5425
#5430
08
1<
#5435
#5440
#5445
#5450
b00000000000000000000000000001000 3
18
0<
#5455
#5460
#5465
#5470
08
1<
#5475
#5480
#5485
#5490
b00000000000000000000000000001001 3
14
18
1;
0<
#5495
#5500
#5505
#5510
08
1<
#5515
#5520
#5525
#5530
b00000000000000000000000000001010 3
04
18
0;
0<
#5535
#5540
#5545
#5550
08
1<
#5555
#5560
#5565
#5570
b00000000000000000000000000001011 3
18
0<
#5575
#5580
#5585
#5590
08
1<
#5595
#5600
#5605
#5610
b00000000000000000000000000001100 3
14
18
1;
0<
#5615
#5620
#5625
#5630
08
1<
#5635
#5640
#5645
#5650
b00000000000000000000000000001101 3
18
0<
#5655
#5660
#5665
#5670
08
1<
#5675
#5680
#5685
#5690
b00000000000000000000000000001110 3
04
18
0;
0<
#5695
#5700
#5705
#5710
08
1<
#5715
#5720
#5725
#5730
b00000000000000000000000000001111 3
18
0<
#5735
#5740
#5745
#5750
08
1<
#5755
#5760
#5765
#5770
b00000000000000000000000000010000 3
18
0<
#5775
#5780
#5785
#5790
08
1<
#5795
#5800
#5805
#5810
b00000000000000000000000000010001 3
18
0<
#5815
#5820
#5825
#5830
08
1<
#5835
#5840
#5845
#5850
b00000000000000000000000000010010 3
14
18
1;
0<
#5855
#5860
#5865
#5870
08
1<
#5875
#5880
#5885
#5890
b00000000000000000000000000010011 3
04
18
0;
0<
#5895
#5900
#5905
#5910
08
1<
#5915
#5920
#5925
#5930
b00000000000000000000000000010100 3
18
0<
#5935
#5940
#5945
#5950
08
1<
#5955
#5960
#5965
#5970
b00000000000000000000000000010101 3
18
0<
#5975
#5980
#5985
#5990
08
1<
#5995
#6000
#6005
#6010
b00000000000000000000000000010110 3
18
0<
#6015
#6020
#6025
#6030
08
1<
#6035
#6040
#6045
#6050
b00000000000000000000000000010111 3
14
18
1;
0<
#6055
#6060
#6065
#6070
08
1<
#6075
#6080
#6085
#6090
b00000000000000000000000000011000 3
04
18
0;
0<
#6095
#6100
#6105
#6110
08
1<
#6115
#6120
#6125
#6130
b00000000000000000000000000011001 3
14
18
1;
0<
#6135
#6140
#6145
#6150
08
1<
#6155
#6160
#6165
#6170
b00000000000000000000000000011010 3
04
18
0;
0<
#6175
#6180
#6185
#6190
08
1<
#6195
#6200
#6205
#6210
b00000000000000000000000000011011 3
14
18
1;
0<
#6215
#6220
#6225
#6230
08
1<
#6235
#6240
#6245
#6250
b00000000000000000000000000011100 3
18
0<
#6255
#6260
#6265
#6270
08
1<
#6275
#6280
#6285
#6290
b00000000000000000000000000011101 3
18
0<
#6295
#6300
#6305
#6310
08
1<
#6315
#6320
#6325
#6330
b00000000000000000000000000011110 3
18
0<
#6335
#6340
#6345
#6350
08
1<
#6355
#6360
#6365
#6370
b00000000000000000000000000011111 3
18
0<
#6375
#6380
#6385
#6390
08
1<
#6395
#6400
#6405
#6410
b00000000000000000000000000100000 3
18
0<
#6415
#6420
#6425
#6430
08
1<
#6435
#6440
#6445
#6450
b00000000000000000000000000100001 3
18
0<
#6455
#6460
#6465
#6470
08
1<
#6475
#6480
#6485
#6490
b00000000000000000000000000100010 3
18
0<
#6495
#6500
#6505
#6510
08
1<
#6515
#6520
#6525
#6530
b00000000000000000000000000100011 3
18
0<
#6535
#6540
#6545
#6550
08
1<
#6555
#6560
#6565
#6570
b00000000000000000000000000100100 3
18
0<
#6575
#6580
#6585
#6590
08
1<
#6595
#6600
#6605
#6610
b00000110 0
b00000000000000000000000000000000 3
04
05
18
0;
#6615
#6620
#6625
#6630
08
#6635
#6640
#6645
#6650
1.
b00000000 0
18
#6655
#6660
#6665
#6670
08
#6675
#6680
#6685
#6690
1$
0.
14
18
1;
#6695
#6700
#6705
#6710
08
#6715
#6720
#6725
#6730
1#
1%
b0011000000001011 *
b00000000000000000000000000000101 -
b0010000010011000010000101111111111110 6
18
#6735
#6740
#6745
#6750
08
#6755
#6760
#6765
#6770
0#
0$
b00000001 0
11
12
04
18
0;
#6775
#6780
#6785
#6790
08
#6795
#6800
#6805
#6810
0%
01
02
b00000000000000000000000000000001 3
15
18
0<
#6815
#6820
#6825
#6830
08
1<
#6835
#6840
#6845
#6850
b00000000000000000000000000000010 3
18
0<
#6855
#6860
#6865
#6870
08
1<
#6875
#6880
#6885
#6890
b00000000000000000000000000000011 3
14
18
1;
0<
#6895
#6900
#6905
#6910
08
1<
#6915
#6920
#6925
#6930
b00000000000000000000000000000100 3
04
18
0;
0<
#6935
#6940
#6945
#6950
08
1<
#6955
#6960
#6965
#6970
b00000000000000000000000000000101 3
18
0<
#6975
#6980
#6985
#6990
08
1<
#6995
#7000
#7005
#7010
b00000000000000000000000000000110 3
18
0<
#7015
#7020
#7025
#7030
08
1<
#7035
#7040
#7045
#7050
b00000000000000000000000000000111 3
18
0<
#7055
#7060
#7065
#7070
08
1<
#7075
#7080
#7085
#7090
b00000000000000000000000000001000 3
18
0<
#7095
#7100
#7105
#7110
08
1<
#7115
#7120
#7125
#7130
b00000000000000000000000000001001 3
14
18
1;
0<
#7135
#7140
#7145
#7150
08
1<
#7155
#7160
#7165
#7170
b00000000000000000000000000001010 3
04
18
0;
0<
#7175
#7180
#7185
#7190
08
1<
#7195
#7200
#7205
#7210
b00000000000000000000000000001011 3
18
0<
#7215
#7220
#7225
#7230
08
1<
#7235
#7240
#7245
#7250
b00000000000000000000000000001100 3
14
18
1;
0<
#7255
#7260
#7265
#7270
08
1<
#7275
#7280
#7285
#7290
b00000000000000000000000000001101 3
18
0<
#7295
#7300
#7305
#7310
08
1<
#7315
#7320
#7325
#7330
b00000000000000000000000000001110 3
04
18
0;
0<
#7335
#7340
#7345
#7350
08
1<
#7355
#7360
#7365
#7370
b00000000000000000000000000001111 3
18
0<
#7375
#7380
#7385
#7390
08
1<
#7395
#7400
#7405
#7410
b00000000000000000000000000010000 3
18
0<
#7415
#7420
#7425
#7430
08
1<
#7435
#7440
#7445
#7450
b00000000000000000000000000010001 3
18
0<
#7455
#7460
#7465
#7470
08
1<
#7475
#7480
#7485
#7490
b00000000000000000000000000010010 3
14
18
1;
0<
#7495
#7500
#7505
#7510
08
1<
#7515
#7520
#7525
#7530
b00000000000000000000000000010011 3
04
18
0;
0<
#7535
#7540
#7545
#7550
08
1<
#7555
#7560
#7565
#7570
b00000000000000000000000000010100 3
18
0<
#7575
#7580
#7585
#7590
08
1<
#7595
#7600
#7605
#7610
b00000000000000000000000000010101 3
18
0<
#7615
#7620
#7625
#7630
08
1<
#7635
#7640
#7645
#7650
b00000000000000000000000000010110 3
18
0<
#7655
#7660
#7665
#7670
08
1<
#7675
#7680
#7685
#7690
b00000000000000000000000000010111 3
14
18
1;
0<
#7695
#7700
#7705
#7710
08
1<
#7715
#7720
#7725
#7730
b00000000000000000000000000011000 3
04
18
0;
0<
#7735
#7740
#7745
#7750
08
1<
#7755
#7760
#7765
#7770
b00000000000000000000000000011001 3
14
18
1;
0<
#7775
#7780
#7785
#7790
08
1<
#7795
#7800
#7805
#7810
b00000000000000000000000000011010 3
18
0<
#7815
#7820
#7825
#7830
08
1<
#7835
#7840
#7845
#7850
b00000000000000000000000000011011 3
18
0<
#7855
#7860
#7865
#7870
08
1<
#7875
#7880
#7885
#7890
b00000000000000000000000000011100 3
18
0<
#7895
#7900
#7905
#7910
08
1<
#7915
#7920
#7925
#7930
b00000000000000000000000000011101 3
18
0<
#7935
#7940
#7945
#7950
08
1<
#7955
#7960
#7965
#7970
b00000000000000000000000000011110 3
18
0<
#7975
#7980
#7985
#7990
08
1<
#7995
#8000
#8005
#8010
b00000000000000000000000000011111 3
18
0<
#8015
#8020
#8025
#8030
08
1<
#8035
#8040
#8045
